[
    {
        "category": "SCHEMA",
        "question": "Вы профессиональный аналитик статей о туристических достопримечательностях. Я предоставлю вам содержание статьи и тип статьи. Вам нужно выполнить различные стратегии идентификации на основе различных типов статей. Возвращайте только извлеченную информацию об играх, не возвращайте никакой другой избыточной информации.\nТип статьи: Автоидентификация\nПожалуйста, извлекайте информацию согласно следующим правилам:\n1. playName: Название игры, относящееся к конкретным названиям игр или активностей, упомянутых в статье.\n2. briefDesc: Однострочное описание, требуется для обобщения основных моментов и особенностей игры, исключая рабочее время, практическую информацию, негативные описания, 68-100 символов (включая пробелы, цифры...).\n3. location: Географическое расположение игры, относящееся к конкретным ориентирам или достопримечательностям в пределах живописных районов или мест проведения, не может быть городами или провинциями.\n4. startDate/endDate: Временной диапазон игры, формат даты xxxx-xx-xx, возвращать пустую строку, если не идентифицировано.\n5. detailDesc: Подробное введение в игру, требуется 315-400 символов (включая пробелы, цифры...), описывающих основные моменты и особенности игры, исключая слова с точки зрения третьих лиц.\n6. price: Информация о цене билета, формат возврата [\"\",\"\"], возвращать пустой список, если не идентифицировано.\n7. issueTime: Если игра относится к концертам, музыкальным фестивалям, Livehouse, кабаре и другим типам, нужно идентифицировать время выпуска билетов, формат даты xxxx-xx-xx, возвращать пустую строку, если нет.\n8. hasNightView: Является ли это ночной активностью (Да/Нет).\n9. isParentChildFriendly: Подходит ли для родителей с детьми (Да/Нет).\n10. isOutdoor: Является ли это игрой на открытом воздухе (Да/Нет).\n11. hasCulturalShow: Включает ли культурные представления (Да/Нет).\n12. hasHotSpring: Есть ли проекты горячих источников (Да/Нет).\nТребования к выводу:\n1. Использовать формат JSON для возврата извлеченной информации\n2. Каждая игра как объект, содержащий все поля\n3. Все игровые объекты образуют массив\n4. Не возвращать никаких символов, кроме формата JSON\nПример формата вывода:\n[\n  {\"playName\":\"Название игры\",\"briefDesc\":\"Однострочное описание\",\"location\":\"Географическое расположение\",\"startDate\":\"Время начала\",\"endDate\":\"Время окончания\",\"detailDesc\":\"Подробное введение в игру\",\"price\":[],\"issueTime\":\"Время выпуска билетов\",\"hasNightView\":\"Да/Нет\",\"isParentChildFriendly\":\"Да/Нет\",\"isOutdoor\":\"Да/Нет\",\"hasCulturalShow\":\"Да/Нет\",\"hasHotSpring\":\"Да/Нет\"}\n]\nСодержание статьи:Рождественский ночной рынок Института машиностроения и электротехники Санлитунь открыт! Wood Eats Talk Зимний рынок, Ночной парад десертов, Выступление независимого музыкального лейбла, 90 часов непрерывного музыкального опыта, рождественская атмосфера и еда собраны. Есть также зоны взаимодействия родителей и детей и рыночные мастерские.",
        "json_schema": {
            "type": "array",
            "items": {
                "type": "object",
                "properties": {
                    "playName": {
                        "type": "string",
                        "description": "Название игры",
                        "能力项": "JSON"
                    },
                    "briefDesc": {
                        "type": "string",
                        "description": "Однострочное описание",
                        "能力项": "范围、50~200字",
                        "pattern": "^.*$|^$",
                        "minLength": 68,
                        "maxLength": 100
                    },
                    "location": {
                        "type": "string",
                        "description": "Географическое расположение игры",
                        "能力项": "JSON"
                    },
                    "startDate": {
                        "type": "string",
                        "pattern": "^\\d{4}-\\d{2}-\\d{2}$|^$",
                        "能力项": "日期格式",
                        "description": "Время начала"
                    },
                    "endDate": {
                        "type": "string",
                        "pattern": "^\\d{4}-\\d{2}-\\d{2}$|^$",
                        "能力项": "日期格式",
                        "description": "Время окончания"
                    },
                    "detailDesc": {
                        "type": "string",
                        "description": "Подробное введение в игру",
                        "能力项": "范围、200字以上",
                        "pattern": "^.*$|^$",
                        "minLength": 315,
                        "maxLength": 400
                    },
                    "price": {
                        "type": "array",
                        "description": "Информация о цене билета",
                        "items": {
                            "type": "string"
                        },
                        "能力项": "主题约束"
                    },
                    "issueTime": {
                        "type": "string",
                        "pattern": "^\\d{4}-\\d{2}-\\d{2}$|^$",
                        "能力项": "日期格式",
                        "description": "Время выпуска билетов"
                    },
                    "hasNightView": {
                        "type": "string",
                        "enum": [
                            "Да",
                            "Нет"
                        ],
                        "description": "Является ли это ночной активностью",
                        "能力项": "特定格式"
                    },
                    "isParentChildFriendly": {
                        "type": "string",
                        "enum": [
                            "Да",
                            "Нет"
                        ],
                        "description": "Подходит ли для родителей с детьми",
                        "能力项": "特定格式"
                    },
                    "isOutdoor": {
                        "type": "string",
                        "enum": [
                            "Да",
                            "Нет"
                        ],
                        "description": "Является ли это игрой на открытом воздухе",
                        "能力项": "特定格式"
                    },
                    "hasCulturalShow": {
                        "type": "string",
                        "enum": [
                            "Да",
                            "Нет"
                        ],
                        "description": "Включает ли культурные представления",
                        "能力项": "特定格式"
                    },
                    "hasHotSpring": {
                        "type": "string",
                        "enum": [
                            "Да",
                            "Нет"
                        ],
                        "description": "Есть ли проекты горячих источников",
                        "能力项": "特定格式"
                    }
                },
                "required": [
                    "playName",
                    "briefDesc",
                    "location",
                    "startDate",
                    "endDate",
                    "detailDesc",
                    "price",
                    "issueTime",
                    "hasNightView",
                    "isParentChildFriendly",
                    "isOutdoor",
                    "hasCulturalShow",
                    "hasHotSpring"
                ]
            }
        },
        "sub_questions": [
            {
                "point_id": 0,
                "question": "Соответствует ли схеме",
                "rule": "SCHEMA:json_schema",
                "dep": [],
                "被依赖": false,
                "能力项": "JSON"
            }
        ]
    },
    {
        "category": "SCHEMA",
        "question": "Вы профессиональный аналитик статей о туристических достопримечательностях. Я предоставлю вам содержание статьи и тип статьи. Вам нужно выполнить различные стратегии идентификации на основе различных типов статей. Возвращайте только извлеченную информацию об играх, не возвращайте никакой другой избыточной информации.\nТип статьи: Автоидентификация\nПожалуйста, извлекайте информацию согласно следующим правилам:\n1. playName: Название игры, относящееся к конкретным названиям игр или активностей, упомянутых в статье.\n2. briefDesc: Однострочное описание, требуется для обобщения основных моментов и особенностей игры, исключая рабочее время, практическую информацию, негативные описания, 68-100 символов (включая пробелы, цифры...).\n3. location: Географическое расположение игры, относящееся к конкретным ориентирам или достопримечательностям в пределах живописных районов или мест проведения, не может быть городами или провинциями.\n4. startDate/endDate: Временной диапазон игры, формат даты xxxx-xx-xx, возвращать пустую строку, если не идентифицировано.\n5. detailDesc: Подробное введение в игру, требуется 315-400 символов (включая пробелы, цифры...), описывающих основные моменты и особенности игры, исключая слова с точки зрения третьих лиц.\n6. price: Информация о цене билета, формат возврата [\"\",\"\"], возвращать пустой список, если не идентифицировано.\n7. issueTime: Если игра относится к концертам, музыкальным фестивалям, Livehouse, кабаре и другим типам, нужно идентифицировать время выпуска билетов, формат даты xxxx-xx-xx, возвращать пустую строку, если нет.\n8. hasNightView: Является ли это ночной активностью (Да/Нет).\n9. isParentChildFriendly: Подходит ли для родителей с детьми (Да/Нет).\n10. isOutdoor: Является ли это игрой на открытом воздухе (Да/Нет).\n11. hasCulturalShow: Включает ли культурные представления (Да/Нет).\n12. hasHotSpring: Есть ли проекты горячих источников (Да/Нет).\nТребования к выводу:\n1. Использовать формат JSON для возврата извлеченной информации\n2. Каждая игра как объект, содержащий все поля\n3. Все игровые объекты образуют массив\n4. Не возвращать никаких символов, кроме формата JSON\nПример формата вывода:\n[\n  {\"playName\":\"Название игры\",\"briefDesc\":\"Однострочное описание\",\"location\":\"Географическое расположение\",\"startDate\":\"Время начала\",\"endDate\":\"Время окончания\",\"detailDesc\":\"Подробное введение в игру\",\"price\":[],\"issueTime\":\"Время выпуска билетов\",\"hasNightView\":\"Да/Нет\",\"isParentChildFriendly\":\"Да/Нет\",\"isOutdoor\":\"Да/Нет\",\"hasCulturalShow\":\"Да/Нет\",\"hasHotSpring\":\"Да/Нет\"}\n]\nСодержание статьи:Рождественское световое шоу Happy Valley открыто, есть крупномасштабные парадные представления и рождественские тематические рынки ночью, родители и дети, пары, друзья могут веселиться, открытый ночной вид незабываем.",
        "json_schema": {
            "type": "array",
            "items": {
                "type": "object",
                "properties": {
                    "playName": {
                        "type": "string",
                        "description": "Название игры",
                        "能力项": "JSON"
                    },
                    "briefDesc": {
                        "type": "string",
                        "description": "Однострочное описание",
                        "能力项": "范围、50~200字",
                        "pattern": "^.*$|^$",
                        "minLength": 68,
                        "maxLength": 100
                    },
                    "location": {
                        "type": "string",
                        "description": "Географическое расположение игры",
                        "能力项": "JSON"
                    },
                    "startDate": {
                        "type": "string",
                        "pattern": "^\\d{4}-\\d{2}-\\d{2}$|^$",
                        "能力项": "日期格式",
                        "description": "Время начала"
                    },
                    "endDate": {
                        "type": "string",
                        "pattern": "^\\d{4}-\\d{2}-\\d{2}$|^$",
                        "能力项": "日期格式",
                        "description": "Время окончания"
                    },
                    "detailDesc": {
                        "type": "string",
                        "description": "Подробное введение в игру",
                        "能力项": "范围、200字以上",
                        "pattern": "^.*$|^$",
                        "minLength": 315,
                        "maxLength": 400
                    },
                    "price": {
                        "type": "array",
                        "description": "Информация о цене билета",
                        "items": {
                            "type": "string"
                        },
                        "能力项": "主题约束"
                    },
                    "issueTime": {
                        "type": "string",
                        "pattern": "^\\d{4}-\\d{2}-\\d{2}$|^$",
                        "能力项": "日期格式",
                        "description": "Время выпуска билетов"
                    },
                    "hasNightView": {
                        "type": "string",
                        "enum": [
                            "Да",
                            "Нет"
                        ],
                        "description": "Является ли это ночной активностью",
                        "能力项": "特定格式"
                    },
                    "isParentChildFriendly": {
                        "type": "string",
                        "enum": [
                            "Да",
                            "Нет"
                        ],
                        "description": "Подходит ли для родителей с детьми",
                        "能力项": "特定格式"
                    },
                    "isOutdoor": {
                        "type": "string",
                        "enum": [
                            "Да",
                            "Нет"
                        ],
                        "description": "Является ли это игрой на открытом воздухе",
                        "能力项": "特定格式"
                    },
                    "hasCulturalShow": {
                        "type": "string",
                        "enum": [
                            "Да",
                            "Нет"
                        ],
                        "description": "Включает ли культурные представления",
                        "能力项": "特定格式"
                    },
                    "hasHotSpring": {
                        "type": "string",
                        "enum": [
                            "Да",
                            "Нет"
                        ],
                        "description": "Есть ли проекты горячих источников",
                        "能力项": "特定格式"
                    }
                },
                "required": [
                    "playName",
                    "briefDesc",
                    "location",
                    "startDate",
                    "endDate",
                    "detailDesc",
                    "price",
                    "issueTime",
                    "hasNightView",
                    "isParentChildFriendly",
                    "isOutdoor",
                    "hasCulturalShow",
                    "hasHotSpring"
                ]
            }
        },
        "sub_questions": [
            {
                "point_id": 0,
                "question": "Соответствует ли схеме",
                "rule": "SCHEMA:json_schema",
                "dep": [],
                "被依赖": false,
                "能力项": "JSON"
            }
        ]
    },
    {
        "category": "SCHEMA",
        "question": "Вы профессиональный аналитик статей о туристических достопримечательностях. Я предоставлю вам содержание статьи и тип статьи. Вам нужно выполнить различные стратегии идентификации на основе различных типов статей. Возвращайте только извлеченную информацию об играх, не возвращайте никакой другой избыточной информации.\nТип статьи: Автоидентификация\nПожалуйста, извлекайте информацию согласно следующим правилам:\n1. playName: Название игры, относящееся к конкретным названиям игр или активностей, упомянутых в статье.\n2. briefDesc: Однострочное описание, требуется для обобщения основных моментов и особенностей игры, исключая рабочее время, практическую информацию, негативные описания, 68-100 символов (включая пробелы, цифры...).\n3. location: Географическое расположение игры, относящееся к конкретным ориентирам или достопримечательностям в пределах живописных районов или мест проведения, не может быть городами или провинциями.\n4. startDate/endDate: Временной диапазон игры, формат даты xxxx-xx-xx, возвращать пустую строку, если не идентифицировано.\n5. detailDesc: Подробное введение в игру, требуется 315-400 символов (включая пробелы, цифры...), описывающих основные моменты и особенности игры, исключая слова с точки зрения третьих лиц.\n6. price: Информация о цене билета, формат возврата [\"\",\"\"], возвращать пустой список, если не идентифицировано.\n7. issueTime: Если игра относится к концертам, музыкальным фестивалям, Livehouse, кабаре и другим типам, нужно идентифицировать время выпуска билетов, формат даты xxxx-xx-xx, возвращать пустую строку, если нет.\n8. hasNightView: Является ли это ночной активностью (Да/Нет).\n9. isParentChildFriendly: Подходит ли для родителей с детьми (Да/Нет).\n10. isOutdoor: Является ли это игрой на открытом воздухе (Да/Нет).\n11. hasCulturalShow: Включает ли культурные представления (Да/Нет).\n12. hasHotSpring: Есть ли проекты горячих источников (Да/Нет).\nТребования к выводу:\n1. Использовать формат JSON для возврата извлеченной информации\n2. Каждая игра как объект, содержащий все поля\n3. Все игровые объекты образуют массив\n4. Не возвращать никаких символов, кроме формата JSON\nПример формата вывода:\n[\n  {\"playName\":\"Название игры\",\"briefDesc\":\"Однострочное описание\",\"location\":\"Географическое расположение\",\"startDate\":\"Время начала\",\"endDate\":\"Время окончания\",\"detailDesc\":\"Подробное введение в игру\",\"price\":[],\"issueTime\":\"Время выпуска билетов\",\"hasNightView\":\"Да/Нет\",\"isParentChildFriendly\":\"Да/Нет\",\"isOutdoor\":\"Да/Нет\",\"hasCulturalShow\":\"Да/Нет\",\"hasHotSpring\":\"Да/Нет\"}\n]\nСодержание статьи:Фестиваль льда и снега Запретного города открывается, выставки ледяных скульптур, снежные горки, ледяные велосипеды и другие богатые способы игры ждут вас, чтобы испытать, ночное световое шоу романтично и мечтательно. Вся семья может найти веселье.",
        "json_schema": {
            "type": "array",
            "items": {
                "type": "object",
                "properties": {
                    "playName": {
                        "type": "string",
                        "description": "Название игры",
                        "能力项": "JSON"
                    },
                    "briefDesc": {
                        "type": "string",
                        "description": "Однострочное описание",
                        "能力项": "范围、50~200字",
                        "pattern": "^.*$|^$",
                        "minLength": 68,
                        "maxLength": 100
                    },
                    "location": {
                        "type": "string",
                        "description": "Географическое расположение игры",
                        "能力项": "JSON"
                    },
                    "startDate": {
                        "type": "string",
                        "pattern": "^\\d{4}-\\d{2}-\\d{2}$|^$",
                        "能力项": "日期格式",
                        "description": "Время начала"
                    },
                    "endDate": {
                        "type": "string",
                        "pattern": "^\\d{4}-\\d{2}-\\d{2}$|^$",
                        "能力项": "日期格式",
                        "description": "Время окончания"
                    },
                    "detailDesc": {
                        "type": "string",
                        "description": "Подробное введение в игру",
                        "能力项": "范围、200字以上",
                        "pattern": "^.*$|^$",
                        "minLength": 315,
                        "maxLength": 400
                    },
                    "price": {
                        "type": "array",
                        "description": "Информация о цене билета",
                        "items": {
                            "type": "string"
                        },
                        "能力项": "主题约束"
                    },
                    "issueTime": {
                        "type": "string",
                        "pattern": "^\\d{4}-\\d{2}-\\d{2}$|^$",
                        "能力项": "日期格式",
                        "description": "Время выпуска билетов"
                    },
                    "hasNightView": {
                        "type": "string",
                        "enum": [
                            "Да",
                            "Нет"
                        ],
                        "description": "Является ли это ночной активностью",
                        "能力项": "特定格式"
                    },
                    "isParentChildFriendly": {
                        "type": "string",
                        "enum": [
                            "Да",
                            "Нет"
                        ],
                        "description": "Подходит ли для родителей с детьми",
                        "能力项": "特定格式"
                    },
                    "isOutdoor": {
                        "type": "string",
                        "enum": [
                            "Да",
                            "Нет"
                        ],
                        "description": "Является ли это игрой на открытом воздухе",
                        "能力项": "特定格式"
                    },
                    "hasCulturalShow": {
                        "type": "string",
                        "enum": [
                            "Да",
                            "Нет"
                        ],
                        "description": "Включает ли культурные представления",
                        "能力项": "特定格式"
                    },
                    "hasHotSpring": {
                        "type": "string",
                        "enum": [
                            "Да",
                            "Нет"
                        ],
                        "description": "Есть ли проекты горячих источников",
                        "能力项": "特定格式"
                    }
                },
                "required": [
                    "playName",
                    "briefDesc",
                    "location",
                    "startDate",
                    "endDate",
                    "detailDesc",
                    "price",
                    "issueTime",
                    "hasNightView",
                    "isParentChildFriendly",
                    "isOutdoor",
                    "hasCulturalShow",
                    "hasHotSpring"
                ]
            }
        },
        "sub_questions": [
            {
                "point_id": 0,
                "question": "Соответствует ли схеме",
                "rule": "SCHEMA:json_schema",
                "dep": [],
                "被依赖": false,
                "能力项": "JSON"
            }
        ]
    },
    {
        "category": "SCHEMA",
        "question": "Вы профессиональный аналитик статей о туристических достопримечательностях. Я предоставлю вам содержание статьи и тип статьи. Вам нужно выполнить различные стратегии идентификации на основе различных типов статей. Возвращайте только извлеченную информацию об играх, не возвращайте никакой другой избыточной информации.\nТип статьи: Автоидентификация\nПожалуйста, извлекайте информацию согласно следующим правилам:\n1. playName: Название игры, относящееся к конкретным названиям игр или активностей, упомянутых в статье.\n2. briefDesc: Однострочное описание, требуется для обобщения основных моментов и особенностей игры, исключая рабочее время, практическую информацию, негативные описания, 68-100 символов (включая пробелы, цифры...).\n3. location: Географическое расположение игры, относящееся к конкретным ориентирам или достопримечательностям в пределах живописных районов или мест проведения, не может быть городами или провинциями.\n4. startDate/endDate: Временной диапазон игры, формат даты xxxx-xx-xx, возвращать пустую строку, если не идентифицировано.\n5. detailDesc: Подробное введение в игру, требуется 315-400 символов (включая пробелы, цифры...), описывающих основные моменты и особенности игры, исключая слова с точки зрения третьих лиц.\n6. price: Информация о цене билета, формат возврата [\"\",\"\"], возвращать пустой список, если не идентифицировано.\n7. issueTime: Если игра относится к концертам, музыкальным фестивалям, Livehouse, кабаре и другим типам, нужно идентифицировать время выпуска билетов, формат даты xxxx-xx-xx, возвращать пустую строку, если нет.\n8. hasNightView: Является ли это ночной активностью (Да/Нет).\n9. isParentChildFriendly: Подходит ли для родителей с детьми (Да/Нет).\n10. isOutdoor: Является ли это игрой на открытом воздухе (Да/Нет).\n11. hasCulturalShow: Включает ли культурные представления (Да/Нет).\n12. hasHotSpring: Есть ли проекты горячих источников (Да/Нет).\nТребования к выводу:\n1. Использовать формат JSON для возврата извлеченной информации\n2. Каждая игра как объект, содержащий все поля\n3. Все игровые объекты образуют массив\n4. Не возвращать никаких символов, кроме формата JSON\nПример формата вывода:\n[\n  {\"playName\":\"Название игры\",\"briefDesc\":\"Однострочное описание\",\"location\":\"Географическое расположение\",\"startDate\":\"Время начала\",\"endDate\":\"Время окончания\",\"detailDesc\":\"Подробное введение в игру\",\"price\":[],\"issueTime\":\"Время выпуска билетов\",\"hasNightView\":\"Да/Нет\",\"isParentChildFriendly\":\"Да/Нет\",\"isOutdoor\":\"Да/Нет\",\"hasCulturalShow\":\"Да/Нет\",\"hasHotSpring\":\"Да/Нет\"}\n]\nСодержание статьи:Фейерверк-шоу Universal Studios в канун Нового года, лучшая точка обзора - Голливудский бульвар, фейерверки и тематические здания в одном кадре, атмосфера взрывная, подходит для свиданий пар и опыта родителей и детей.",
        "json_schema": {
            "type": "array",
            "items": {
                "type": "object",
                "properties": {
                    "playName": {
                        "type": "string",
                        "description": "Название игры",
                        "能力项": "JSON"
                    },
                    "briefDesc": {
                        "type": "string",
                        "description": "Однострочное описание",
                        "能力项": "范围、50~200字",
                        "pattern": "^.*$|^$",
                        "minLength": 68,
                        "maxLength": 100
                    },
                    "location": {
                        "type": "string",
                        "description": "Географическое расположение игры",
                        "能力项": "JSON"
                    },
                    "startDate": {
                        "type": "string",
                        "pattern": "^\\d{4}-\\d{2}-\\d{2}$|^$",
                        "能力项": "日期格式",
                        "description": "Время начала"
                    },
                    "endDate": {
                        "type": "string",
                        "pattern": "^\\d{4}-\\d{2}-\\d{2}$|^$",
                        "能力项": "日期格式",
                        "description": "Время окончания"
                    },
                    "detailDesc": {
                        "type": "string",
                        "description": "Подробное введение в игру",
                        "能力项": "范围、200字以上",
                        "pattern": "^.*$|^$",
                        "minLength": 315,
                        "maxLength": 400
                    },
                    "price": {
                        "type": "array",
                        "description": "Информация о цене билета",
                        "items": {
                            "type": "string"
                        },
                        "能力项": "主题约束"
                    },
                    "issueTime": {
                        "type": "string",
                        "pattern": "^\\d{4}-\\d{2}-\\d{2}$|^$",
                        "能力项": "日期格式",
                        "description": "Время выпуска билетов"
                    },
                    "hasNightView": {
                        "type": "string",
                        "enum": [
                            "Да",
                            "Нет"
                        ],
                        "description": "Является ли это ночной активностью",
                        "能力项": "特定格式"
                    },
                    "isParentChildFriendly": {
                        "type": "string",
                        "enum": [
                            "Да",
                            "Нет"
                        ],
                        "description": "Подходит ли для родителей с детьми",
                        "能力项": "特定格式"
                    },
                    "isOutdoor": {
                        "type": "string",
                        "enum": [
                            "Да",
                            "Нет"
                        ],
                        "description": "Является ли это игрой на открытом воздухе",
                        "能力项": "特定格式"
                    },
                    "hasCulturalShow": {
                        "type": "string",
                        "enum": [
                            "Да",
                            "Нет"
                        ],
                        "description": "Включает ли культурные представления",
                        "能力项": "特定格式"
                    },
                    "hasHotSpring": {
                        "type": "string",
                        "enum": [
                            "Да",
                            "Нет"
                        ],
                        "description": "Есть ли проекты горячих источников",
                        "能力项": "特定格式"
                    }
                },
                "required": [
                    "playName",
                    "briefDesc",
                    "location",
                    "startDate",
                    "endDate",
                    "detailDesc",
                    "price",
                    "issueTime",
                    "hasNightView",
                    "isParentChildFriendly",
                    "isOutdoor",
                    "hasCulturalShow",
                    "hasHotSpring"
                ]
            }
        },
        "sub_questions": [
            {
                "point_id": 0,
                "question": "Соответствует ли схеме",
                "rule": "SCHEMA:json_schema",
                "dep": [],
                "被依赖": false,
                "能力项": "JSON"
            }
        ]
    },
    {
        "category": "SCHEMA",
        "question": "Вы профессиональный аналитик статей о туристических достопримечательностях. Я предоставлю вам содержание статьи и тип статьи. Вам нужно выполнить различные стратегии идентификации на основе различных типов статей. Возвращайте только извлеченную информацию об играх, не возвращайте никакой другой избыточной информации.\nТип статьи: Автоидентификация\nПожалуйста, извлекайте информацию согласно следующим правилам:\n1. playName: Название игры, относящееся к конкретным названиям игр или активностей, упомянутых в статье.\n2. briefDesc: Однострочное описание, требуется для обобщения основных моментов и особенностей игры, исключая рабочее время, практическую информацию, негативные описания, 68-100 символов (включая пробелы, цифры...).\n3. location: Географическое расположение игры, относящееся к конкретным ориентирам или достопримечательностям в пределах живописных районов или мест проведения, не может быть городами или провинциями.\n4. startDate/endDate: Временной диапазон игры, формат даты xxxx-xx-xx, возвращать пустую строку, если не идентифицировано.\n5. detailDesc: Подробное введение в игру, требуется 315-400 символов (включая пробелы, цифры...), описывающих основные моменты и особенности игры, исключая слова с точки зрения третьих лиц.\n6. price: Информация о цене билета, формат возврата [\"\",\"\"], возвращать пустой список, если не идентифицировано.\n7. issueTime: Если игра относится к концертам, музыкальным фестивалям, Livehouse, кабаре и другим типам, нужно идентифицировать время выпуска билетов, формат даты xxxx-xx-xx, возвращать пустую строку, если нет.\n8. hasNightView: Является ли это ночной активностью (Да/Нет).\n9. isParentChildFriendly: Подходит ли для родителей с детьми (Да/Нет).\n10. isOutdoor: Является ли это игрой на открытом воздухе (Да/Нет).\n11. hasCulturalShow: Включает ли культурные представления (Да/Нет).\n12. hasHotSpring: Есть ли проекты горячих источников (Да/Нет).\nТребования к выводу:\n1. Использовать формат JSON для возврата извлеченной информации\n2. Каждая игра как объект, содержащий все поля\n3. Все игровые объекты образуют массив\n4. Не возвращать никаких символов, кроме формата JSON\nПример формата вывода:\n[\n  {\"playName\":\"Название игры\",\"briefDesc\":\"Однострочное описание\",\"location\":\"Географическое расположение\",\"startDate\":\"Время начала\",\"endDate\":\"Время окончания\",\"detailDesc\":\"Подробное введение в игру\",\"price\":[],\"issueTime\":\"Время выпуска билетов\",\"hasNightView\":\"Да/Нет\",\"isParentChildFriendly\":\"Да/Нет\",\"isOutdoor\":\"Да/Нет\",\"hasCulturalShow\":\"Да/Нет\",\"hasHotSpring\":\"Да/Нет\"}\n]\nСодержание статьи:Фестиваль лодок-драконов Западного озера начинается в День лодок-драконов, гонки лодок-драконов, народные представления, еда фестиваля лодок-драконов - все доступно, опыт просмотра с берега отличный, есть световые и водные шоу ночью.",
        "json_schema": {
            "type": "array",
            "items": {
                "type": "object",
                "properties": {
                    "playName": {
                        "type": "string",
                        "description": "Название игры",
                        "能力项": "JSON"
                    },
                    "briefDesc": {
                        "type": "string",
                        "description": "Однострочное описание",
                        "能力项": "范围、50~200字",
                        "pattern": "^.*$|^$",
                        "minLength": 68,
                        "maxLength": 100
                    },
                    "location": {
                        "type": "string",
                        "description": "Географическое расположение игры",
                        "能力项": "JSON"
                    },
                    "startDate": {
                        "type": "string",
                        "pattern": "^\\d{4}-\\d{2}-\\d{2}$|^$",
                        "能力项": "日期格式",
                        "description": "Время начала"
                    },
                    "endDate": {
                        "type": "string",
                        "pattern": "^\\d{4}-\\d{2}-\\d{2}$|^$",
                        "能力项": "日期格式",
                        "description": "Время окончания"
                    },
                    "detailDesc": {
                        "type": "string",
                        "description": "Подробное введение в игру",
                        "能力项": "范围、200字以上",
                        "pattern": "^.*$|^$",
                        "minLength": 315,
                        "maxLength": 400
                    },
                    "price": {
                        "type": "array",
                        "description": "Информация о цене билета",
                        "items": {
                            "type": "string"
                        },
                        "能力项": "主题约束"
                    },
                    "issueTime": {
                        "type": "string",
                        "pattern": "^\\d{4}-\\d{2}-\\d{2}$|^$",
                        "能力项": "日期格式",
                        "description": "Время выпуска билетов"
                    },
                    "hasNightView": {
                        "type": "string",
                        "enum": [
                            "Да",
                            "Нет"
                        ],
                        "description": "Является ли это ночной активностью",
                        "能力项": "特定格式"
                    },
                    "isParentChildFriendly": {
                        "type": "string",
                        "enum": [
                            "Да",
                            "Нет"
                        ],
                        "description": "Подходит ли для родителей с детьми",
                        "能力项": "特定格式"
                    },
                    "isOutdoor": {
                        "type": "string",
                        "enum": [
                            "Да",
                            "Нет"
                        ],
                        "description": "Является ли это игрой на открытом воздухе",
                        "能力项": "特定格式"
                    },
                    "hasCulturalShow": {
                        "type": "string",
                        "enum": [
                            "Да",
                            "Нет"
                        ],
                        "description": "Включает ли культурные представления",
                        "能力项": "特定格式"
                    },
                    "hasHotSpring": {
                        "type": "string",
                        "enum": [
                            "Да",
                            "Нет"
                        ],
                        "description": "Есть ли проекты горячих источников",
                        "能力项": "特定格式"
                    }
                },
                "required": [
                    "playName",
                    "briefDesc",
                    "location",
                    "startDate",
                    "endDate",
                    "detailDesc",
                    "price",
                    "issueTime",
                    "hasNightView",
                    "isParentChildFriendly",
                    "isOutdoor",
                    "hasCulturalShow",
                    "hasHotSpring"
                ]
            }
        },
        "sub_questions": [
            {
                "point_id": 0,
                "question": "Соответствует ли схеме",
                "rule": "SCHEMA:json_schema",
                "dep": [],
                "被依赖": false,
                "能力项": "JSON"
            }
        ]
    },
    {
        "category": "SCHEMA",
        "question": "Вы профессиональный аналитик статей о туристических достопримечательностях. Я предоставлю вам содержание статьи и тип статьи. Вам нужно выполнить различные стратегии идентификации на основе различных типов статей. Возвращайте только извлеченную информацию об играх, не возвращайте никакой другой избыточной информации.\nТип статьи: Автоидентификация\nПожалуйста, извлекайте информацию согласно следующим правилам:\n1. playName: Название игры, относящееся к конкретным названиям игр или активностей, упомянутых в статье.\n2. briefDesc: Однострочное описание, требуется для обобщения основных моментов и особенностей игры, исключая рабочее время, практическую информацию, негативные описания, 68-100 символов (включая пробелы, цифры...).\n3. location: Географическое расположение игры, относящееся к конкретным ориентирам или достопримечательностям в пределах живописных районов или мест проведения, не может быть городами или провинциями.\n4. startDate/endDate: Временной диапазон игры, формат даты xxxx-xx-xx, возвращать пустую строку, если не идентифицировано.\n5. detailDesc: Подробное введение в игру, требуется 315-400 символов (включая пробелы, цифры...), описывающих основные моменты и особенности игры, исключая слова с точки зрения третьих лиц.\n6. price: Информация о цене билета, формат возврата [\"\",\"\"], возвращать пустой список, если не идентифицировано.\n7. issueTime: Если игра относится к концертам, музыкальным фестивалям, Livehouse, кабаре и другим типам, нужно идентифицировать время выпуска билетов, формат даты xxxx-xx-xx, возвращать пустую строку, если нет.\n8. hasNightView: Является ли это ночной активностью (Да/Нет).\n9. isParentChildFriendly: Подходит ли для родителей с детьми (Да/Нет).\n10. isOutdoor: Является ли это игрой на открытом воздухе (Да/Нет).\n11. hasCulturalShow: Включает ли культурные представления (Да/Нет).\n12. hasHotSpring: Есть ли проекты горячих источников (Да/Нет).\nТребования к выводу:\n1. Использовать формат JSON для возврата извлеченной информации\n2. Каждая игра как объект, содержащий все поля\n3. Все игровые объекты образуют массив\n4. Не возвращать никаких символов, кроме формата JSON\nПример формата вывода:\n[\n  {\"playName\":\"Название игры\",\"briefDesc\":\"Однострочное описание\",\"location\":\"Географическое расположение\",\"startDate\":\"Время начала\",\"endDate\":\"Время окончания\",\"detailDesc\":\"Подробное введение в игру\",\"price\":[],\"issueTime\":\"Время выпуска билетов\",\"hasNightView\":\"Да/Нет\",\"isParentChildFriendly\":\"Да/Нет\",\"isOutdoor\":\"Да/Нет\",\"hasCulturalShow\":\"Да/Нет\",\"hasHotSpring\":\"Да/Нет\"}\n]\nСодержание статьи:Водный парк Chimelong открыт ночью летом. Водная вечеринка и световое и электронное музыкальное шоу заставят все место взволноваться. Ночной туристический опыт уникален и подходит для родителей и детей и молодых людей.",
        "json_schema": {
            "type": "array",
            "items": {
                "type": "object",
                "properties": {
                    "playName": {
                        "type": "string",
                        "description": "Название игры",
                        "能力项": "JSON"
                    },
                    "briefDesc": {
                        "type": "string",
                        "description": "Однострочное описание",
                        "能力项": "范围、50~200字",
                        "pattern": "^.*$|^$",
                        "minLength": 68,
                        "maxLength": 100
                    },
                    "location": {
                        "type": "string",
                        "description": "Географическое расположение игры",
                        "能力项": "JSON"
                    },
                    "startDate": {
                        "type": "string",
                        "pattern": "^\\d{4}-\\d{2}-\\d{2}$|^$",
                        "能力项": "日期格式",
                        "description": "Время начала"
                    },
                    "endDate": {
                        "type": "string",
                        "pattern": "^\\d{4}-\\d{2}-\\d{2}$|^$",
                        "能力项": "日期格式",
                        "description": "Время окончания"
                    },
                    "detailDesc": {
                        "type": "string",
                        "description": "Подробное введение в игру",
                        "能力项": "范围、200字以上",
                        "pattern": "^.*$|^$",
                        "minLength": 315,
                        "maxLength": 400
                    },
                    "price": {
                        "type": "array",
                        "description": "Информация о цене билета",
                        "items": {
                            "type": "string"
                        },
                        "能力项": "主题约束"
                    },
                    "issueTime": {
                        "type": "string",
                        "pattern": "^\\d{4}-\\d{2}-\\d{2}$|^$",
                        "能力项": "日期格式",
                        "description": "Время выпуска билетов"
                    },
                    "hasNightView": {
                        "type": "string",
                        "enum": [
                            "Да",
                            "Нет"
                        ],
                        "description": "Является ли это ночной активностью",
                        "能力项": "特定格式"
                    },
                    "isParentChildFriendly": {
                        "type": "string",
                        "enum": [
                            "Да",
                            "Нет"
                        ],
                        "description": "Подходит ли для родителей с детьми",
                        "能力项": "特定格式"
                    },
                    "isOutdoor": {
                        "type": "string",
                        "enum": [
                            "Да",
                            "Нет"
                        ],
                        "description": "Является ли это игрой на открытом воздухе",
                        "能力项": "特定格式"
                    },
                    "hasCulturalShow": {
                        "type": "string",
                        "enum": [
                            "Да",
                            "Нет"
                        ],
                        "description": "Включает ли культурные представления",
                        "能力项": "特定格式"
                    },
                    "hasHotSpring": {
                        "type": "string",
                        "enum": [
                            "Да",
                            "Нет"
                        ],
                        "description": "Есть ли проекты горячих источников",
                        "能力项": "特定格式"
                    }
                },
                "required": [
                    "playName",
                    "briefDesc",
                    "location",
                    "startDate",
                    "endDate",
                    "detailDesc",
                    "price",
                    "issueTime",
                    "hasNightView",
                    "isParentChildFriendly",
                    "isOutdoor",
                    "hasCulturalShow",
                    "hasHotSpring"
                ]
            }
        },
        "sub_questions": [
            {
                "point_id": 0,
                "question": "Соответствует ли схеме",
                "rule": "SCHEMA:json_schema",
                "dep": [],
                "被依赖": false,
                "能力项": "JSON"
            }
        ]
    },
    {
        "category": "SCHEMA",
        "question": "Вы профессиональный аналитик статей о туристических достопримечательностях. Я предоставлю вам содержание статьи и тип статьи. Вам нужно выполнить различные стратегии идентификации на основе различных типов статей. Возвращайте только извлеченную информацию об играх, не возвращайте никакой другой избыточной информации.\nТип статьи: Автоидентификация\nПожалуйста, извлекайте информацию согласно следующим правилам:\n1. playName: Название игры, относящееся к конкретным названиям игр или активностей, упомянутых в статье.\n2. briefDesc: Однострочное описание, требуется для обобщения основных моментов и особенностей игры, исключая рабочее время, практическую информацию, негативные описания, 68-100 символов (включая пробелы, цифры...).\n3. location: Географическое расположение игры, относящееся к конкретным ориентирам или достопримечательностям в пределах живописных районов или мест проведения, не может быть городами или провинциями.\n4. startDate/endDate: Временной диапазон игры, формат даты xxxx-xx-xx, возвращать пустую строку, если не идентифицировано.\n5. detailDesc: Подробное введение в игру, требуется 315-400 символов (включая пробелы, цифры...), описывающих основные моменты и особенности игры, исключая слова с точки зрения третьих лиц.\n6. price: Информация о цене билета, формат возврата [\"\",\"\"], возвращать пустой список, если не идентифицировано.\n7. issueTime: Если игра относится к концертам, музыкальным фестивалям, Livehouse, кабаре и другим типам, нужно идентифицировать время выпуска билетов, формат даты xxxx-xx-xx, возвращать пустую строку, если нет.\n8. hasNightView: Является ли это ночной активностью (Да/Нет).\n9. isParentChildFriendly: Подходит ли для родителей с детьми (Да/Нет).\n10. isOutdoor: Является ли это игрой на открытом воздухе (Да/Нет).\n11. hasCulturalShow: Включает ли культурные представления (Да/Нет).\n12. hasHotSpring: Есть ли проекты горячих источников (Да/Нет).\nТребования к выводу:\n1. Использовать формат JSON для возврата извлеченной информации\n2. Каждая игра как объект, содержащий все поля\n3. Все игровые объекты образуют массив\n4. Не возвращать никаких символов, кроме формата JSON\nПример формата вывода:\n[\n  {\"playName\":\"Название игры\",\"briefDesc\":\"Однострочное описание\",\"location\":\"Географическое расположение\",\"startDate\":\"Время начала\",\"endDate\":\"Время окончания\",\"detailDesc\":\"Подробное введение в игру\",\"price\":[],\"issueTime\":\"Время выпуска билетов\",\"hasNightView\":\"Да/Нет\",\"isParentChildFriendly\":\"Да/Нет\",\"isOutdoor\":\"Да/Нет\",\"hasCulturalShow\":\"Да/Нет\",\"hasHotSpring\":\"Да/Нет\"}\n]\nСодержание статьи:Рождественский парад Shanghai Disneyland, все члены семьи Микки вышли, церемония зажжения рождественской елки теплая и романтичная. Ночное фейерверк-шоу и световое шоу дополняют друг друга.",
        "json_schema": {
            "type": "array",
            "items": {
                "type": "object",
                "properties": {
                    "playName": {
                        "type": "string",
                        "description": "Название игры",
                        "能力项": "JSON"
                    },
                    "briefDesc": {
                        "type": "string",
                        "description": "Однострочное описание",
                        "能力项": "范围、50~200字",
                        "pattern": "^.*$|^$",
                        "minLength": 68,
                        "maxLength": 100
                    },
                    "location": {
                        "type": "string",
                        "description": "Географическое расположение игры",
                        "能力项": "JSON"
                    },
                    "startDate": {
                        "type": "string",
                        "pattern": "^\\d{4}-\\d{2}-\\d{2}$|^$",
                        "能力项": "日期格式",
                        "description": "Время начала"
                    },
                    "endDate": {
                        "type": "string",
                        "pattern": "^\\d{4}-\\d{2}-\\d{2}$|^$",
                        "能力项": "日期格式",
                        "description": "Время окончания"
                    },
                    "detailDesc": {
                        "type": "string",
                        "description": "Подробное введение в игру",
                        "能力项": "范围、200字以上",
                        "pattern": "^.*$|^$",
                        "minLength": 315,
                        "maxLength": 400
                    },
                    "price": {
                        "type": "array",
                        "description": "Информация о цене билета",
                        "items": {
                            "type": "string"
                        },
                        "能力项": "主题约束"
                    },
                    "issueTime": {
                        "type": "string",
                        "pattern": "^\\d{4}-\\d{2}-\\d{2}$|^$",
                        "能力项": "日期格式",
                        "description": "Время выпуска билетов"
                    },
                    "hasNightView": {
                        "type": "string",
                        "enum": [
                            "Да",
                            "Нет"
                        ],
                        "description": "Является ли это ночной активностью",
                        "能力项": "特定格式"
                    },
                    "isParentChildFriendly": {
                        "type": "string",
                        "enum": [
                            "Да",
                            "Нет"
                        ],
                        "description": "Подходит ли для родителей с детьми",
                        "能力项": "特定格式"
                    },
                    "isOutdoor": {
                        "type": "string",
                        "enum": [
                            "Да",
                            "Нет"
                        ],
                        "description": "Является ли это игрой на открытом воздухе",
                        "能力项": "特定格式"
                    },
                    "hasCulturalShow": {
                        "type": "string",
                        "enum": [
                            "Да",
                            "Нет"
                        ],
                        "description": "Включает ли культурные представления",
                        "能力项": "特定格式"
                    },
                    "hasHotSpring": {
                        "type": "string",
                        "enum": [
                            "Да",
                            "Нет"
                        ],
                        "description": "Есть ли проекты горячих источников",
                        "能力项": "特定格式"
                    }
                },
                "required": [
                    "playName",
                    "briefDesc",
                    "location",
                    "startDate",
                    "endDate",
                    "detailDesc",
                    "price",
                    "issueTime",
                    "hasNightView",
                    "isParentChildFriendly",
                    "isOutdoor",
                    "hasCulturalShow",
                    "hasHotSpring"
                ]
            }
        },
        "sub_questions": [
            {
                "point_id": 0,
                "question": "Соответствует ли схеме",
                "rule": "SCHEMA:json_schema",
                "dep": [],
                "被依赖": false,
                "能力项": "JSON"
            }
        ]
    },
    {
        "category": "SCHEMA",
        "question": "Вы профессиональный аналитик статей о туристических достопримечательностях. Я предоставлю вам содержание статьи и тип статьи. Вам нужно выполнить различные стратегии идентификации на основе различных типов статей. Возвращайте только извлеченную информацию об играх, не возвращайте никакой другой избыточной информации.\nТип статьи: Автоидентификация\nПожалуйста, извлекайте информацию согласно следующим правилам:\n1. playName: Название игры, относящееся к конкретным названиям игр или активностей, упомянутых в статье.\n2. briefDesc: Однострочное описание, требуется для обобщения основных моментов и особенностей игры, исключая рабочее время, практическую информацию, негативные описания, 68-100 символов (включая пробелы, цифры...).\n3. location: Географическое расположение игры, относящееся к конкретным ориентирам или достопримечательностям в пределах живописных районов или мест проведения, не может быть городами или провинциями.\n4. startDate/endDate: Временной диапазон игры, формат даты xxxx-xx-xx, возвращать пустую строку, если не идентифицировано.\n5. detailDesc: Подробное введение в игру, требуется 315-400 символов (включая пробелы, цифры...), описывающих основные моменты и особенности игры, исключая слова с точки зрения третьих лиц.\n6. price: Информация о цене билета, формат возврата [\"\",\"\"], возвращать пустой список, если не идентифицировано.\n7. issueTime: Если игра относится к концертам, музыкальным фестивалям, Livehouse, кабаре и другим типам, нужно идентифицировать время выпуска билетов, формат даты xxxx-xx-xx, возвращать пустую строку, если нет.\n8. hasNightView: Является ли это ночной активностью (Да/Нет).\n9. isParentChildFriendly: Подходит ли для родителей с детьми (Да/Нет).\n10. isOutdoor: Является ли это игрой на открытом воздухе (Да/Нет).\n11. hasCulturalShow: Включает ли культурные представления (Да/Нет).\n12. hasHotSpring: Есть ли проекты горячих источников (Да/Нет).\nТребования к выводу:\n1. Использовать формат JSON для возврата извлеченной информации\n2. Каждая игра как объект, содержащий все поля\n3. Все игровые объекты образуют массив\n4. Не возвращать никаких символов, кроме формата JSON\nПример формата вывода:\n[\n  {\"playName\":\"Название игры\",\"briefDesc\":\"Однострочное описание\",\"location\":\"Географическое расположение\",\"startDate\":\"Время начала\",\"endDate\":\"Время окончания\",\"detailDesc\":\"Подробное введение в игру\",\"price\":[],\"issueTime\":\"Время выпуска билетов\",\"hasNightView\":\"Да/Нет\",\"isParentChildFriendly\":\"Да/Нет\",\"isOutdoor\":\"Да/Нет\",\"hasCulturalShow\":\"Да/Нет\",\"hasHotSpring\":\"Да/Нет\"}\n]\nСодержание статьи:Музыкальный фестиваль ночного рынка Chongqing Hongyadong, независимые группы выступают по очереди, ночной вид на берег реки и музыка идеально интегрированы, родители и дети, пары подходят для ночных регистраций.",
        "json_schema": {
            "type": "array",
            "items": {
                "type": "object",
                "properties": {
                    "playName": {
                        "type": "string",
                        "description": "Название игры",
                        "能力项": "JSON"
                    },
                    "briefDesc": {
                        "type": "string",
                        "description": "Однострочное описание",
                        "能力项": "范围、50~200字",
                        "pattern": "^.*$|^$",
                        "minLength": 68,
                        "maxLength": 100
                    },
                    "location": {
                        "type": "string",
                        "description": "Географическое расположение игры",
                        "能力项": "JSON"
                    },
                    "startDate": {
                        "type": "string",
                        "pattern": "^\\d{4}-\\d{2}-\\d{2}$|^$",
                        "能力项": "日期格式",
                        "description": "Время начала"
                    },
                    "endDate": {
                        "type": "string",
                        "pattern": "^\\d{4}-\\d{2}-\\d{2}$|^$",
                        "能力项": "日期格式",
                        "description": "Время окончания"
                    },
                    "detailDesc": {
                        "type": "string",
                        "description": "Подробное введение в игру",
                        "能力项": "范围、200字以上",
                        "pattern": "^.*$|^$",
                        "minLength": 315,
                        "maxLength": 400
                    },
                    "price": {
                        "type": "array",
                        "description": "Информация о цене билета",
                        "items": {
                            "type": "string"
                        },
                        "能力项": "主题约束"
                    },
                    "issueTime": {
                        "type": "string",
                        "pattern": "^\\d{4}-\\d{2}-\\d{2}$|^$",
                        "能力项": "日期格式",
                        "description": "Время выпуска билетов"
                    },
                    "hasNightView": {
                        "type": "string",
                        "enum": [
                            "Да",
                            "Нет"
                        ],
                        "description": "Является ли это ночной активностью",
                        "能力项": "特定格式"
                    },
                    "isParentChildFriendly": {
                        "type": "string",
                        "enum": [
                            "Да",
                            "Нет"
                        ],
                        "description": "Подходит ли для родителей с детьми",
                        "能力项": "特定格式"
                    },
                    "isOutdoor": {
                        "type": "string",
                        "enum": [
                            "Да",
                            "Нет"
                        ],
                        "description": "Является ли это игрой на открытом воздухе",
                        "能力项": "特定格式"
                    },
                    "hasCulturalShow": {
                        "type": "string",
                        "enum": [
                            "Да",
                            "Нет"
                        ],
                        "description": "Включает ли культурные представления",
                        "能力项": "特定格式"
                    },
                    "hasHotSpring": {
                        "type": "string",
                        "enum": [
                            "Да",
                            "Нет"
                        ],
                        "description": "Есть ли проекты горячих источников",
                        "能力项": "特定格式"
                    }
                },
                "required": [
                    "playName",
                    "briefDesc",
                    "location",
                    "startDate",
                    "endDate",
                    "detailDesc",
                    "price",
                    "issueTime",
                    "hasNightView",
                    "isParentChildFriendly",
                    "isOutdoor",
                    "hasCulturalShow",
                    "hasHotSpring"
                ]
            }
        },
        "sub_questions": [
            {
                "point_id": 0,
                "question": "Соответствует ли схеме",
                "rule": "SCHEMA:json_schema",
                "dep": [],
                "被依赖": false,
                "能力项": "JSON"
            }
        ]
    },
    {
        "category": "SCHEMA",
        "question": "Вы профессиональный аналитик статей о туристических достопримечательностях. Я предоставлю вам содержание статьи и тип статьи. Вам нужно выполнить различные стратегии идентификации на основе различных типов статей. Возвращайте только извлеченную информацию об играх, не возвращайте никакой другой избыточной информации.\nТип статьи: Автоидентификация\nПожалуйста, извлекайте информацию согласно следующим правилам:\n1. playName: Название игры, относящееся к конкретным названиям игр или активностей, упомянутых в статье.\n2. briefDesc: Однострочное описание, требуется для обобщения основных моментов и особенностей игры, исключая рабочее время, практическую информацию, негативные описания, 68-100 символов (включая пробелы, цифры...).\n3. location: Географическое расположение игры, относящееся к конкретным ориентирам или достопримечательностям в пределах живописных районов или мест проведения, не может быть городами или провинциями.\n4. startDate/endDate: Временной диапазон игры, формат даты xxxx-xx-xx, возвращать пустую строку, если не идентифицировано.\n5. detailDesc: Подробное введение в игру, требуется 315-400 символов (включая пробелы, цифры...), описывающих основные моменты и особенности игры, исключая слова с точки зрения третьих лиц.\n6. price: Информация о цене билета, формат возврата [\"\",\"\"], возвращать пустой список, если не идентифицировано.\n7. issueTime: Если игра относится к концертам, музыкальным фестивалям, Livehouse, кабаре и другим типам, нужно идентифицировать время выпуска билетов, формат даты xxxx-xx-xx, возвращать пустую строку, если нет.\n8. hasNightView: Является ли это ночной активностью (Да/Нет).\n9. isParentChildFriendly: Подходит ли для родителей с детьми (Да/Нет).\n10. isOutdoor: Является ли это игрой на открытом воздухе (Да/Нет).\n11. hasCulturalShow: Включает ли культурные представления (Да/Нет).\n12. hasHotSpring: Есть ли проекты горячих источников (Да/Нет).\nТребования к выводу:\n1. Использовать формат JSON для возврата извлеченной информации\n2. Каждая игра как объект, содержащий все поля\n3. Все игровые объекты образуют массив\n4. Не возвращать никаких символов, кроме формата JSON\nПример формата вывода:\n[\n  {\"playName\":\"Название игры\",\"briefDesc\":\"Однострочное описание\",\"location\":\"Географическое расположение\",\"startDate\":\"Время начала\",\"endDate\":\"Время окончания\",\"detailDesc\":\"Подробное введение в игру\",\"price\":[],\"issueTime\":\"Время выпуска билетов\",\"hasNightView\":\"Да/Нет\",\"isParentChildFriendly\":\"Да/Нет\",\"isOutdoor\":\"Да/Нет\",\"hasCulturalShow\":\"Да/Нет\",\"hasHotSpring\":\"Да/Нет\"}\n]\nСодержание статьи:Новогодняя храмовая ярмарка древнего города Дали, танец Бай, народный рынок, фейерверк-шоу освещает ночное небо древнего города, опыт горячих источников и еда ночного рынка богаты и красочны.",
        "json_schema": {
            "type": "array",
            "items": {
                "type": "object",
                "properties": {
                    "playName": {
                        "type": "string",
                        "description": "Название игры",
                        "能力项": "JSON"
                    },
                    "briefDesc": {
                        "type": "string",
                        "description": "Однострочное описание",
                        "能力项": "范围、50~200字",
                        "pattern": "^.*$|^$",
                        "minLength": 68,
                        "maxLength": 100
                    },
                    "location": {
                        "type": "string",
                        "description": "Географическое расположение игры",
                        "能力项": "JSON"
                    },
                    "startDate": {
                        "type": "string",
                        "pattern": "^\\d{4}-\\d{2}-\\d{2}$|^$",
                        "能力项": "日期格式",
                        "description": "Время начала"
                    },
                    "endDate": {
                        "type": "string",
                        "pattern": "^\\d{4}-\\d{2}-\\d{2}$|^$",
                        "能力项": "日期格式",
                        "description": "Время окончания"
                    },
                    "detailDesc": {
                        "type": "string",
                        "description": "Подробное введение в игру",
                        "能力项": "范围、200字以上",
                        "pattern": "^.*$|^$",
                        "minLength": 315,
                        "maxLength": 400
                    },
                    "price": {
                        "type": "array",
                        "description": "Информация о цене билета",
                        "items": {
                            "type": "string"
                        },
                        "能力项": "主题约束"
                    },
                    "issueTime": {
                        "type": "string",
                        "pattern": "^\\d{4}-\\d{2}-\\d{2}$|^$",
                        "能力项": "日期格式",
                        "description": "Время выпуска билетов"
                    },
                    "hasNightView": {
                        "type": "string",
                        "enum": [
                            "Да",
                            "Нет"
                        ],
                        "description": "Является ли это ночной активностью",
                        "能力项": "特定格式"
                    },
                    "isParentChildFriendly": {
                        "type": "string",
                        "enum": [
                            "Да",
                            "Нет"
                        ],
                        "description": "Подходит ли для родителей с детьми",
                        "能力项": "特定格式"
                    },
                    "isOutdoor": {
                        "type": "string",
                        "enum": [
                            "Да",
                            "Нет"
                        ],
                        "description": "Является ли это игрой на открытом воздухе",
                        "能力项": "特定格式"
                    },
                    "hasCulturalShow": {
                        "type": "string",
                        "enum": [
                            "Да",
                            "Нет"
                        ],
                        "description": "Включает ли культурные представления",
                        "能力项": "特定格式"
                    },
                    "hasHotSpring": {
                        "type": "string",
                        "enum": [
                            "Да",
                            "Нет"
                        ],
                        "description": "Есть ли проекты горячих источников",
                        "能力项": "特定格式"
                    }
                },
                "required": [
                    "playName",
                    "briefDesc",
                    "location",
                    "startDate",
                    "endDate",
                    "detailDesc",
                    "price",
                    "issueTime",
                    "hasNightView",
                    "isParentChildFriendly",
                    "isOutdoor",
                    "hasCulturalShow",
                    "hasHotSpring"
                ]
            }
        },
        "sub_questions": [
            {
                "point_id": 0,
                "question": "Соответствует ли схеме",
                "rule": "SCHEMA:json_schema",
                "dep": [],
                "被依赖": false,
                "能力项": "JSON"
            }
        ]
    },
    {
        "category": "SCHEMA",
        "question": "Вы профессиональный аналитик статей о туристических достопримечательностях. Я предоставлю вам содержание статьи и тип статьи. Вам нужно выполнить различные стратегии идентификации на основе различных типов статей. Возвращайте только извлеченную информацию об играх, не возвращайте никакой другой избыточной информации.\nТип статьи: Автоидентификация\nПожалуйста, извлекайте информацию согласно следующим правилам:\n1. playName: Название игры, относящееся к конкретным названиям игр или активностей, упомянутых в статье.\n2. briefDesc: Однострочное описание, требуется для обобщения основных моментов и особенностей игры, исключая рабочее время, практическую информацию, негативные описания, 68-100 символов (включая пробелы, цифры...).\n3. location: Географическое расположение игры, относящееся к конкретным ориентирам или достопримечательностям в пределах живописных районов или мест проведения, не может быть городами или провинциями.\n4. startDate/endDate: Временной диапазон игры, формат даты xxxx-xx-xx, возвращать пустую строку, если не идентифицировано.\n5. detailDesc: Подробное введение в игру, требуется 315-400 символов (включая пробелы, цифры...), описывающих основные моменты и особенности игры, исключая слова с точки зрения третьих лиц.\n6. price: Информация о цене билета, формат возврата [\"\",\"\"], возвращать пустой список, если не идентифицировано.\n7. issueTime: Если игра относится к концертам, музыкальным фестивалям, Livehouse, кабаре и другим типам, нужно идентифицировать время выпуска билетов, формат даты xxxx-xx-xx, возвращать пустую строку, если нет.\n8. hasNightView: Является ли это ночной активностью (Да/Нет).\n9. isParentChildFriendly: Подходит ли для родителей с детьми (Да/Нет).\n10. isOutdoor: Является ли это игрой на открытом воздухе (Да/Нет).\n11. hasCulturalShow: Включает ли культурные представления (Да/Нет).\n12. hasHotSpring: Есть ли проекты горячих источников (Да/Нет).\nТребования к выводу:\n1. Использовать формат JSON для возврата извлеченной информации\n2. Каждая игра как объект, содержащий все поля\n3. Все игровые объекты образуют массив\n4. Не возвращать никаких символов, кроме формата JSON\nПример формата вывода:\n[\n  {\"playName\":\"Название игры\",\"briefDesc\":\"Однострочное описание\",\"location\":\"Географическое расположение\",\"startDate\":\"Время начала\",\"endDate\":\"Время окончания\",\"detailDesc\":\"Подробное введение в игру\",\"price\":[],\"issueTime\":\"Время выпуска билетов\",\"hasNightView\":\"Да/Нет\",\"isParentChildFriendly\":\"Да/Нет\",\"isOutdoor\":\"Да/Нет\",\"hasCulturalShow\":\"Да/Нет\",\"hasHotSpring\":\"Да/Нет\"}\n]\nСодержание статьи:Научный тур для родителей и детей на базе панд Чэнду, объяснение панд, ручной опыт, богатые и красочные тематические сувениры, в парке есть небольшое ночное световое шоу.",
        "json_schema": {
            "type": "array",
            "items": {
                "type": "object",
                "properties": {
                    "playName": {
                        "type": "string",
                        "description": "Название игры",
                        "能力项": "JSON"
                    },
                    "briefDesc": {
                        "type": "string",
                        "description": "Однострочное описание",
                        "能力项": "范围、50~200字",
                        "pattern": "^.*$|^$",
                        "minLength": 68,
                        "maxLength": 100
                    },
                    "location": {
                        "type": "string",
                        "description": "Географическое расположение игры",
                        "能力项": "JSON"
                    },
                    "startDate": {
                        "type": "string",
                        "pattern": "^\\d{4}-\\d{2}-\\d{2}$|^$",
                        "能力项": "日期格式",
                        "description": "Время начала"
                    },
                    "endDate": {
                        "type": "string",
                        "pattern": "^\\d{4}-\\d{2}-\\d{2}$|^$",
                        "能力项": "日期格式",
                        "description": "Время окончания"
                    },
                    "detailDesc": {
                        "type": "string",
                        "description": "Подробное введение в игру",
                        "能力项": "范围、200字以上",
                        "pattern": "^.*$|^$",
                        "minLength": 315,
                        "maxLength": 400
                    },
                    "price": {
                        "type": "array",
                        "description": "Информация о цене билета",
                        "items": {
                            "type": "string"
                        },
                        "能力项": "主题约束"
                    },
                    "issueTime": {
                        "type": "string",
                        "pattern": "^\\d{4}-\\d{2}-\\d{2}$|^$",
                        "能力项": "日期格式",
                        "description": "Время выпуска билетов"
                    },
                    "hasNightView": {
                        "type": "string",
                        "enum": [
                            "Да",
                            "Нет"
                        ],
                        "description": "Является ли это ночной активностью",
                        "能力项": "特定格式"
                    },
                    "isParentChildFriendly": {
                        "type": "string",
                        "enum": [
                            "Да",
                            "Нет"
                        ],
                        "description": "Подходит ли для родителей с детьми",
                        "能力项": "特定格式"
                    },
                    "isOutdoor": {
                        "type": "string",
                        "enum": [
                            "Да",
                            "Нет"
                        ],
                        "description": "Является ли это игрой на открытом воздухе",
                        "能力项": "特定格式"
                    },
                    "hasCulturalShow": {
                        "type": "string",
                        "enum": [
                            "Да",
                            "Нет"
                        ],
                        "description": "Включает ли культурные представления",
                        "能力项": "特定格式"
                    },
                    "hasHotSpring": {
                        "type": "string",
                        "enum": [
                            "Да",
                            "Нет"
                        ],
                        "description": "Есть ли проекты горячих источников",
                        "能力项": "特定格式"
                    }
                },
                "required": [
                    "playName",
                    "briefDesc",
                    "location",
                    "startDate",
                    "endDate",
                    "detailDesc",
                    "price",
                    "issueTime",
                    "hasNightView",
                    "isParentChildFriendly",
                    "isOutdoor",
                    "hasCulturalShow",
                    "hasHotSpring"
                ]
            }
        },
        "sub_questions": [
            {
                "point_id": 0,
                "question": "Соответствует ли схеме",
                "rule": "SCHEMA:json_schema",
                "dep": [],
                "被依赖": false,
                "能力项": "JSON"
            }
        ]
    }
]