[
    {
        "category": "SCHEMA",
        "question": "أنت محلل مقالات مواقع السياحة المحترف. سأقدم لك محتوى المقال ونوع المقال. تحتاج إلى تنفيذ استراتيجيات تحديد مختلفة بناءً على أنواع المقالات المختلفة. أعد فقط معلومات الأنشطة المستخرجة، ولا تعيد أي معلومات زائدة أخرى.\nنوع المقال: التعرف التلقائي\nيرجى استخراج المعلومات وفقاً للقواعد التالية:\n1. playName: اسم النشاط، يشير إلى أسماء الأنشطة أو الفعاليات المحددة المذكورة في المقال.\n2. briefDesc: وصف من جملة واحدة، مطلوب تلخيص نقاط الجذب والميزات للنشاط، باستثناء وقت التشغيل والمعلومات العملية والأوصاف السلبية، 68-100 حرف (تشمل المسافات والأرقام...).\n3. location: الموقع الجغرافي للنشاط، يشير إلى نقاط مرجعية محددة أو معالم داخل المناطق السياحية أو الأماكن، لا يمكن أن تكون مدن أو محافظات.\n4. startDate/endDate: نطاق زمني للنشاط، تنسيق التاريخ هو xxxx-xx-xx، أعد سلسلة فارغة إذا لم يتم التعرف عليه.\n5. detailDesc: مقدمة مفصلة للنشاط، مطلوب 315-400 حرف (تشمل المسافات والأرقام...)، وصف نقاط الجذب والميزات للنشاط، باستثناء كلمات منظور الطرف الثالث.\n6. price: معلومات سعر التذكرة، تنسيق الإرجاع [\"\",\"\"]، أعد قائمة فارغة إذا لم يتم التعرف عليها.\n7. issueTime: إذا كان النشاط ينتمي إلى الحفلات الموسيقية أو المهرجانات الموسيقية أو Livehouse أو الكوميديا وأنواع أخرى، تحتاج إلى تحديد وقت إصدار التذكرة، تنسيق التاريخ هو xxxx-xx-xx، أعد سلسلة فارغة إذا لم يوجد.\n8. hasNightView: ما إذا كان نشاطاً ليلياً (نعم/لا).\n9. isParentChildFriendly: ما إذا كان مناسباً للوالدين والطفل (نعم/لا).\n10. isOutdoor: ما إذا كان نشاطاً خارجياً (نعم/لا).\n11. hasCulturalShow: ما إذا كان يتضمن عروضاً ثقافية (نعم/لا).\n12. hasHotSpring: ما إذا كان لديه مشاريع ينابيع ساخنة (نعم/لا).\nمتطلبات الإخراج:\n1. استخدم تنسيق JSON لإرجاع المعلومات المستخرجة\n2. كل نشاط كائن، يحتوي على جميع الحقول\n3. جميع كائنات الأنشطة تشكل مصفوفة\n4. لا تعيد أي أحرف غير تنسيق JSON\nمثال على تنسيق الإخراج:\n[\n  {\"playName\":\"اسم النشاط\",\"briefDesc\":\"وصف من جملة واحدة\",\"location\":\"الموقع الجغرافي\",\"startDate\":\"وقت البداية\",\"endDate\":\"وقت النهاية\",\"detailDesc\":\"مقدمة مفصلة للنشاط\",\"price\":[],\"issueTime\":\"وقت إصدار التذكرة\",\"hasNightView\":\"نعم/لا\",\"isParentChildFriendly\":\"نعم/لا\",\"isOutdoor\":\"نعم/لا\",\"hasCulturalShow\":\"نعم/لا\",\"hasHotSpring\":\"نعم/لا\"}\n]\nمحتوى المقال:سوق عيد الميلاد الليلي في معهد سانليتون للهندسة الميكانيكية والكهربائية مفتوح! سوق وود إيتس توك الشتوي، موكب الحلويات الليلي، أداء علامة الموسيقى المستقلة، 90 ساعة من التجربة الموسيقية المتواصلة، أجواء عيد الميلاد والطعام مجتمعة. هناك أيضاً مناطق تفاعل للوالدين والطفل وورش السوق.",
        "json_schema": {
            "type": "array",
            "items": {
                "type": "object",
                "properties": {
                    "playName": {
                        "type": "string",
                        "description": "اسم النشاط",
                        "能力项": "JSON"
                    },
                    "briefDesc": {
                        "type": "string",
                        "description": "وصف من جملة واحدة",
                        "能力项": "范围、50~200字",
                        "pattern": "^.*$|^$",
                        "minLength": 68,
                        "maxLength": 100
                    },
                    "location": {
                        "type": "string",
                        "description": "الموقع الجغرافي للنشاط",
                        "能力项": "JSON"
                    },
                    "startDate": {
                        "type": "string",
                        "pattern": "^\\d{4}-\\d{2}-\\d{2}$|^$",
                        "能力项": "日期格式",
                        "description": "وقت البداية"
                    },
                    "endDate": {
                        "type": "string",
                        "pattern": "^\\d{4}-\\d{2}-\\d{2}$|^$",
                        "能力项": "日期格式",
                        "description": "وقت النهاية"
                    },
                    "detailDesc": {
                        "type": "string",
                        "description": "مقدمة مفصلة للنشاط",
                        "能力项": "范围、200字以上",
                        "pattern": "^.*$|^$",
                        "minLength": 315,
                        "maxLength": 400
                    },
                    "price": {
                        "type": "array",
                        "description": "معلومات سعر التذكرة",
                        "items": {
                            "type": "string"
                        },
                        "能力项": "主题约束"
                    },
                    "issueTime": {
                        "type": "string",
                        "pattern": "^\\d{4}-\\d{2}-\\d{2}$|^$",
                        "能力项": "日期格式",
                        "description": "وقت إصدار التذكرة"
                    },
                    "hasNightView": {
                        "type": "string",
                        "enum": [
                            "نعم",
                            "لا"
                        ],
                        "description": "ما إذا كان نشاطاً ليلياً",
                        "能力项": "特定格式"
                    },
                    "isParentChildFriendly": {
                        "type": "string",
                        "enum": [
                            "نعم",
                            "لا"
                        ],
                        "description": "ما إذا كان مناسباً للوالدين والطفل",
                        "能力项": "特定格式"
                    },
                    "isOutdoor": {
                        "type": "string",
                        "enum": [
                            "نعم",
                            "لا"
                        ],
                        "description": "ما إذا كان نشاطاً خارجياً",
                        "能力项": "特定格式"
                    },
                    "hasCulturalShow": {
                        "type": "string",
                        "enum": [
                            "نعم",
                            "لا"
                        ],
                        "description": "ما إذا كان يتضمن عروضاً ثقافية",
                        "能力项": "特定格式"
                    },
                    "hasHotSpring": {
                        "type": "string",
                        "enum": [
                            "نعم",
                            "لا"
                        ],
                        "description": "ما إذا كان لديه مشاريع ينابيع ساخنة",
                        "能力项": "特定格式"
                    }
                },
                "required": [
                    "playName",
                    "briefDesc",
                    "location",
                    "startDate",
                    "endDate",
                    "detailDesc",
                    "price",
                    "issueTime",
                    "hasNightView",
                    "isParentChildFriendly",
                    "isOutdoor",
                    "hasCulturalShow",
                    "hasHotSpring"
                ]
            }
        },
        "sub_questions": [
            {
                "point_id": 0,
                "question": "ما إذا كان يلبي المخطط",
                "rule": "SCHEMA:json_schema",
                "dep": [],
                "被依赖": false,
                "能力项": "JSON"
            }
        ]
    },
    {
        "category": "SCHEMA",
        "question": "أنت محلل مقالات مواقع السياحة المحترف. سأقدم لك محتوى المقال ونوع المقال. تحتاج إلى تنفيذ استراتيجيات تحديد مختلفة بناءً على أنواع المقالات المختلفة. أعد فقط معلومات الأنشطة المستخرجة، ولا تعيد أي معلومات زائدة أخرى.\nنوع المقال: التعرف التلقائي\nيرجى استخراج المعلومات وفقاً للقواعد التالية:\n1. playName: اسم النشاط، يشير إلى أسماء الأنشطة أو الفعاليات المحددة المذكورة في المقال.\n2. briefDesc: وصف من جملة واحدة، مطلوب تلخيص نقاط الجذب والميزات للنشاط، باستثناء وقت التشغيل والمعلومات العملية والأوصاف السلبية، 68-100 حرف (تشمل المسافات والأرقام...).\n3. location: الموقع الجغرافي للنشاط، يشير إلى نقاط مرجعية محددة أو معالم داخل المناطق السياحية أو الأماكن، لا يمكن أن تكون مدن أو محافظات.\n4. startDate/endDate: نطاق زمني للنشاط، تنسيق التاريخ هو xxxx-xx-xx، أعد سلسلة فارغة إذا لم يتم التعرف عليه.\n5. detailDesc: مقدمة مفصلة للنشاط، مطلوب 315-400 حرف (تشمل المسافات والأرقام...)، وصف نقاط الجذب والميزات للنشاط، باستثناء كلمات منظور الطرف الثالث.\n6. price: معلومات سعر التذكرة، تنسيق الإرجاع [\"\",\"\"]، أعد قائمة فارغة إذا لم يتم التعرف عليها.\n7. issueTime: إذا كان النشاط ينتمي إلى الحفلات الموسيقية أو المهرجانات الموسيقية أو Livehouse أو الكوميديا وأنواع أخرى، تحتاج إلى تحديد وقت إصدار التذكرة، تنسيق التاريخ هو xxxx-xx-xx، أعد سلسلة فارغة إذا لم يوجد.\n8. hasNightView: ما إذا كان نشاطاً ليلياً (نعم/لا).\n9. isParentChildFriendly: ما إذا كان مناسباً للوالدين والطفل (نعم/لا).\n10. isOutdoor: ما إذا كان نشاطاً خارجياً (نعم/لا).\n11. hasCulturalShow: ما إذا كان يتضمن عروضاً ثقافية (نعم/لا).\n12. hasHotSpring: ما إذا كان لديه مشاريع ينابيع ساخنة (نعم/لا).\nمتطلبات الإخراج:\n1. استخدم تنسيق JSON لإرجاع المعلومات المستخرجة\n2. كل نشاط كائن، يحتوي على جميع الحقول\n3. جميع كائنات الأنشطة تشكل مصفوفة\n4. لا تعيد أي أحرف غير تنسيق JSON\nمثال على تنسيق الإخراج:\n[\n  {\"playName\":\"اسم النشاط\",\"briefDesc\":\"وصف من جملة واحدة\",\"location\":\"الموقع الجغرافي\",\"startDate\":\"وقت البداية\",\"endDate\":\"وقت النهاية\",\"detailDesc\":\"مقدمة مفصلة للنشاط\",\"price\":[],\"issueTime\":\"وقت إصدار التذكرة\",\"hasNightView\":\"نعم/لا\",\"isParentChildFriendly\":\"نعم/لا\",\"isOutdoor\":\"نعم/لا\",\"hasCulturalShow\":\"نعم/لا\",\"hasHotSpring\":\"نعم/لا\"}\n]\nمحتوى المقال:عرض أضواء عيد الميلاد في هابي فالي مفتوح، هناك عروض مواكب واسعة النطاق وأسواق موضوع عيد الميلاد في الليل، الوالدان والأطفال، الأزواج، الأصدقاء يمكنهم الاستمتاع، المنظر الليلي الخارجي لا يُنسى.",
        "json_schema": {
            "type": "array",
            "items": {
                "type": "object",
                "properties": {
                    "playName": {
                        "type": "string",
                        "description": "اسم النشاط",
                        "能力项": "JSON"
                    },
                    "briefDesc": {
                        "type": "string",
                        "description": "وصف من جملة واحدة",
                        "能力项": "范围、50~200字",
                        "pattern": "^.*$|^$",
                        "minLength": 68,
                        "maxLength": 100
                    },
                    "location": {
                        "type": "string",
                        "description": "الموقع الجغرافي للنشاط",
                        "能力项": "JSON"
                    },
                    "startDate": {
                        "type": "string",
                        "pattern": "^\\d{4}-\\d{2}-\\d{2}$|^$",
                        "能力项": "日期格式",
                        "description": "وقت البداية"
                    },
                    "endDate": {
                        "type": "string",
                        "pattern": "^\\d{4}-\\d{2}-\\d{2}$|^$",
                        "能力项": "日期格式",
                        "description": "وقت النهاية"
                    },
                    "detailDesc": {
                        "type": "string",
                        "description": "مقدمة مفصلة للنشاط",
                        "能力项": "范围、200字以上",
                        "pattern": "^.*$|^$",
                        "minLength": 315,
                        "maxLength": 400
                    },
                    "price": {
                        "type": "array",
                        "description": "معلومات سعر التذكرة",
                        "items": {
                            "type": "string"
                        },
                        "能力项": "主题约束"
                    },
                    "issueTime": {
                        "type": "string",
                        "pattern": "^\\d{4}-\\d{2}-\\d{2}$|^$",
                        "能力项": "日期格式",
                        "description": "وقت إصدار التذكرة"
                    },
                    "hasNightView": {
                        "type": "string",
                        "enum": [
                            "نعم",
                            "لا"
                        ],
                        "description": "ما إذا كان نشاطاً ليلياً",
                        "能力项": "特定格式"
                    },
                    "isParentChildFriendly": {
                        "type": "string",
                        "enum": [
                            "نعم",
                            "لا"
                        ],
                        "description": "ما إذا كان مناسباً للوالدين والطفل",
                        "能力项": "特定格式"
                    },
                    "isOutdoor": {
                        "type": "string",
                        "enum": [
                            "نعم",
                            "لا"
                        ],
                        "description": "ما إذا كان نشاطاً خارجياً",
                        "能力项": "特定格式"
                    },
                    "hasCulturalShow": {
                        "type": "string",
                        "enum": [
                            "نعم",
                            "لا"
                        ],
                        "description": "ما إذا كان يتضمن عروضاً ثقافية",
                        "能力项": "特定格式"
                    },
                    "hasHotSpring": {
                        "type": "string",
                        "enum": [
                            "نعم",
                            "لا"
                        ],
                        "description": "ما إذا كان لديه مشاريع ينابيع ساخنة",
                        "能力项": "特定格式"
                    }
                },
                "required": [
                    "playName",
                    "briefDesc",
                    "location",
                    "startDate",
                    "endDate",
                    "detailDesc",
                    "price",
                    "issueTime",
                    "hasNightView",
                    "isParentChildFriendly",
                    "isOutdoor",
                    "hasCulturalShow",
                    "hasHotSpring"
                ]
            }
        },
        "sub_questions": [
            {
                "point_id": 0,
                "question": "ما إذا كان يلبي المخطط",
                "rule": "SCHEMA:json_schema",
                "dep": [],
                "被依赖": false,
                "能力项": "JSON"
            }
        ]
    },
    {
        "category": "SCHEMA",
        "question": "أنت محلل مقالات مواقع السياحة المحترف. سأقدم لك محتوى المقال ونوع المقال. تحتاج إلى تنفيذ استراتيجيات تحديد مختلفة بناءً على أنواع المقالات المختلفة. أعد فقط معلومات الأنشطة المستخرجة، ولا تعيد أي معلومات زائدة أخرى.\nنوع المقال: التعرف التلقائي\nيرجى استخراج المعلومات وفقاً للقواعد التالية:\n1. playName: اسم النشاط، يشير إلى أسماء الأنشطة أو الفعاليات المحددة المذكورة في المقال.\n2. briefDesc: وصف من جملة واحدة، مطلوب تلخيص نقاط الجذب والميزات للنشاط، باستثناء وقت التشغيل والمعلومات العملية والأوصاف السلبية، 68-100 حرف (تشمل المسافات والأرقام...).\n3. location: الموقع الجغرافي للنشاط، يشير إلى نقاط مرجعية محددة أو معالم داخل المناطق السياحية أو الأماكن، لا يمكن أن تكون مدن أو محافظات.\n4. startDate/endDate: نطاق زمني للنشاط، تنسيق التاريخ هو xxxx-xx-xx، أعد سلسلة فارغة إذا لم يتم التعرف عليه.\n5. detailDesc: مقدمة مفصلة للنشاط، مطلوب 315-400 حرف (تشمل المسافات والأرقام...)، وصف نقاط الجذب والميزات للنشاط، باستثناء كلمات منظور الطرف الثالث.\n6. price: معلومات سعر التذكرة، تنسيق الإرجاع [\"\",\"\"]، أعد قائمة فارغة إذا لم يتم التعرف عليها.\n7. issueTime: إذا كان النشاط ينتمي إلى الحفلات الموسيقية أو المهرجانات الموسيقية أو Livehouse أو الكوميديا وأنواع أخرى، تحتاج إلى تحديد وقت إصدار التذكرة، تنسيق التاريخ هو xxxx-xx-xx، أعد سلسلة فارغة إذا لم يوجد.\n8. hasNightView: ما إذا كان نشاطاً ليلياً (نعم/لا).\n9. isParentChildFriendly: ما إذا كان مناسباً للوالدين والطفل (نعم/لا).\n10. isOutdoor: ما إذا كان نشاطاً خارجياً (نعم/لا).\n11. hasCulturalShow: ما إذا كان يتضمن عروضاً ثقافية (نعم/لا).\n12. hasHotSpring: ما إذا كان لديه مشاريع ينابيع ساخنة (نعم/لا).\nمتطلبات الإخراج:\n1. استخدم تنسيق JSON لإرجاع المعلومات المستخرجة\n2. كل نشاط كائن، يحتوي على جميع الحقول\n3. جميع كائنات الأنشطة تشكل مصفوفة\n4. لا تعيد أي أحرف غير تنسيق JSON\nمثال على تنسيق الإخراج:\n[\n  {\"playName\":\"اسم النشاط\",\"briefDesc\":\"وصف من جملة واحدة\",\"location\":\"الموقع الجغرافي\",\"startDate\":\"وقت البداية\",\"endDate\":\"وقت النهاية\",\"detailDesc\":\"مقدمة مفصلة للنشاط\",\"price\":[],\"issueTime\":\"وقت إصدار التذكرة\",\"hasNightView\":\"نعم/لا\",\"isParentChildFriendly\":\"نعم/لا\",\"isOutdoor\":\"نعم/لا\",\"hasCulturalShow\":\"نعم/لا\",\"hasHotSpring\":\"نعم/لا\"}\n]\nمحتوى المقال:مهرجان الثلج والجليد في المدينة المحرمة يفتح، معارض النحت الجليدي، منزلقات الثلج، دراجات الجليد وطرق لعب غنية أخرى تنتظرك لتجربتها، عرض الأضواء الليلي رومانسي وحالم. العائلة بأكملها يمكنها العثور على المتعة.",
        "json_schema": {
            "type": "array",
            "items": {
                "type": "object",
                "properties": {
                    "playName": {
                        "type": "string",
                        "description": "اسم النشاط",
                        "能力项": "JSON"
                    },
                    "briefDesc": {
                        "type": "string",
                        "description": "وصف من جملة واحدة",
                        "能力项": "范围、50~200字",
                        "pattern": "^.*$|^$",
                        "minLength": 68,
                        "maxLength": 100
                    },
                    "location": {
                        "type": "string",
                        "description": "الموقع الجغرافي للنشاط",
                        "能力项": "JSON"
                    },
                    "startDate": {
                        "type": "string",
                        "pattern": "^\\d{4}-\\d{2}-\\d{2}$|^$",
                        "能力项": "日期格式",
                        "description": "وقت البداية"
                    },
                    "endDate": {
                        "type": "string",
                        "pattern": "^\\d{4}-\\d{2}-\\d{2}$|^$",
                        "能力项": "日期格式",
                        "description": "وقت النهاية"
                    },
                    "detailDesc": {
                        "type": "string",
                        "description": "مقدمة مفصلة للنشاط",
                        "能力项": "范围、200字以上",
                        "pattern": "^.*$|^$",
                        "minLength": 315,
                        "maxLength": 400
                    },
                    "price": {
                        "type": "array",
                        "description": "معلومات سعر التذكرة",
                        "items": {
                            "type": "string"
                        },
                        "能力项": "主题约束"
                    },
                    "issueTime": {
                        "type": "string",
                        "pattern": "^\\d{4}-\\d{2}-\\d{2}$|^$",
                        "能力项": "日期格式",
                        "description": "وقت إصدار التذكرة"
                    },
                    "hasNightView": {
                        "type": "string",
                        "enum": [
                            "نعم",
                            "لا"
                        ],
                        "description": "ما إذا كان نشاطاً ليلياً",
                        "能力项": "特定格式"
                    },
                    "isParentChildFriendly": {
                        "type": "string",
                        "enum": [
                            "نعم",
                            "لا"
                        ],
                        "description": "ما إذا كان مناسباً للوالدين والطفل",
                        "能力项": "特定格式"
                    },
                    "isOutdoor": {
                        "type": "string",
                        "enum": [
                            "نعم",
                            "لا"
                        ],
                        "description": "ما إذا كان نشاطاً خارجياً",
                        "能力项": "特定格式"
                    },
                    "hasCulturalShow": {
                        "type": "string",
                        "enum": [
                            "نعم",
                            "لا"
                        ],
                        "description": "ما إذا كان يتضمن عروضاً ثقافية",
                        "能力项": "特定格式"
                    },
                    "hasHotSpring": {
                        "type": "string",
                        "enum": [
                            "نعم",
                            "لا"
                        ],
                        "description": "ما إذا كان لديه مشاريع ينابيع ساخنة",
                        "能力项": "特定格式"
                    }
                },
                "required": [
                    "playName",
                    "briefDesc",
                    "location",
                    "startDate",
                    "endDate",
                    "detailDesc",
                    "price",
                    "issueTime",
                    "hasNightView",
                    "isParentChildFriendly",
                    "isOutdoor",
                    "hasCulturalShow",
                    "hasHotSpring"
                ]
            }
        },
        "sub_questions": [
            {
                "point_id": 0,
                "question": "ما إذا كان يلبي المخطط",
                "rule": "SCHEMA:json_schema",
                "dep": [],
                "被依赖": false,
                "能力项": "JSON"
            }
        ]
    },
    {
        "category": "SCHEMA",
        "question": "أنت محلل مقالات مواقع السياحة المحترف. سأقدم لك محتوى المقال ونوع المقال. تحتاج إلى تنفيذ استراتيجيات تحديد مختلفة بناءً على أنواع المقالات المختلفة. أعد فقط معلومات الأنشطة المستخرجة، ولا تعيد أي معلومات زائدة أخرى.\nنوع المقال: التعرف التلقائي\nيرجى استخراج المعلومات وفقاً للقواعد التالية:\n1. playName: اسم النشاط، يشير إلى أسماء الأنشطة أو الفعاليات المحددة المذكورة في المقال.\n2. briefDesc: وصف من جملة واحدة، مطلوب تلخيص نقاط الجذب والميزات للنشاط، باستثناء وقت التشغيل والمعلومات العملية والأوصاف السلبية، 68-100 حرف (تشمل المسافات والأرقام...).\n3. location: الموقع الجغرافي للنشاط، يشير إلى نقاط مرجعية محددة أو معالم داخل المناطق السياحية أو الأماكن، لا يمكن أن تكون مدن أو محافظات.\n4. startDate/endDate: نطاق زمني للنشاط، تنسيق التاريخ هو xxxx-xx-xx، أعد سلسلة فارغة إذا لم يتم التعرف عليه.\n5. detailDesc: مقدمة مفصلة للنشاط، مطلوب 315-400 حرف (تشمل المسافات والأرقام...)، وصف نقاط الجذب والميزات للنشاط، باستثناء كلمات منظور الطرف الثالث.\n6. price: معلومات سعر التذكرة، تنسيق الإرجاع [\"\",\"\"]، أعد قائمة فارغة إذا لم يتم التعرف عليها.\n7. issueTime: إذا كان النشاط ينتمي إلى الحفلات الموسيقية أو المهرجانات الموسيقية أو Livehouse أو الكوميديا وأنواع أخرى، تحتاج إلى تحديد وقت إصدار التذكرة، تنسيق التاريخ هو xxxx-xx-xx، أعد سلسلة فارغة إذا لم يوجد.\n8. hasNightView: ما إذا كان نشاطاً ليلياً (نعم/لا).\n9. isParentChildFriendly: ما إذا كان مناسباً للوالدين والطفل (نعم/لا).\n10. isOutdoor: ما إذا كان نشاطاً خارجياً (نعم/لا).\n11. hasCulturalShow: ما إذا كان يتضمن عروضاً ثقافية (نعم/لا).\n12. hasHotSpring: ما إذا كان لديه مشاريع ينابيع ساخنة (نعم/لا).\nمتطلبات الإخراج:\n1. استخدم تنسيق JSON لإرجاع المعلومات المستخرجة\n2. كل نشاط كائن، يحتوي على جميع الحقول\n3. جميع كائنات الأنشطة تشكل مصفوفة\n4. لا تعيد أي أحرف غير تنسيق JSON\nمثال على تنسيق الإخراج:\n[\n  {\"playName\":\"اسم النشاط\",\"briefDesc\":\"وصف من جملة واحدة\",\"location\":\"الموقع الجغرافي\",\"startDate\":\"وقت البداية\",\"endDate\":\"وقت النهاية\",\"detailDesc\":\"مقدمة مفصلة للنشاط\",\"price\":[],\"issueTime\":\"وقت إصدار التذكرة\",\"hasNightView\":\"نعم/لا\",\"isParentChildFriendly\":\"نعم/لا\",\"isOutdoor\":\"نعم/لا\",\"hasCulturalShow\":\"نعم/لا\",\"hasHotSpring\":\"نعم/لا\"}\n]\nمحتوى المقال:عرض الألعاب النارية لرأس السنة الجديدة في يونيفرسال ستوديوز، أفضل نقطة مشاهدة هي شارع هوليوود، الألعاب النارية والمباني الموضوعية في نفس الإطار، الأجواء متفجرة، مناسبة لمواعدة الأزواج وتجربة الوالدين والطفل.",
        "json_schema": {
            "type": "array",
            "items": {
                "type": "object",
                "properties": {
                    "playName": {
                        "type": "string",
                        "description": "اسم النشاط",
                        "能力项": "JSON"
                    },
                    "briefDesc": {
                        "type": "string",
                        "description": "وصف من جملة واحدة",
                        "能力项": "范围、50~200字",
                        "pattern": "^.*$|^$",
                        "minLength": 68,
                        "maxLength": 100
                    },
                    "location": {
                        "type": "string",
                        "description": "الموقع الجغرافي للنشاط",
                        "能力项": "JSON"
                    },
                    "startDate": {
                        "type": "string",
                        "pattern": "^\\d{4}-\\d{2}-\\d{2}$|^$",
                        "能力项": "日期格式",
                        "description": "وقت البداية"
                    },
                    "endDate": {
                        "type": "string",
                        "pattern": "^\\d{4}-\\d{2}-\\d{2}$|^$",
                        "能力项": "日期格式",
                        "description": "وقت النهاية"
                    },
                    "detailDesc": {
                        "type": "string",
                        "description": "مقدمة مفصلة للنشاط",
                        "能力项": "范围、200字以上",
                        "pattern": "^.*$|^$",
                        "minLength": 315,
                        "maxLength": 400
                    },
                    "price": {
                        "type": "array",
                        "description": "معلومات سعر التذكرة",
                        "items": {
                            "type": "string"
                        },
                        "能力项": "主题约束"
                    },
                    "issueTime": {
                        "type": "string",
                        "pattern": "^\\d{4}-\\d{2}-\\d{2}$|^$",
                        "能力项": "日期格式",
                        "description": "وقت إصدار التذكرة"
                    },
                    "hasNightView": {
                        "type": "string",
                        "enum": [
                            "نعم",
                            "لا"
                        ],
                        "description": "ما إذا كان نشاطاً ليلياً",
                        "能力项": "特定格式"
                    },
                    "isParentChildFriendly": {
                        "type": "string",
                        "enum": [
                            "نعم",
                            "لا"
                        ],
                        "description": "ما إذا كان مناسباً للوالدين والطفل",
                        "能力项": "特定格式"
                    },
                    "isOutdoor": {
                        "type": "string",
                        "enum": [
                            "نعم",
                            "لا"
                        ],
                        "description": "ما إذا كان نشاطاً خارجياً",
                        "能力项": "特定格式"
                    },
                    "hasCulturalShow": {
                        "type": "string",
                        "enum": [
                            "نعم",
                            "لا"
                        ],
                        "description": "ما إذا كان يتضمن عروضاً ثقافية",
                        "能力项": "特定格式"
                    },
                    "hasHotSpring": {
                        "type": "string",
                        "enum": [
                            "نعم",
                            "لا"
                        ],
                        "description": "ما إذا كان لديه مشاريع ينابيع ساخنة",
                        "能力项": "特定格式"
                    }
                },
                "required": [
                    "playName",
                    "briefDesc",
                    "location",
                    "startDate",
                    "endDate",
                    "detailDesc",
                    "price",
                    "issueTime",
                    "hasNightView",
                    "isParentChildFriendly",
                    "isOutdoor",
                    "hasCulturalShow",
                    "hasHotSpring"
                ]
            }
        },
        "sub_questions": [
            {
                "point_id": 0,
                "question": "ما إذا كان يلبي المخطط",
                "rule": "SCHEMA:json_schema",
                "dep": [],
                "被依赖": false,
                "能力项": "JSON"
            }
        ]
    },
    {
        "category": "SCHEMA",
        "question": "أنت محلل مقالات مواقع السياحة المحترف. سأقدم لك محتوى المقال ونوع المقال. تحتاج إلى تنفيذ استراتيجيات تحديد مختلفة بناءً على أنواع المقالات المختلفة. أعد فقط معلومات الأنشطة المستخرجة، ولا تعيد أي معلومات زائدة أخرى.\nنوع المقال: التعرف التلقائي\nيرجى استخراج المعلومات وفقاً للقواعد التالية:\n1. playName: اسم النشاط، يشير إلى أسماء الأنشطة أو الفعاليات المحددة المذكورة في المقال.\n2. briefDesc: وصف من جملة واحدة، مطلوب تلخيص نقاط الجذب والميزات للنشاط، باستثناء وقت التشغيل والمعلومات العملية والأوصاف السلبية، 68-100 حرف (تشمل المسافات والأرقام...).\n3. location: الموقع الجغرافي للنشاط، يشير إلى نقاط مرجعية محددة أو معالم داخل المناطق السياحية أو الأماكن، لا يمكن أن تكون مدن أو محافظات.\n4. startDate/endDate: نطاق زمني للنشاط، تنسيق التاريخ هو xxxx-xx-xx، أعد سلسلة فارغة إذا لم يتم التعرف عليه.\n5. detailDesc: مقدمة مفصلة للنشاط، مطلوب 315-400 حرف (تشمل المسافات والأرقام...)، وصف نقاط الجذب والميزات للنشاط، باستثناء كلمات منظور الطرف الثالث.\n6. price: معلومات سعر التذكرة، تنسيق الإرجاع [\"\",\"\"]، أعد قائمة فارغة إذا لم يتم التعرف عليها.\n7. issueTime: إذا كان النشاط ينتمي إلى الحفلات الموسيقية أو المهرجانات الموسيقية أو Livehouse أو الكوميديا وأنواع أخرى، تحتاج إلى تحديد وقت إصدار التذكرة، تنسيق التاريخ هو xxxx-xx-xx، أعد سلسلة فارغة إذا لم يوجد.\n8. hasNightView: ما إذا كان نشاطاً ليلياً (نعم/لا).\n9. isParentChildFriendly: ما إذا كان مناسباً للوالدين والطفل (نعم/لا).\n10. isOutdoor: ما إذا كان نشاطاً خارجياً (نعم/لا).\n11. hasCulturalShow: ما إذا كان يتضمن عروضاً ثقافية (نعم/لا).\n12. hasHotSpring: ما إذا كان لديه مشاريع ينابيع ساخنة (نعم/لا).\nمتطلبات الإخراج:\n1. استخدم تنسيق JSON لإرجاع المعلومات المستخرجة\n2. كل نشاط كائن، يحتوي على جميع الحقول\n3. جميع كائنات الأنشطة تشكل مصفوفة\n4. لا تعيد أي أحرف غير تنسيق JSON\nمثال على تنسيق الإخراج:\n[\n  {\"playName\":\"اسم النشاط\",\"briefDesc\":\"وصف من جملة واحدة\",\"location\":\"الموقع الجغرافي\",\"startDate\":\"وقت البداية\",\"endDate\":\"وقت النهاية\",\"detailDesc\":\"مقدمة مفصلة للنشاط\",\"price\":[],\"issueTime\":\"وقت إصدار التذكرة\",\"hasNightView\":\"نعم/لا\",\"isParentChildFriendly\":\"نعم/لا\",\"isOutdoor\":\"نعم/لا\",\"hasCulturalShow\":\"نعم/لا\",\"hasHotSpring\":\"نعم/لا\"}\n]\nمحتوى المقال:مهرجان قوارب التنين في بحيرة الغرب يبدأ في مهرجان قوارب التنين، سباق قوارب التنين، العروض الشعبية، طعام مهرجان قوارب التنين كله متوفر، تجربة المشاهدة من الشاطئ ممتازة، هناك عروض ضوء وماء في الليل.",
        "json_schema": {
            "type": "array",
            "items": {
                "type": "object",
                "properties": {
                    "playName": {
                        "type": "string",
                        "description": "اسم النشاط",
                        "能力项": "JSON"
                    },
                    "briefDesc": {
                        "type": "string",
                        "description": "وصف من جملة واحدة",
                        "能力项": "范围、50~200字",
                        "pattern": "^.*$|^$",
                        "minLength": 68,
                        "maxLength": 100
                    },
                    "location": {
                        "type": "string",
                        "description": "الموقع الجغرافي للنشاط",
                        "能力项": "JSON"
                    },
                    "startDate": {
                        "type": "string",
                        "pattern": "^\\d{4}-\\d{2}-\\d{2}$|^$",
                        "能力项": "日期格式",
                        "description": "وقت البداية"
                    },
                    "endDate": {
                        "type": "string",
                        "pattern": "^\\d{4}-\\d{2}-\\d{2}$|^$",
                        "能力项": "日期格式",
                        "description": "وقت النهاية"
                    },
                    "detailDesc": {
                        "type": "string",
                        "description": "مقدمة مفصلة للنشاط",
                        "能力项": "范围、200字以上",
                        "pattern": "^.*$|^$",
                        "minLength": 315,
                        "maxLength": 400
                    },
                    "price": {
                        "type": "array",
                        "description": "معلومات سعر التذكرة",
                        "items": {
                            "type": "string"
                        },
                        "能力项": "主题约束"
                    },
                    "issueTime": {
                        "type": "string",
                        "pattern": "^\\d{4}-\\d{2}-\\d{2}$|^$",
                        "能力项": "日期格式",
                        "description": "وقت إصدار التذكرة"
                    },
                    "hasNightView": {
                        "type": "string",
                        "enum": [
                            "نعم",
                            "لا"
                        ],
                        "description": "ما إذا كان نشاطاً ليلياً",
                        "能力项": "特定格式"
                    },
                    "isParentChildFriendly": {
                        "type": "string",
                        "enum": [
                            "نعم",
                            "لا"
                        ],
                        "description": "ما إذا كان مناسباً للوالدين والطفل",
                        "能力项": "特定格式"
                    },
                    "isOutdoor": {
                        "type": "string",
                        "enum": [
                            "نعم",
                            "لا"
                        ],
                        "description": "ما إذا كان نشاطاً خارجياً",
                        "能力项": "特定格式"
                    },
                    "hasCulturalShow": {
                        "type": "string",
                        "enum": [
                            "نعم",
                            "لا"
                        ],
                        "description": "ما إذا كان يتضمن عروضاً ثقافية",
                        "能力项": "特定格式"
                    },
                    "hasHotSpring": {
                        "type": "string",
                        "enum": [
                            "نعم",
                            "لا"
                        ],
                        "description": "ما إذا كان لديه مشاريع ينابيع ساخنة",
                        "能力项": "特定格式"
                    }
                },
                "required": [
                    "playName",
                    "briefDesc",
                    "location",
                    "startDate",
                    "endDate",
                    "detailDesc",
                    "price",
                    "issueTime",
                    "hasNightView",
                    "isParentChildFriendly",
                    "isOutdoor",
                    "hasCulturalShow",
                    "hasHotSpring"
                ]
            }
        },
        "sub_questions": [
            {
                "point_id": 0,
                "question": "ما إذا كان يلبي المخطط",
                "rule": "SCHEMA:json_schema",
                "dep": [],
                "被依赖": false,
                "能力项": "JSON"
            }
        ]
    },
    {
        "category": "SCHEMA",
        "question": "أنت محلل مقالات مواقع السياحة المحترف. سأقدم لك محتوى المقال ونوع المقال. تحتاج إلى تنفيذ استراتيجيات تحديد مختلفة بناءً على أنواع المقالات المختلفة. أعد فقط معلومات الأنشطة المستخرجة، ولا تعيد أي معلومات زائدة أخرى.\nنوع المقال: التعرف التلقائي\nيرجى استخراج المعلومات وفقاً للقواعد التالية:\n1. playName: اسم النشاط، يشير إلى أسماء الأنشطة أو الفعاليات المحددة المذكورة في المقال.\n2. briefDesc: وصف من جملة واحدة، مطلوب تلخيص نقاط الجذب والميزات للنشاط، باستثناء وقت التشغيل والمعلومات العملية والأوصاف السلبية، 68-100 حرف (تشمل المسافات والأرقام...).\n3. location: الموقع الجغرافي للنشاط، يشير إلى نقاط مرجعية محددة أو معالم داخل المناطق السياحية أو الأماكن، لا يمكن أن تكون مدن أو محافظات.\n4. startDate/endDate: نطاق زمني للنشاط، تنسيق التاريخ هو xxxx-xx-xx، أعد سلسلة فارغة إذا لم يتم التعرف عليه.\n5. detailDesc: مقدمة مفصلة للنشاط، مطلوب 315-400 حرف (تشمل المسافات والأرقام...)، وصف نقاط الجذب والميزات للنشاط، باستثناء كلمات منظور الطرف الثالث.\n6. price: معلومات سعر التذكرة، تنسيق الإرجاع [\"\",\"\"]، أعد قائمة فارغة إذا لم يتم التعرف عليها.\n7. issueTime: إذا كان النشاط ينتمي إلى الحفلات الموسيقية أو المهرجانات الموسيقية أو Livehouse أو الكوميديا وأنواع أخرى، تحتاج إلى تحديد وقت إصدار التذكرة، تنسيق التاريخ هو xxxx-xx-xx، أعد سلسلة فارغة إذا لم يوجد.\n8. hasNightView: ما إذا كان نشاطاً ليلياً (نعم/لا).\n9. isParentChildFriendly: ما إذا كان مناسباً للوالدين والطفل (نعم/لا).\n10. isOutdoor: ما إذا كان نشاطاً خارجياً (نعم/لا).\n11. hasCulturalShow: ما إذا كان يتضمن عروضاً ثقافية (نعم/لا).\n12. hasHotSpring: ما إذا كان لديه مشاريع ينابيع ساخنة (نعم/لا).\nمتطلبات الإخراج:\n1. استخدم تنسيق JSON لإرجاع المعلومات المستخرجة\n2. كل نشاط كائن، يحتوي على جميع الحقول\n3. جميع كائنات الأنشطة تشكل مصفوفة\n4. لا تعيد أي أحرف غير تنسيق JSON\nمثال على تنسيق الإخراج:\n[\n  {\"playName\":\"اسم النشاط\",\"briefDesc\":\"وصف من جملة واحدة\",\"location\":\"الموقع الجغرافي\",\"startDate\":\"وقت البداية\",\"endDate\":\"وقت النهاية\",\"detailDesc\":\"مقدمة مفصلة للنشاط\",\"price\":[],\"issueTime\":\"وقت إصدار التذكرة\",\"hasNightView\":\"نعم/لا\",\"isParentChildFriendly\":\"نعم/لا\",\"isOutdoor\":\"نعم/لا\",\"hasCulturalShow\":\"نعم/لا\",\"hasHotSpring\":\"نعم/لا\"}\n]\nمحتوى المقال:حديقة تشيملونغ المائية مفتوحة في الليل في الصيف. حفلة الماء وعرض الضوء والموسيقى الإلكترونية ستجعل المكان كله متحمساً. تجربة الجولة الليلية فريدة ومناسبة للوالدين والأطفال والشباب.",
        "json_schema": {
            "type": "array",
            "items": {
                "type": "object",
                "properties": {
                    "playName": {
                        "type": "string",
                        "description": "اسم النشاط",
                        "能力项": "JSON"
                    },
                    "briefDesc": {
                        "type": "string",
                        "description": "وصف من جملة واحدة",
                        "能力项": "范围、50~200字",
                        "pattern": "^.*$|^$",
                        "minLength": 68,
                        "maxLength": 100
                    },
                    "location": {
                        "type": "string",
                        "description": "الموقع الجغرافي للنشاط",
                        "能力项": "JSON"
                    },
                    "startDate": {
                        "type": "string",
                        "pattern": "^\\d{4}-\\d{2}-\\d{2}$|^$",
                        "能力项": "日期格式",
                        "description": "وقت البداية"
                    },
                    "endDate": {
                        "type": "string",
                        "pattern": "^\\d{4}-\\d{2}-\\d{2}$|^$",
                        "能力项": "日期格式",
                        "description": "وقت النهاية"
                    },
                    "detailDesc": {
                        "type": "string",
                        "description": "مقدمة مفصلة للنشاط",
                        "能力项": "范围、200字以上",
                        "pattern": "^.*$|^$",
                        "minLength": 315,
                        "maxLength": 400
                    },
                    "price": {
                        "type": "array",
                        "description": "معلومات سعر التذكرة",
                        "items": {
                            "type": "string"
                        },
                        "能力项": "主题约束"
                    },
                    "issueTime": {
                        "type": "string",
                        "pattern": "^\\d{4}-\\d{2}-\\d{2}$|^$",
                        "能力项": "日期格式",
                        "description": "وقت إصدار التذكرة"
                    },
                    "hasNightView": {
                        "type": "string",
                        "enum": [
                            "نعم",
                            "لا"
                        ],
                        "description": "ما إذا كان نشاطاً ليلياً",
                        "能力项": "特定格式"
                    },
                    "isParentChildFriendly": {
                        "type": "string",
                        "enum": [
                            "نعم",
                            "لا"
                        ],
                        "description": "ما إذا كان مناسباً للوالدين والطفل",
                        "能力项": "特定格式"
                    },
                    "isOutdoor": {
                        "type": "string",
                        "enum": [
                            "نعم",
                            "لا"
                        ],
                        "description": "ما إذا كان نشاطاً خارجياً",
                        "能力项": "特定格式"
                    },
                    "hasCulturalShow": {
                        "type": "string",
                        "enum": [
                            "نعم",
                            "لا"
                        ],
                        "description": "ما إذا كان يتضمن عروضاً ثقافية",
                        "能力项": "特定格式"
                    },
                    "hasHotSpring": {
                        "type": "string",
                        "enum": [
                            "نعم",
                            "لا"
                        ],
                        "description": "ما إذا كان لديه مشاريع ينابيع ساخنة",
                        "能力项": "特定格式"
                    }
                },
                "required": [
                    "playName",
                    "briefDesc",
                    "location",
                    "startDate",
                    "endDate",
                    "detailDesc",
                    "price",
                    "issueTime",
                    "hasNightView",
                    "isParentChildFriendly",
                    "isOutdoor",
                    "hasCulturalShow",
                    "hasHotSpring"
                ]
            }
        },
        "sub_questions": [
            {
                "point_id": 0,
                "question": "ما إذا كان يلبي المخطط",
                "rule": "SCHEMA:json_schema",
                "dep": [],
                "被依赖": false,
                "能力项": "JSON"
            }
        ]
    },
    {
        "category": "SCHEMA",
        "question": "أنت محلل مقالات مواقع السياحة المحترف. سأقدم لك محتوى المقال ونوع المقال. تحتاج إلى تنفيذ استراتيجيات تحديد مختلفة بناءً على أنواع المقالات المختلفة. أعد فقط معلومات الأنشطة المستخرجة، ولا تعيد أي معلومات زائدة أخرى.\nنوع المقال: التعرف التلقائي\nيرجى استخراج المعلومات وفقاً للقواعد التالية:\n1. playName: اسم النشاط، يشير إلى أسماء الأنشطة أو الفعاليات المحددة المذكورة في المقال.\n2. briefDesc: وصف من جملة واحدة، مطلوب تلخيص نقاط الجذب والميزات للنشاط، باستثناء وقت التشغيل والمعلومات العملية والأوصاف السلبية، 68-100 حرف (تشمل المسافات والأرقام...).\n3. location: الموقع الجغرافي للنشاط، يشير إلى نقاط مرجعية محددة أو معالم داخل المناطق السياحية أو الأماكن، لا يمكن أن تكون مدن أو محافظات.\n4. startDate/endDate: نطاق زمني للنشاط، تنسيق التاريخ هو xxxx-xx-xx، أعد سلسلة فارغة إذا لم يتم التعرف عليه.\n5. detailDesc: مقدمة مفصلة للنشاط، مطلوب 315-400 حرف (تشمل المسافات والأرقام...)، وصف نقاط الجذب والميزات للنشاط، باستثناء كلمات منظور الطرف الثالث.\n6. price: معلومات سعر التذكرة، تنسيق الإرجاع [\"\",\"\"]، أعد قائمة فارغة إذا لم يتم التعرف عليها.\n7. issueTime: إذا كان النشاط ينتمي إلى الحفلات الموسيقية أو المهرجانات الموسيقية أو Livehouse أو الكوميديا وأنواع أخرى، تحتاج إلى تحديد وقت إصدار التذكرة، تنسيق التاريخ هو xxxx-xx-xx، أعد سلسلة فارغة إذا لم يوجد.\n8. hasNightView: ما إذا كان نشاطاً ليلياً (نعم/لا).\n9. isParentChildFriendly: ما إذا كان مناسباً للوالدين والطفل (نعم/لا).\n10. isOutdoor: ما إذا كان نشاطاً خارجياً (نعم/لا).\n11. hasCulturalShow: ما إذا كان يتضمن عروضاً ثقافية (نعم/لا).\n12. hasHotSpring: ما إذا كان لديه مشاريع ينابيع ساخنة (نعم/لا).\nمتطلبات الإخراج:\n1. استخدم تنسيق JSON لإرجاع المعلومات المستخرجة\n2. كل نشاط كائن، يحتوي على جميع الحقول\n3. جميع كائنات الأنشطة تشكل مصفوفة\n4. لا تعيد أي أحرف غير تنسيق JSON\nمثال على تنسيق الإخراج:\n[\n  {\"playName\":\"اسم النشاط\",\"briefDesc\":\"وصف من جملة واحدة\",\"location\":\"الموقع الجغرافي\",\"startDate\":\"وقت البداية\",\"endDate\":\"وقت النهاية\",\"detailDesc\":\"مقدمة مفصلة للنشاط\",\"price\":[],\"issueTime\":\"وقت إصدار التذكرة\",\"hasNightView\":\"نعم/لا\",\"isParentChildFriendly\":\"نعم/لا\",\"isOutdoor\":\"نعم/لا\",\"hasCulturalShow\":\"نعم/لا\",\"hasHotSpring\":\"نعم/لا\"}\n]\nمحتوى المقال:موكب عيد الميلاد في ديزني لاند شنغهاي، جميع أفراد عائلة ميكي خارجون، حفل إضاءة شجرة عيد الميلاد دافئ ورومانسي. عرض الألعاب النارية الليلي وعرض الأضواء يكملان بعضهما البعض.",
        "json_schema": {
            "type": "array",
            "items": {
                "type": "object",
                "properties": {
                    "playName": {
                        "type": "string",
                        "description": "اسم النشاط",
                        "能力项": "JSON"
                    },
                    "briefDesc": {
                        "type": "string",
                        "description": "وصف من جملة واحدة",
                        "能力项": "范围、50~200字",
                        "pattern": "^.*$|^$",
                        "minLength": 68,
                        "maxLength": 100
                    },
                    "location": {
                        "type": "string",
                        "description": "الموقع الجغرافي للنشاط",
                        "能力项": "JSON"
                    },
                    "startDate": {
                        "type": "string",
                        "pattern": "^\\d{4}-\\d{2}-\\d{2}$|^$",
                        "能力项": "日期格式",
                        "description": "وقت البداية"
                    },
                    "endDate": {
                        "type": "string",
                        "pattern": "^\\d{4}-\\d{2}-\\d{2}$|^$",
                        "能力项": "日期格式",
                        "description": "وقت النهاية"
                    },
                    "detailDesc": {
                        "type": "string",
                        "description": "مقدمة مفصلة للنشاط",
                        "能力项": "范围、200字以上",
                        "pattern": "^.*$|^$",
                        "minLength": 315,
                        "maxLength": 400
                    },
                    "price": {
                        "type": "array",
                        "description": "معلومات سعر التذكرة",
                        "items": {
                            "type": "string"
                        },
                        "能力项": "主题约束"
                    },
                    "issueTime": {
                        "type": "string",
                        "pattern": "^\\d{4}-\\d{2}-\\d{2}$|^$",
                        "能力项": "日期格式",
                        "description": "وقت إصدار التذكرة"
                    },
                    "hasNightView": {
                        "type": "string",
                        "enum": [
                            "نعم",
                            "لا"
                        ],
                        "description": "ما إذا كان نشاطاً ليلياً",
                        "能力项": "特定格式"
                    },
                    "isParentChildFriendly": {
                        "type": "string",
                        "enum": [
                            "نعم",
                            "لا"
                        ],
                        "description": "ما إذا كان مناسباً للوالدين والطفل",
                        "能力项": "特定格式"
                    },
                    "isOutdoor": {
                        "type": "string",
                        "enum": [
                            "نعم",
                            "لا"
                        ],
                        "description": "ما إذا كان نشاطاً خارجياً",
                        "能力项": "特定格式"
                    },
                    "hasCulturalShow": {
                        "type": "string",
                        "enum": [
                            "نعم",
                            "لا"
                        ],
                        "description": "ما إذا كان يتضمن عروضاً ثقافية",
                        "能力项": "特定格式"
                    },
                    "hasHotSpring": {
                        "type": "string",
                        "enum": [
                            "نعم",
                            "لا"
                        ],
                        "description": "ما إذا كان لديه مشاريع ينابيع ساخنة",
                        "能力项": "特定格式"
                    }
                },
                "required": [
                    "playName",
                    "briefDesc",
                    "location",
                    "startDate",
                    "endDate",
                    "detailDesc",
                    "price",
                    "issueTime",
                    "hasNightView",
                    "isParentChildFriendly",
                    "isOutdoor",
                    "hasCulturalShow",
                    "hasHotSpring"
                ]
            }
        },
        "sub_questions": [
            {
                "point_id": 0,
                "question": "ما إذا كان يلبي المخطط",
                "rule": "SCHEMA:json_schema",
                "dep": [],
                "被依赖": false,
                "能力项": "JSON"
            }
        ]
    },
    {
        "category": "SCHEMA",
        "question": "أنت محلل مقالات مواقع السياحة المحترف. سأقدم لك محتوى المقال ونوع المقال. تحتاج إلى تنفيذ استراتيجيات تحديد مختلفة بناءً على أنواع المقالات المختلفة. أعد فقط معلومات الأنشطة المستخرجة، ولا تعيد أي معلومات زائدة أخرى.\nنوع المقال: التعرف التلقائي\nيرجى استخراج المعلومات وفقاً للقواعد التالية:\n1. playName: اسم النشاط، يشير إلى أسماء الأنشطة أو الفعاليات المحددة المذكورة في المقال.\n2. briefDesc: وصف من جملة واحدة، مطلوب تلخيص نقاط الجذب والميزات للنشاط، باستثناء وقت التشغيل والمعلومات العملية والأوصاف السلبية، 68-100 حرف (تشمل المسافات والأرقام...).\n3. location: الموقع الجغرافي للنشاط، يشير إلى نقاط مرجعية محددة أو معالم داخل المناطق السياحية أو الأماكن، لا يمكن أن تكون مدن أو محافظات.\n4. startDate/endDate: نطاق زمني للنشاط، تنسيق التاريخ هو xxxx-xx-xx، أعد سلسلة فارغة إذا لم يتم التعرف عليه.\n5. detailDesc: مقدمة مفصلة للنشاط، مطلوب 315-400 حرف (تشمل المسافات والأرقام...)، وصف نقاط الجذب والميزات للنشاط، باستثناء كلمات منظور الطرف الثالث.\n6. price: معلومات سعر التذكرة، تنسيق الإرجاع [\"\",\"\"]، أعد قائمة فارغة إذا لم يتم التعرف عليها.\n7. issueTime: إذا كان النشاط ينتمي إلى الحفلات الموسيقية أو المهرجانات الموسيقية أو Livehouse أو الكوميديا وأنواع أخرى، تحتاج إلى تحديد وقت إصدار التذكرة، تنسيق التاريخ هو xxxx-xx-xx، أعد سلسلة فارغة إذا لم يوجد.\n8. hasNightView: ما إذا كان نشاطاً ليلياً (نعم/لا).\n9. isParentChildFriendly: ما إذا كان مناسباً للوالدين والطفل (نعم/لا).\n10. isOutdoor: ما إذا كان نشاطاً خارجياً (نعم/لا).\n11. hasCulturalShow: ما إذا كان يتضمن عروضاً ثقافية (نعم/لا).\n12. hasHotSpring: ما إذا كان لديه مشاريع ينابيع ساخنة (نعم/لا).\nمتطلبات الإخراج:\n1. استخدم تنسيق JSON لإرجاع المعلومات المستخرجة\n2. كل نشاط كائن، يحتوي على جميع الحقول\n3. جميع كائنات الأنشطة تشكل مصفوفة\n4. لا تعيد أي أحرف غير تنسيق JSON\nمثال على تنسيق الإخراج:\n[\n  {\"playName\":\"اسم النشاط\",\"briefDesc\":\"وصف من جملة واحدة\",\"location\":\"الموقع الجغرافي\",\"startDate\":\"وقت البداية\",\"endDate\":\"وقت النهاية\",\"detailDesc\":\"مقدمة مفصلة للنشاط\",\"price\":[],\"issueTime\":\"وقت إصدار التذكرة\",\"hasNightView\":\"نعم/لا\",\"isParentChildFriendly\":\"نعم/لا\",\"isOutdoor\":\"نعم/لا\",\"hasCulturalShow\":\"نعم/لا\",\"hasHotSpring\":\"نعم/لا\"}\n]\nمحتوى المقال:مهرجان الموسيقى في سوق هونغيادونغ الليلي في تشونغتشينغ، الفرق المستقلة تؤدي بالتناوب، منظر النهر الليلي والموسيقى متكاملان بشكل مثالي، الوالدان والأطفال، الأزواج مناسبون لتسجيل الوصول الليلي.",
        "json_schema": {
            "type": "array",
            "items": {
                "type": "object",
                "properties": {
                    "playName": {
                        "type": "string",
                        "description": "اسم النشاط",
                        "能力项": "JSON"
                    },
                    "briefDesc": {
                        "type": "string",
                        "description": "وصف من جملة واحدة",
                        "能力项": "范围、50~200字",
                        "pattern": "^.*$|^$",
                        "minLength": 68,
                        "maxLength": 100
                    },
                    "location": {
                        "type": "string",
                        "description": "الموقع الجغرافي للنشاط",
                        "能力项": "JSON"
                    },
                    "startDate": {
                        "type": "string",
                        "pattern": "^\\d{4}-\\d{2}-\\d{2}$|^$",
                        "能力项": "日期格式",
                        "description": "وقت البداية"
                    },
                    "endDate": {
                        "type": "string",
                        "pattern": "^\\d{4}-\\d{2}-\\d{2}$|^$",
                        "能力项": "日期格式",
                        "description": "وقت النهاية"
                    },
                    "detailDesc": {
                        "type": "string",
                        "description": "مقدمة مفصلة للنشاط",
                        "能力项": "范围、200字以上",
                        "pattern": "^.*$|^$",
                        "minLength": 315,
                        "maxLength": 400
                    },
                    "price": {
                        "type": "array",
                        "description": "معلومات سعر التذكرة",
                        "items": {
                            "type": "string"
                        },
                        "能力项": "主题约束"
                    },
                    "issueTime": {
                        "type": "string",
                        "pattern": "^\\d{4}-\\d{2}-\\d{2}$|^$",
                        "能力项": "日期格式",
                        "description": "وقت إصدار التذكرة"
                    },
                    "hasNightView": {
                        "type": "string",
                        "enum": [
                            "نعم",
                            "لا"
                        ],
                        "description": "ما إذا كان نشاطاً ليلياً",
                        "能力项": "特定格式"
                    },
                    "isParentChildFriendly": {
                        "type": "string",
                        "enum": [
                            "نعم",
                            "لا"
                        ],
                        "description": "ما إذا كان مناسباً للوالدين والطفل",
                        "能力项": "特定格式"
                    },
                    "isOutdoor": {
                        "type": "string",
                        "enum": [
                            "نعم",
                            "لا"
                        ],
                        "description": "ما إذا كان نشاطاً خارجياً",
                        "能力项": "特定格式"
                    },
                    "hasCulturalShow": {
                        "type": "string",
                        "enum": [
                            "نعم",
                            "لا"
                        ],
                        "description": "ما إذا كان يتضمن عروضاً ثقافية",
                        "能力项": "特定格式"
                    },
                    "hasHotSpring": {
                        "type": "string",
                        "enum": [
                            "نعم",
                            "لا"
                        ],
                        "description": "ما إذا كان لديه مشاريع ينابيع ساخنة",
                        "能力项": "特定格式"
                    }
                },
                "required": [
                    "playName",
                    "briefDesc",
                    "location",
                    "startDate",
                    "endDate",
                    "detailDesc",
                    "price",
                    "issueTime",
                    "hasNightView",
                    "isParentChildFriendly",
                    "isOutdoor",
                    "hasCulturalShow",
                    "hasHotSpring"
                ]
            }
        },
        "sub_questions": [
            {
                "point_id": 0,
                "question": "ما إذا كان يلبي المخطط",
                "rule": "SCHEMA:json_schema",
                "dep": [],
                "被依赖": false,
                "能力项": "JSON"
            }
        ]
    },
    {
        "category": "SCHEMA",
        "question": "أنت محلل مقالات مواقع السياحة المحترف. سأقدم لك محتوى المقال ونوع المقال. تحتاج إلى تنفيذ استراتيجيات تحديد مختلفة بناءً على أنواع المقالات المختلفة. أعد فقط معلومات الأنشطة المستخرجة، ولا تعيد أي معلومات زائدة أخرى.\nنوع المقال: التعرف التلقائي\nيرجى استخراج المعلومات وفقاً للقواعد التالية:\n1. playName: اسم النشاط، يشير إلى أسماء الأنشطة أو الفعاليات المحددة المذكورة في المقال.\n2. briefDesc: وصف من جملة واحدة، مطلوب تلخيص نقاط الجذب والميزات للنشاط، باستثناء وقت التشغيل والمعلومات العملية والأوصاف السلبية، 68-100 حرف (تشمل المسافات والأرقام...).\n3. location: الموقع الجغرافي للنشاط، يشير إلى نقاط مرجعية محددة أو معالم داخل المناطق السياحية أو الأماكن، لا يمكن أن تكون مدن أو محافظات.\n4. startDate/endDate: نطاق زمني للنشاط، تنسيق التاريخ هو xxxx-xx-xx، أعد سلسلة فارغة إذا لم يتم التعرف عليه.\n5. detailDesc: مقدمة مفصلة للنشاط، مطلوب 315-400 حرف (تشمل المسافات والأرقام...)، وصف نقاط الجذب والميزات للنشاط، باستثناء كلمات منظور الطرف الثالث.\n6. price: معلومات سعر التذكرة، تنسيق الإرجاع [\"\",\"\"]، أعد قائمة فارغة إذا لم يتم التعرف عليها.\n7. issueTime: إذا كان النشاط ينتمي إلى الحفلات الموسيقية أو المهرجانات الموسيقية أو Livehouse أو الكوميديا وأنواع أخرى، تحتاج إلى تحديد وقت إصدار التذكرة، تنسيق التاريخ هو xxxx-xx-xx، أعد سلسلة فارغة إذا لم يوجد.\n8. hasNightView: ما إذا كان نشاطاً ليلياً (نعم/لا).\n9. isParentChildFriendly: ما إذا كان مناسباً للوالدين والطفل (نعم/لا).\n10. isOutdoor: ما إذا كان نشاطاً خارجياً (نعم/لا).\n11. hasCulturalShow: ما إذا كان يتضمن عروضاً ثقافية (نعم/لا).\n12. hasHotSpring: ما إذا كان لديه مشاريع ينابيع ساخنة (نعم/لا).\nمتطلبات الإخراج:\n1. استخدم تنسيق JSON لإرجاع المعلومات المستخرجة\n2. كل نشاط كائن، يحتوي على جميع الحقول\n3. جميع كائنات الأنشطة تشكل مصفوفة\n4. لا تعيد أي أحرف غير تنسيق JSON\nمثال على تنسيق الإخراج:\n[\n  {\"playName\":\"اسم النشاط\",\"briefDesc\":\"وصف من جملة واحدة\",\"location\":\"الموقع الجغرافي\",\"startDate\":\"وقت البداية\",\"endDate\":\"وقت النهاية\",\"detailDesc\":\"مقدمة مفصلة للنشاط\",\"price\":[],\"issueTime\":\"وقت إصدار التذكرة\",\"hasNightView\":\"نعم/لا\",\"isParentChildFriendly\":\"نعم/لا\",\"isOutdoor\":\"نعم/لا\",\"hasCulturalShow\":\"نعم/لا\",\"hasHotSpring\":\"نعم/لا\"}\n]\nمحتوى المقال:معرض المعبد للسنة الجديدة في مدينة دالي القديمة، رقص باي، سوق شعبي، عرض الألعاب النارية يضيء سماء المدينة القديمة الليلية، تجربة الينابيع الساخنة وطعام السوق الليلي غنية وملونة.",
        "json_schema": {
            "type": "array",
            "items": {
                "type": "object",
                "properties": {
                    "playName": {
                        "type": "string",
                        "description": "اسم النشاط",
                        "能力项": "JSON"
                    },
                    "briefDesc": {
                        "type": "string",
                        "description": "وصف من جملة واحدة",
                        "能力项": "范围、50~200字",
                        "pattern": "^.*$|^$",
                        "minLength": 68,
                        "maxLength": 100
                    },
                    "location": {
                        "type": "string",
                        "description": "الموقع الجغرافي للنشاط",
                        "能力项": "JSON"
                    },
                    "startDate": {
                        "type": "string",
                        "pattern": "^\\d{4}-\\d{2}-\\d{2}$|^$",
                        "能力项": "日期格式",
                        "description": "وقت البداية"
                    },
                    "endDate": {
                        "type": "string",
                        "pattern": "^\\d{4}-\\d{2}-\\d{2}$|^$",
                        "能力项": "日期格式",
                        "description": "وقت النهاية"
                    },
                    "detailDesc": {
                        "type": "string",
                        "description": "مقدمة مفصلة للنشاط",
                        "能力项": "范围、200字以上",
                        "pattern": "^.*$|^$",
                        "minLength": 315,
                        "maxLength": 400
                    },
                    "price": {
                        "type": "array",
                        "description": "معلومات سعر التذكرة",
                        "items": {
                            "type": "string"
                        },
                        "能力项": "主题约束"
                    },
                    "issueTime": {
                        "type": "string",
                        "pattern": "^\\d{4}-\\d{2}-\\d{2}$|^$",
                        "能力项": "日期格式",
                        "description": "وقت إصدار التذكرة"
                    },
                    "hasNightView": {
                        "type": "string",
                        "enum": [
                            "نعم",
                            "لا"
                        ],
                        "description": "ما إذا كان نشاطاً ليلياً",
                        "能力项": "特定格式"
                    },
                    "isParentChildFriendly": {
                        "type": "string",
                        "enum": [
                            "نعم",
                            "لا"
                        ],
                        "description": "ما إذا كان مناسباً للوالدين والطفل",
                        "能力项": "特定格式"
                    },
                    "isOutdoor": {
                        "type": "string",
                        "enum": [
                            "نعم",
                            "لا"
                        ],
                        "description": "ما إذا كان نشاطاً خارجياً",
                        "能力项": "特定格式"
                    },
                    "hasCulturalShow": {
                        "type": "string",
                        "enum": [
                            "نعم",
                            "لا"
                        ],
                        "description": "ما إذا كان يتضمن عروضاً ثقافية",
                        "能力项": "特定格式"
                    },
                    "hasHotSpring": {
                        "type": "string",
                        "enum": [
                            "نعم",
                            "لا"
                        ],
                        "description": "ما إذا كان لديه مشاريع ينابيع ساخنة",
                        "能力项": "特定格式"
                    }
                },
                "required": [
                    "playName",
                    "briefDesc",
                    "location",
                    "startDate",
                    "endDate",
                    "detailDesc",
                    "price",
                    "issueTime",
                    "hasNightView",
                    "isParentChildFriendly",
                    "isOutdoor",
                    "hasCulturalShow",
                    "hasHotSpring"
                ]
            }
        },
        "sub_questions": [
            {
                "point_id": 0,
                "question": "ما إذا كان يلبي المخطط",
                "rule": "SCHEMA:json_schema",
                "dep": [],
                "被依赖": false,
                "能力项": "JSON"
            }
        ]
    },
    {
        "category": "SCHEMA",
        "question": "أنت محلل مقالات مواقع السياحة المحترف. سأقدم لك محتوى المقال ونوع المقال. تحتاج إلى تنفيذ استراتيجيات تحديد مختلفة بناءً على أنواع المقالات المختلفة. أعد فقط معلومات الأنشطة المستخرجة، ولا تعيد أي معلومات زائدة أخرى.\nنوع المقال: التعرف التلقائي\nيرجى استخراج المعلومات وفقاً للقواعد التالية:\n1. playName: اسم النشاط، يشير إلى أسماء الأنشطة أو الفعاليات المحددة المذكورة في المقال.\n2. briefDesc: وصف من جملة واحدة، مطلوب تلخيص نقاط الجذب والميزات للنشاط، باستثناء وقت التشغيل والمعلومات العملية والأوصاف السلبية، 68-100 حرف (تشمل المسافات والأرقام...).\n3. location: الموقع الجغرافي للنشاط، يشير إلى نقاط مرجعية محددة أو معالم داخل المناطق السياحية أو الأماكن، لا يمكن أن تكون مدن أو محافظات.\n4. startDate/endDate: نطاق زمني للنشاط، تنسيق التاريخ هو xxxx-xx-xx، أعد سلسلة فارغة إذا لم يتم التعرف عليه.\n5. detailDesc: مقدمة مفصلة للنشاط، مطلوب 315-400 حرف (تشمل المسافات والأرقام...)، وصف نقاط الجذب والميزات للنشاط، باستثناء كلمات منظور الطرف الثالث.\n6. price: معلومات سعر التذكرة، تنسيق الإرجاع [\"\",\"\"]، أعد قائمة فارغة إذا لم يتم التعرف عليها.\n7. issueTime: إذا كان النشاط ينتمي إلى الحفلات الموسيقية أو المهرجانات الموسيقية أو Livehouse أو الكوميديا وأنواع أخرى، تحتاج إلى تحديد وقت إصدار التذكرة، تنسيق التاريخ هو xxxx-xx-xx، أعد سلسلة فارغة إذا لم يوجد.\n8. hasNightView: ما إذا كان نشاطاً ليلياً (نعم/لا).\n9. isParentChildFriendly: ما إذا كان مناسباً للوالدين والطفل (نعم/لا).\n10. isOutdoor: ما إذا كان نشاطاً خارجياً (نعم/لا).\n11. hasCulturalShow: ما إذا كان يتضمن عروضاً ثقافية (نعم/لا).\n12. hasHotSpring: ما إذا كان لديه مشاريع ينابيع ساخنة (نعم/لا).\nمتطلبات الإخراج:\n1. استخدم تنسيق JSON لإرجاع المعلومات المستخرجة\n2. كل نشاط كائن، يحتوي على جميع الحقول\n3. جميع كائنات الأنشطة تشكل مصفوفة\n4. لا تعيد أي أحرف غير تنسيق JSON\nمثال على تنسيق الإخراج:\n[\n  {\"playName\":\"اسم النشاط\",\"briefDesc\":\"وصف من جملة واحدة\",\"location\":\"الموقع الجغرافي\",\"startDate\":\"وقت البداية\",\"endDate\":\"وقت النهاية\",\"detailDesc\":\"مقدمة مفصلة للنشاط\",\"price\":[],\"issueTime\":\"وقت إصدار التذكرة\",\"hasNightView\":\"نعم/لا\",\"isParentChildFriendly\":\"نعم/لا\",\"isOutdoor\":\"نعم/لا\",\"hasCulturalShow\":\"نعم/لا\",\"hasHotSpring\":\"نعم/لا\"}\n]\nمحتوى المقال:جولة علمية للوالدين والطفل في قاعدة الباندا في تشنغدو، شرح الباندا، تجربة الصنع اليدوي، هدايا تذكارية موضوعية غنية وملونة، الحديقة لديها عرض أضواء ليلي صغير.",
        "json_schema": {
            "type": "array",
            "items": {
                "type": "object",
                "properties": {
                    "playName": {
                        "type": "string",
                        "description": "اسم النشاط",
                        "能力项": "JSON"
                    },
                    "briefDesc": {
                        "type": "string",
                        "description": "وصف من جملة واحدة",
                        "能力项": "范围、50~200字",
                        "pattern": "^.*$|^$",
                        "minLength": 68,
                        "maxLength": 100
                    },
                    "location": {
                        "type": "string",
                        "description": "الموقع الجغرافي للنشاط",
                        "能力项": "JSON"
                    },
                    "startDate": {
                        "type": "string",
                        "pattern": "^\\d{4}-\\d{2}-\\d{2}$|^$",
                        "能力项": "日期格式",
                        "description": "وقت البداية"
                    },
                    "endDate": {
                        "type": "string",
                        "pattern": "^\\d{4}-\\d{2}-\\d{2}$|^$",
                        "能力项": "日期格式",
                        "description": "وقت النهاية"
                    },
                    "detailDesc": {
                        "type": "string",
                        "description": "مقدمة مفصلة للنشاط",
                        "能力项": "范围、200字以上",
                        "pattern": "^.*$|^$",
                        "minLength": 315,
                        "maxLength": 400
                    },
                    "price": {
                        "type": "array",
                        "description": "معلومات سعر التذكرة",
                        "items": {
                            "type": "string"
                        },
                        "能力项": "主题约束"
                    },
                    "issueTime": {
                        "type": "string",
                        "pattern": "^\\d{4}-\\d{2}-\\d{2}$|^$",
                        "能力项": "日期格式",
                        "description": "وقت إصدار التذكرة"
                    },
                    "hasNightView": {
                        "type": "string",
                        "enum": [
                            "نعم",
                            "لا"
                        ],
                        "description": "ما إذا كان نشاطاً ليلياً",
                        "能力项": "特定格式"
                    },
                    "isParentChildFriendly": {
                        "type": "string",
                        "enum": [
                            "نعم",
                            "لا"
                        ],
                        "description": "ما إذا كان مناسباً للوالدين والطفل",
                        "能力项": "特定格式"
                    },
                    "isOutdoor": {
                        "type": "string",
                        "enum": [
                            "نعم",
                            "لا"
                        ],
                        "description": "ما إذا كان نشاطاً خارجياً",
                        "能力项": "特定格式"
                    },
                    "hasCulturalShow": {
                        "type": "string",
                        "enum": [
                            "نعم",
                            "لا"
                        ],
                        "description": "ما إذا كان يتضمن عروضاً ثقافية",
                        "能力项": "特定格式"
                    },
                    "hasHotSpring": {
                        "type": "string",
                        "enum": [
                            "نعم",
                            "لا"
                        ],
                        "description": "ما إذا كان لديه مشاريع ينابيع ساخنة",
                        "能力项": "特定格式"
                    }
                },
                "required": [
                    "playName",
                    "briefDesc",
                    "location",
                    "startDate",
                    "endDate",
                    "detailDesc",
                    "price",
                    "issueTime",
                    "hasNightView",
                    "isParentChildFriendly",
                    "isOutdoor",
                    "hasCulturalShow",
                    "hasHotSpring"
                ]
            }
        },
        "sub_questions": [
            {
                "point_id": 0,
                "question": "ما إذا كان يلبي المخطط",
                "rule": "SCHEMA:json_schema",
                "dep": [],
                "被依赖": false,
                "能力项": "JSON"
            }
        ]
    }
]