[
    {
        "category": "SCHEMA",
        "question": "Você é um analista profissional de artigos sobre pontos turísticos. Fornecerei conteúdo do artigo e tipo de artigo. Você precisa executar diferentes estratégias de identificação baseadas em diferentes tipos de artigos. Retorne apenas as informações de atividades extraídas, não retorne nenhuma outra informação redundante.\nTipo de artigo: Auto-identificar\nPor favor, extraia informações de acordo com as seguintes regras:\n1. nomeAtividade: Nome da atividade, referindo-se a nomes específicos de atividades ou jogos mencionados no artigo.\n2. descricaoBreve: Descrição de uma frase, necessária para resumir destaques e características da atividade, excluindo horário operacional, informações práticas, descrições negativas, 68-100 caracteres (incluindo espaços, números...).\n3. localizacao: Localização geográfica da atividade, referindo-se a pontos de referência específicos ou marcos dentro de áreas cênicas ou locais, não pode ser cidades ou províncias.\n4. dataInicio/dataFim: Período de tempo da atividade, formato de data é xxxx-xx-xx, retorne string vazia se não identificado.\n5. descricaoDetalhada: Introdução detalhada da atividade, necessária 315-400 caracteres (incluindo espaços, números...), descrevendo destaques e características da atividade, excluindo palavras de perspectiva de terceiros.\n6. preco: Informações de preço do ingresso, formato de retorno [\"\",\"\"], retorne lista vazia se não identificado.\n7. tempoLancamento: Se a atividade pertence a concertos, festivais de música, Livehouse, comédia e outros tipos, precisa identificar o tempo de lançamento do ingresso, formato de data é xxxx-xx-xx, retorne string vazia se nenhum.\n8. temVistanoturna: Se é uma atividade noturna (Sim/Não).\n9. adequadoFamilias: Se é adequado para pais e filhos (Sim/Não).\n10. aoArLivre: Se é atividade ao ar livre (Sim/Não).\n11. temEspetaculoCultural: Se inclui apresentações culturais (Sim/Não).\n12. temTermas: Se tem projetos de águas termais (Sim/Não).\nRequisitos de saída:\n1. Use formato JSON para retornar informações extraídas\n2. Cada atividade como um objeto, contendo todos os campos\n3. Todos os objetos de atividade formam um array\n4. Não retorne nenhum caractere além do formato JSON\nExemplo de formato de saída:\n[\n  {\"nomeAtividade\":\"Nome da Atividade\",\"descricaoBreve\":\"Descrição de uma frase\",\"localizacao\":\"Localização geográfica\",\"dataInicio\":\"Tempo de início\",\"dataFim\":\"Tempo de fim\",\"descricaoDetalhada\":\"Introdução detalhada da atividade\",\"preco\":[],\"tempoLancamento\":\"Tempo de lançamento do ingresso\",\"temVistanoturna\":\"Sim/Não\",\"adequadoFamilias\":\"Sim/Não\",\"aoArLivre\":\"Sim/Não\",\"temEspetaculoCultural\":\"Sim/Não\",\"temTermas\":\"Sim/Não\"}\n]\nConteúdo do artigo:O Mercado de Natal Noturno do Instituto de Engenharia Mecânica e Elétrica de Sanlitun está aberto! Mercado de Inverno Wood Eats Talk, Desfile de Sobremesas Noturnas, Apresentação de Gravadora Musical Independente, 90 horas de experiência musical ininterrupta, atmosfera natalina e comida reunidas. Há também áreas de interação entre pais e filhos e oficinas de mercado.",
        "json_schema": {
            "type": "array",
            "items": {
                "type": "object",
                "properties": {
                    "nomeAtividade": {
                        "type": "string",
                        "description": "Nome da atividade",
                        "能力项": "JSON"
                    },
                    "descricaoBreve": {
                        "type": "string",
                        "description": "Descrição de uma frase",
                        "能力项": "范围、50~200字",
                        "pattern": "^.*$|^$",
                        "minLength": 68,
                        "maxLength": 100
                    },
                    "localizacao": {
                        "type": "string",
                        "description": "Localização geográfica da atividade",
                        "能力项": "JSON"
                    },
                    "dataInicio": {
                        "type": "string",
                        "pattern": "^\\d{4}-\\d{2}-\\d{2}$|^$",
                        "能力项": "日期格式",
                        "description": "Tempo de início"
                    },
                    "dataFim": {
                        "type": "string",
                        "pattern": "^\\d{4}-\\d{2}-\\d{2}$|^$",
                        "能力项": "日期格式",
                        "description": "Tempo de fim"
                    },
                    "descricaoDetalhada": {
                        "type": "string",
                        "description": "Introdução detalhada da atividade",
                        "能力项": "范围、200字以上",
                        "pattern": "^.*$|^$",
                        "minLength": 315,
                        "maxLength": 400
                    },
                    "preco": {
                        "type": "array",
                        "description": "Informações de preço do ingresso",
                        "items": {
                            "type": "string"
                        },
                        "能力项": "主题约束"
                    },
                    "tempoLancamento": {
                        "type": "string",
                        "pattern": "^\\d{4}-\\d{2}-\\d{2}$|^$",
                        "能力项": "日期格式",
                        "description": "Tempo de lançamento do ingresso"
                    },
                    "temVistanoturna": {
                        "type": "string",
                        "enum": [
                            "Sim",
                            "Não"
                        ],
                        "description": "Se é uma atividade noturna",
                        "能力项": "特定格式"
                    },
                    "adequadoFamilias": {
                        "type": "string",
                        "enum": [
                            "Sim",
                            "Não"
                        ],
                        "description": "Se é adequado para pais e filhos",
                        "能力项": "特定格式"
                    },
                    "aoArLivre": {
                        "type": "string",
                        "enum": [
                            "Sim",
                            "Não"
                        ],
                        "description": "Se é atividade ao ar livre",
                        "能力项": "特定格式"
                    },
                    "temEspetaculoCultural": {
                        "type": "string",
                        "enum": [
                            "Sim",
                            "Não"
                        ],
                        "description": "Se inclui apresentações culturais",
                        "能力项": "特定格式"
                    },
                    "temTermas": {
                        "type": "string",
                        "enum": [
                            "Sim",
                            "Não"
                        ],
                        "description": "Se tem projetos de águas termais",
                        "能力项": "特定格式"
                    }
                },
                "required": [
                    "nomeAtividade",
                    "descricaoBreve",
                    "localizacao",
                    "dataInicio",
                    "dataFim",
                    "descricaoDetalhada",
                    "preco",
                    "tempoLancamento",
                    "temVistanoturna",
                    "adequadoFamilias",
                    "aoArLivre",
                    "temEspetaculoCultural",
                    "temTermas"
                ]
            }
        },
        "sub_questions": [
            {
                "point_id": 0,
                "question": "Se atende ao schema",
                "rule": "SCHEMA:json_schema",
                "dep": [],
                "被依赖": false,
                "能力项": "JSON"
            }
        ]
    },
    {
        "category": "SCHEMA",
        "question": "Você é um analista profissional de artigos sobre pontos turísticos. Fornecerei conteúdo do artigo e tipo de artigo. Você precisa executar diferentes estratégias de identificação baseadas em diferentes tipos de artigos. Retorne apenas as informações de atividades extraídas, não retorne nenhuma outra informação redundante.\nTipo de artigo: Auto-identificar\nPor favor, extraia informações de acordo com as seguintes regras:\n1. nomeAtividade: Nome da atividade, referindo-se a nomes específicos de atividades ou jogos mencionados no artigo.\n2. descricaoBreve: Descrição de uma frase, necessária para resumir destaques e características da atividade, excluindo horário operacional, informações práticas, descrições negativas, 68-100 caracteres (incluindo espaços, números...).\n3. localizacao: Localização geográfica da atividade, referindo-se a pontos de referência específicos ou marcos dentro de áreas cênicas ou locais, não pode ser cidades ou províncias.\n4. dataInicio/dataFim: Período de tempo da atividade, formato de data é xxxx-xx-xx, retorne string vazia se não identificado.\n5. descricaoDetalhada: Introdução detalhada da atividade, necessária 315-400 caracteres (incluindo espaços, números...), descrevendo destaques e características da atividade, excluindo palavras de perspectiva de terceiros.\n6. preco: Informações de preço do ingresso, formato de retorno [\"\",\"\"], retorne lista vazia se não identificado.\n7. tempoLancamento: Se a atividade pertence a concertos, festivais de música, Livehouse, comédia e outros tipos, precisa identificar o tempo de lançamento do ingresso, formato de data é xxxx-xx-xx, retorne string vazia se nenhum.\n8. temVistanoturna: Se é uma atividade noturna (Sim/Não).\n9. adequadoFamilias: Se é adequado para pais e filhos (Sim/Não).\n10. aoArLivre: Se é atividade ao ar livre (Sim/Não).\n11. temEspetaculoCultural: Se inclui apresentações culturais (Sim/Não).\n12. temTermas: Se tem projetos de águas termais (Sim/Não).\nRequisitos de saída:\n1. Use formato JSON para retornar informações extraídas\n2. Cada atividade como um objeto, contendo todos os campos\n3. Todos os objetos de atividade formam um array\n4. Não retorne nenhum caractere além do formato JSON\nExemplo de formato de saída:\n[\n  {\"nomeAtividade\":\"Nome da Atividade\",\"descricaoBreve\":\"Descrição de uma frase\",\"localizacao\":\"Localização geográfica\",\"dataInicio\":\"Tempo de início\",\"dataFim\":\"Tempo de fim\",\"descricaoDetalhada\":\"Introdução detalhada da atividade\",\"preco\":[],\"tempoLancamento\":\"Tempo de lançamento do ingresso\",\"temVistanoturna\":\"Sim/Não\",\"adequadoFamilias\":\"Sim/Não\",\"aoArLivre\":\"Sim/Não\",\"temEspetaculoCultural\":\"Sim/Não\",\"temTermas\":\"Sim/Não\"}\n]\nConteúdo do artigo:O Show de Luzes de Natal do Happy Valley está aberto, há apresentações de desfile em grande escala e mercados temáticos de Natal à noite, pais e filhos, casais, amigos podem se divertir, a vista noturna ao ar livre é inesquecível.",
        "json_schema": {
            "type": "array",
            "items": {
                "type": "object",
                "properties": {
                    "nomeAtividade": {
                        "type": "string",
                        "description": "Nome da atividade",
                        "能力项": "JSON"
                    },
                    "descricaoBreve": {
                        "type": "string",
                        "description": "Descrição de uma frase",
                        "能力项": "范围、50~200字",
                        "pattern": "^.*$|^$",
                        "minLength": 68,
                        "maxLength": 100
                    },
                    "localizacao": {
                        "type": "string",
                        "description": "Localização geográfica da atividade",
                        "能力项": "JSON"
                    },
                    "dataInicio": {
                        "type": "string",
                        "pattern": "^\\d{4}-\\d{2}-\\d{2}$|^$",
                        "能力项": "日期格式",
                        "description": "Tempo de início"
                    },
                    "dataFim": {
                        "type": "string",
                        "pattern": "^\\d{4}-\\d{2}-\\d{2}$|^$",
                        "能力项": "日期格式",
                        "description": "Tempo de fim"
                    },
                    "descricaoDetalhada": {
                        "type": "string",
                        "description": "Introdução detalhada da atividade",
                        "能力项": "范围、200字以上",
                        "pattern": "^.*$|^$",
                        "minLength": 315,
                        "maxLength": 400
                    },
                    "preco": {
                        "type": "array",
                        "description": "Informações de preço do ingresso",
                        "items": {
                            "type": "string"
                        },
                        "能力项": "主题约束"
                    },
                    "tempoLancamento": {
                        "type": "string",
                        "pattern": "^\\d{4}-\\d{2}-\\d{2}$|^$",
                        "能力项": "日期格式",
                        "description": "Tempo de lançamento do ingresso"
                    },
                    "temVistanoturna": {
                        "type": "string",
                        "enum": [
                            "Sim",
                            "Não"
                        ],
                        "description": "Se é uma atividade noturna",
                        "能力项": "特定格式"
                    },
                    "adequadoFamilias": {
                        "type": "string",
                        "enum": [
                            "Sim",
                            "Não"
                        ],
                        "description": "Se é adequado para pais e filhos",
                        "能力项": "特定格式"
                    },
                    "aoArLivre": {
                        "type": "string",
                        "enum": [
                            "Sim",
                            "Não"
                        ],
                        "description": "Se é atividade ao ar livre",
                        "能力项": "特定格式"
                    },
                    "temEspetaculoCultural": {
                        "type": "string",
                        "enum": [
                            "Sim",
                            "Não"
                        ],
                        "description": "Se inclui apresentações culturais",
                        "能力项": "特定格式"
                    },
                    "temTermas": {
                        "type": "string",
                        "enum": [
                            "Sim",
                            "Não"
                        ],
                        "description": "Se tem projetos de águas termais",
                        "能力项": "特定格式"
                    }
                },
                "required": [
                    "nomeAtividade",
                    "descricaoBreve",
                    "localizacao",
                    "dataInicio",
                    "dataFim",
                    "descricaoDetalhada",
                    "preco",
                    "tempoLancamento",
                    "temVistanoturna",
                    "adequadoFamilias",
                    "aoArLivre",
                    "temEspetaculoCultural",
                    "temTermas"
                ]
            }
        },
        "sub_questions": [
            {
                "point_id": 0,
                "question": "Se atende ao schema",
                "rule": "SCHEMA:json_schema",
                "dep": [],
                "被依赖": false,
                "能力项": "JSON"
            }
        ]
    },
    {
        "category": "SCHEMA",
        "question": "Você é um analista profissional de artigos sobre pontos turísticos. Fornecerei conteúdo do artigo e tipo de artigo. Você precisa executar diferentes estratégias de identificação baseadas em diferentes tipos de artigos. Retorne apenas as informações de atividades extraídas, não retorne nenhuma outra informação redundante.\nTipo de artigo: Auto-identificar\nPor favor, extraia informações de acordo com as seguintes regras:\n1. nomeAtividade: Nome da atividade, referindo-se a nomes específicos de atividades ou jogos mencionados no artigo.\n2. descricaoBreve: Descrição de uma frase, necessária para resumir destaques e características da atividade, excluindo horário operacional, informações práticas, descrições negativas, 68-100 caracteres (incluindo espaços, números...).\n3. localizacao: Localização geográfica da atividade, referindo-se a pontos de referência específicos ou marcos dentro de áreas cênicas ou locais, não pode ser cidades ou províncias.\n4. dataInicio/dataFim: Período de tempo da atividade, formato de data é xxxx-xx-xx, retorne string vazia se não identificado.\n5. descricaoDetalhada: Introdução detalhada da atividade, necessária 315-400 caracteres (incluindo espaços, números...), descrevendo destaques e características da atividade, excluindo palavras de perspectiva de terceiros.\n6. preco: Informações de preço do ingresso, formato de retorno [\"\",\"\"], retorne lista vazia se não identificado.\n7. tempoLancamento: Se a atividade pertence a concertos, festivais de música, Livehouse, comédia e outros tipos, precisa identificar o tempo de lançamento do ingresso, formato de data é xxxx-xx-xx, retorne string vazia se nenhum.\n8. temVistanoturna: Se é uma atividade noturna (Sim/Não).\n9. adequadoFamilias: Se é adequado para pais e filhos (Sim/Não).\n10. aoArLivre: Se é atividade ao ar livre (Sim/Não).\n11. temEspetaculoCultural: Se inclui apresentações culturais (Sim/Não).\n12. temTermas: Se tem projetos de águas termais (Sim/Não).\nRequisitos de saída:\n1. Use formato JSON para retornar informações extraídas\n2. Cada atividade como um objeto, contendo todos os campos\n3. Todos os objetos de atividade formam um array\n4. Não retorne nenhum caractere além do formato JSON\nExemplo de formato de saída:\n[\n  {\"nomeAtividade\":\"Nome da Atividade\",\"descricaoBreve\":\"Descrição de uma frase\",\"localizacao\":\"Localização geográfica\",\"dataInicio\":\"Tempo de início\",\"dataFim\":\"Tempo de fim\",\"descricaoDetalhada\":\"Introdução detalhada da atividade\",\"preco\":[],\"tempoLancamento\":\"Tempo de lançamento do ingresso\",\"temVistanoturna\":\"Sim/Não\",\"adequadoFamilias\":\"Sim/Não\",\"aoArLivre\":\"Sim/Não\",\"temEspetaculoCultural\":\"Sim/Não\",\"temTermas\":\"Sim/Não\"}\n]\nConteúdo do artigo:O Festival de Gelo e Neve da Cidade Proibida abre, exposições de esculturas de gelo, tobogãs de neve, bicicletas de gelo e outras formas ricas de brincar estão esperando você experimentar, o show de luzes noturnas é romântico e sonhador. Toda a família pode encontrar diversão.",
        "json_schema": {
            "type": "array",
            "items": {
                "type": "object",
                "properties": {
                    "nomeAtividade": {
                        "type": "string",
                        "description": "Nome da atividade",
                        "能力项": "JSON"
                    },
                    "descricaoBreve": {
                        "type": "string",
                        "description": "Descrição de uma frase",
                        "能力项": "范围、50~200字",
                        "pattern": "^.*$|^$",
                        "minLength": 68,
                        "maxLength": 100
                    },
                    "localizacao": {
                        "type": "string",
                        "description": "Localização geográfica da atividade",
                        "能力项": "JSON"
                    },
                    "dataInicio": {
                        "type": "string",
                        "pattern": "^\\d{4}-\\d{2}-\\d{2}$|^$",
                        "能力项": "日期格式",
                        "description": "Tempo de início"
                    },
                    "dataFim": {
                        "type": "string",
                        "pattern": "^\\d{4}-\\d{2}-\\d{2}$|^$",
                        "能力项": "日期格式",
                        "description": "Tempo de fim"
                    },
                    "descricaoDetalhada": {
                        "type": "string",
                        "description": "Introdução detalhada da atividade",
                        "能力项": "范围、200字以上",
                        "pattern": "^.*$|^$",
                        "minLength": 315,
                        "maxLength": 400
                    },
                    "preco": {
                        "type": "array",
                        "description": "Informações de preço do ingresso",
                        "items": {
                            "type": "string"
                        },
                        "能力项": "主题约束"
                    },
                    "tempoLancamento": {
                        "type": "string",
                        "pattern": "^\\d{4}-\\d{2}-\\d{2}$|^$",
                        "能力项": "日期格式",
                        "description": "Tempo de lançamento do ingresso"
                    },
                    "temVistanoturna": {
                        "type": "string",
                        "enum": [
                            "Sim",
                            "Não"
                        ],
                        "description": "Se é uma atividade noturna",
                        "能力项": "特定格式"
                    },
                    "adequadoFamilias": {
                        "type": "string",
                        "enum": [
                            "Sim",
                            "Não"
                        ],
                        "description": "Se é adequado para pais e filhos",
                        "能力项": "特定格式"
                    },
                    "aoArLivre": {
                        "type": "string",
                        "enum": [
                            "Sim",
                            "Não"
                        ],
                        "description": "Se é atividade ao ar livre",
                        "能力项": "特定格式"
                    },
                    "temEspetaculoCultural": {
                        "type": "string",
                        "enum": [
                            "Sim",
                            "Não"
                        ],
                        "description": "Se inclui apresentações culturais",
                        "能力项": "特定格式"
                    },
                    "temTermas": {
                        "type": "string",
                        "enum": [
                            "Sim",
                            "Não"
                        ],
                        "description": "Se tem projetos de águas termais",
                        "能力项": "特定格式"
                    }
                },
                "required": [
                    "nomeAtividade",
                    "descricaoBreve",
                    "localizacao",
                    "dataInicio",
                    "dataFim",
                    "descricaoDetalhada",
                    "preco",
                    "tempoLancamento",
                    "temVistanoturna",
                    "adequadoFamilias",
                    "aoArLivre",
                    "temEspetaculoCultural",
                    "temTermas"
                ]
            }
        },
        "sub_questions": [
            {
                "point_id": 0,
                "question": "Se atende ao schema",
                "rule": "SCHEMA:json_schema",
                "dep": [],
                "被依赖": false,
                "能力项": "JSON"
            }
        ]
    },
    {
        "category": "SCHEMA",
        "question": "Você é um analista profissional de artigos sobre pontos turísticos. Fornecerei conteúdo do artigo e tipo de artigo. Você precisa executar diferentes estratégias de identificação baseadas em diferentes tipos de artigos. Retorne apenas as informações de atividades extraídas, não retorne nenhuma outra informação redundante.\nTipo de artigo: Auto-identificar\nPor favor, extraia informações de acordo com as seguintes regras:\n1. nomeAtividade: Nome da atividade, referindo-se a nomes específicos de atividades ou jogos mencionados no artigo.\n2. descricaoBreve: Descrição de uma frase, necessária para resumir destaques e características da atividade, excluindo horário operacional, informações práticas, descrições negativas, 68-100 caracteres (incluindo espaços, números...).\n3. localizacao: Localização geográfica da atividade, referindo-se a pontos de referência específicos ou marcos dentro de áreas cênicas ou locais, não pode ser cidades ou províncias.\n4. dataInicio/dataFim: Período de tempo da atividade, formato de data é xxxx-xx-xx, retorne string vazia se não identificado.\n5. descricaoDetalhada: Introdução detalhada da atividade, necessária 315-400 caracteres (incluindo espaços, números...), descrevendo destaques e características da atividade, excluindo palavras de perspectiva de terceiros.\n6. preco: Informações de preço do ingresso, formato de retorno [\"\",\"\"], retorne lista vazia se não identificado.\n7. tempoLancamento: Se a atividade pertence a concertos, festivais de música, Livehouse, comédia e outros tipos, precisa identificar o tempo de lançamento do ingresso, formato de data é xxxx-xx-xx, retorne string vazia se nenhum.\n8. temVistanoturna: Se é uma atividade noturna (Sim/Não).\n9. adequadoFamilias: Se é adequado para pais e filhos (Sim/Não).\n10. aoArLivre: Se é atividade ao ar livre (Sim/Não).\n11. temEspetaculoCultural: Se inclui apresentações culturais (Sim/Não).\n12. temTermas: Se tem projetos de águas termais (Sim/Não).\nRequisitos de saída:\n1. Use formato JSON para retornar informações extraídas\n2. Cada atividade como um objeto, contendo todos os campos\n3. Todos os objetos de atividade formam um array\n4. Não retorne nenhum caractere além do formato JSON\nExemplo de formato de saída:\n[\n  {\"nomeAtividade\":\"Nome da Atividade\",\"descricaoBreve\":\"Descrição de uma frase\",\"localizacao\":\"Localização geográfica\",\"dataInicio\":\"Tempo de início\",\"dataFim\":\"Tempo de fim\",\"descricaoDetalhada\":\"Introdução detalhada da atividade\",\"preco\":[],\"tempoLancamento\":\"Tempo de lançamento do ingresso\",\"temVistanoturna\":\"Sim/Não\",\"adequadoFamilias\":\"Sim/Não\",\"aoArLivre\":\"Sim/Não\",\"temEspetaculoCultural\":\"Sim/Não\",\"temTermas\":\"Sim/Não\"}\n]\nConteúdo do artigo:Show de Fogos de Artifício de Ano Novo dos Universal Studios, o melhor ponto de observação é Hollywood Boulevard, fogos de artifício e edifícios temáticos estão no mesmo quadro, a atmosfera é explosiva, adequado para encontros de casais e experiência entre pais e filhos.",
        "json_schema": {
            "type": "array",
            "items": {
                "type": "object",
                "properties": {
                    "nomeAtividade": {
                        "type": "string",
                        "description": "Nome da atividade",
                        "能力项": "JSON"
                    },
                    "descricaoBreve": {
                        "type": "string",
                        "description": "Descrição de uma frase",
                        "能力项": "范围、50~200字",
                        "pattern": "^.*$|^$",
                        "minLength": 68,
                        "maxLength": 100
                    },
                    "localizacao": {
                        "type": "string",
                        "description": "Localização geográfica da atividade",
                        "能力项": "JSON"
                    },
                    "dataInicio": {
                        "type": "string",
                        "pattern": "^\\d{4}-\\d{2}-\\d{2}$|^$",
                        "能力项": "日期格式",
                        "description": "Tempo de início"
                    },
                    "dataFim": {
                        "type": "string",
                        "pattern": "^\\d{4}-\\d{2}-\\d{2}$|^$",
                        "能力项": "日期格式",
                        "description": "Tempo de fim"
                    },
                    "descricaoDetalhada": {
                        "type": "string",
                        "description": "Introdução detalhada da atividade",
                        "能力项": "范围、200字以上",
                        "pattern": "^.*$|^$",
                        "minLength": 315,
                        "maxLength": 400
                    },
                    "preco": {
                        "type": "array",
                        "description": "Informações de preço do ingresso",
                        "items": {
                            "type": "string"
                        },
                        "能力项": "主题约束"
                    },
                    "tempoLancamento": {
                        "type": "string",
                        "pattern": "^\\d{4}-\\d{2}-\\d{2}$|^$",
                        "能力项": "日期格式",
                        "description": "Tempo de lançamento do ingresso"
                    },
                    "temVistanoturna": {
                        "type": "string",
                        "enum": [
                            "Sim",
                            "Não"
                        ],
                        "description": "Se é uma atividade noturna",
                        "能力项": "特定格式"
                    },
                    "adequadoFamilias": {
                        "type": "string",
                        "enum": [
                            "Sim",
                            "Não"
                        ],
                        "description": "Se é adequado para pais e filhos",
                        "能力项": "特定格式"
                    },
                    "aoArLivre": {
                        "type": "string",
                        "enum": [
                            "Sim",
                            "Não"
                        ],
                        "description": "Se é atividade ao ar livre",
                        "能力项": "特定格式"
                    },
                    "temEspetaculoCultural": {
                        "type": "string",
                        "enum": [
                            "Sim",
                            "Não"
                        ],
                        "description": "Se inclui apresentações culturais",
                        "能力项": "特定格式"
                    },
                    "temTermas": {
                        "type": "string",
                        "enum": [
                            "Sim",
                            "Não"
                        ],
                        "description": "Se tem projetos de águas termais",
                        "能力项": "特定格式"
                    }
                },
                "required": [
                    "nomeAtividade",
                    "descricaoBreve",
                    "localizacao",
                    "dataInicio",
                    "dataFim",
                    "descricaoDetalhada",
                    "preco",
                    "tempoLancamento",
                    "temVistanoturna",
                    "adequadoFamilias",
                    "aoArLivre",
                    "temEspetaculoCultural",
                    "temTermas"
                ]
            }
        },
        "sub_questions": [
            {
                "point_id": 0,
                "question": "Se atende ao schema",
                "rule": "SCHEMA:json_schema",
                "dep": [],
                "被依赖": false,
                "能力项": "JSON"
            }
        ]
    },
    {
        "category": "SCHEMA",
        "question": "Você é um analista profissional de artigos sobre pontos turísticos. Fornecerei conteúdo do artigo e tipo de artigo. Você precisa executar diferentes estratégias de identificação baseadas em diferentes tipos de artigos. Retorne apenas as informações de atividades extraídas, não retorne nenhuma outra informação redundante.\nTipo de artigo: Auto-identificar\nPor favor, extraia informações de acordo com as seguintes regras:\n1. nomeAtividade: Nome da atividade, referindo-se a nomes específicos de atividades ou jogos mencionados no artigo.\n2. descricaoBreve: Descrição de uma frase, necessária para resumir destaques e características da atividade, excluindo horário operacional, informações práticas, descrições negativas, 68-100 caracteres (incluindo espaços, números...).\n3. localizacao: Localização geográfica da atividade, referindo-se a pontos de referência específicos ou marcos dentro de áreas cênicas ou locais, não pode ser cidades ou províncias.\n4. dataInicio/dataFim: Período de tempo da atividade, formato de data é xxxx-xx-xx, retorne string vazia se não identificado.\n5. descricaoDetalhada: Introdução detalhada da atividade, necessária 315-400 caracteres (incluindo espaços, números...), descrevendo destaques e características da atividade, excluindo palavras de perspectiva de terceiros.\n6. preco: Informações de preço do ingresso, formato de retorno [\"\",\"\"], retorne lista vazia se não identificado.\n7. tempoLancamento: Se a atividade pertence a concertos, festivais de música, Livehouse, comédia e outros tipos, precisa identificar o tempo de lançamento do ingresso, formato de data é xxxx-xx-xx, retorne string vazia se nenhum.\n8. temVistanoturna: Se é uma atividade noturna (Sim/Não).\n9. adequadoFamilias: Se é adequado para pais e filhos (Sim/Não).\n10. aoArLivre: Se é atividade ao ar livre (Sim/Não).\n11. temEspetaculoCultural: Se inclui apresentações culturais (Sim/Não).\n12. temTermas: Se tem projetos de águas termais (Sim/Não).\nRequisitos de saída:\n1. Use formato JSON para retornar informações extraídas\n2. Cada atividade como um objeto, contendo todos os campos\n3. Todos os objetos de atividade formam um array\n4. Não retorne nenhum caractere além do formato JSON\nExemplo de formato de saída:\n[\n  {\"nomeAtividade\":\"Nome da Atividade\",\"descricaoBreve\":\"Descrição de uma frase\",\"localizacao\":\"Localização geográfica\",\"dataInicio\":\"Tempo de início\",\"dataFim\":\"Tempo de fim\",\"descricaoDetalhada\":\"Introdução detalhada da atividade\",\"preco\":[],\"tempoLancamento\":\"Tempo de lançamento do ingresso\",\"temVistanoturna\":\"Sim/Não\",\"adequadoFamilias\":\"Sim/Não\",\"aoArLivre\":\"Sim/Não\",\"temEspetaculoCultural\":\"Sim/Não\",\"temTermas\":\"Sim/Não\"}\n]\nConteúdo do artigo:O Festival do Barco Dragão do Lago Oeste começa no Festival do Barco Dragão, corrida de barcos dragão, apresentações folclóricas, comida do Festival do Barco Dragão estão todas disponíveis, a experiência de visualização da margem é excelente, há shows de luz e água à noite.",
        "json_schema": {
            "type": "array",
            "items": {
                "type": "object",
                "properties": {
                    "nomeAtividade": {
                        "type": "string",
                        "description": "Nome da atividade",
                        "能力项": "JSON"
                    },
                    "descricaoBreve": {
                        "type": "string",
                        "description": "Descrição de uma frase",
                        "能力项": "范围、50~200字",
                        "pattern": "^.*$|^$",
                        "minLength": 68,
                        "maxLength": 100
                    },
                    "localizacao": {
                        "type": "string",
                        "description": "Localização geográfica da atividade",
                        "能力项": "JSON"
                    },
                    "dataInicio": {
                        "type": "string",
                        "pattern": "^\\d{4}-\\d{2}-\\d{2}$|^$",
                        "能力项": "日期格式",
                        "description": "Tempo de início"
                    },
                    "dataFim": {
                        "type": "string",
                        "pattern": "^\\d{4}-\\d{2}-\\d{2}$|^$",
                        "能力项": "日期格式",
                        "description": "Tempo de fim"
                    },
                    "descricaoDetalhada": {
                        "type": "string",
                        "description": "Introdução detalhada da atividade",
                        "能力项": "范围、200字以上",
                        "pattern": "^.*$|^$",
                        "minLength": 315,
                        "maxLength": 400
                    },
                    "preco": {
                        "type": "array",
                        "description": "Informações de preço do ingresso",
                        "items": {
                            "type": "string"
                        },
                        "能力项": "主题约束"
                    },
                    "tempoLancamento": {
                        "type": "string",
                        "pattern": "^\\d{4}-\\d{2}-\\d{2}$|^$",
                        "能力项": "日期格式",
                        "description": "Tempo de lançamento do ingresso"
                    },
                    "temVistanoturna": {
                        "type": "string",
                        "enum": [
                            "Sim",
                            "Não"
                        ],
                        "description": "Se é uma atividade noturna",
                        "能力项": "特定格式"
                    },
                    "adequadoFamilias": {
                        "type": "string",
                        "enum": [
                            "Sim",
                            "Não"
                        ],
                        "description": "Se é adequado para pais e filhos",
                        "能力项": "特定格式"
                    },
                    "aoArLivre": {
                        "type": "string",
                        "enum": [
                            "Sim",
                            "Não"
                        ],
                        "description": "Se é atividade ao ar livre",
                        "能力项": "特定格式"
                    },
                    "temEspetaculoCultural": {
                        "type": "string",
                        "enum": [
                            "Sim",
                            "Não"
                        ],
                        "description": "Se inclui apresentações culturais",
                        "能力项": "特定格式"
                    },
                    "temTermas": {
                        "type": "string",
                        "enum": [
                            "Sim",
                            "Não"
                        ],
                        "description": "Se tem projetos de águas termais",
                        "能力项": "特定格式"
                    }
                },
                "required": [
                    "nomeAtividade",
                    "descricaoBreve",
                    "localizacao",
                    "dataInicio",
                    "dataFim",
                    "descricaoDetalhada",
                    "preco",
                    "tempoLancamento",
                    "temVistanoturna",
                    "adequadoFamilias",
                    "aoArLivre",
                    "temEspetaculoCultural",
                    "temTermas"
                ]
            }
        },
        "sub_questions": [
            {
                "point_id": 0,
                "question": "Se atende ao schema",
                "rule": "SCHEMA:json_schema",
                "dep": [],
                "被依赖": false,
                "能力项": "JSON"
            }
        ]
    },
    {
        "category": "SCHEMA",
        "question": "Você é um analista profissional de artigos sobre pontos turísticos. Fornecerei conteúdo do artigo e tipo de artigo. Você precisa executar diferentes estratégias de identificação baseadas em diferentes tipos de artigos. Retorne apenas as informações de atividades extraídas, não retorne nenhuma outra informação redundante.\nTipo de artigo: Auto-identificar\nPor favor, extraia informações de acordo com as seguintes regras:\n1. nomeAtividade: Nome da atividade, referindo-se a nomes específicos de atividades ou jogos mencionados no artigo.\n2. descricaoBreve: Descrição de uma frase, necessária para resumir destaques e características da atividade, excluindo horário operacional, informações práticas, descrições negativas, 68-100 caracteres (incluindo espaços, números...).\n3. localizacao: Localização geográfica da atividade, referindo-se a pontos de referência específicos ou marcos dentro de áreas cênicas ou locais, não pode ser cidades ou províncias.\n4. dataInicio/dataFim: Período de tempo da atividade, formato de data é xxxx-xx-xx, retorne string vazia se não identificado.\n5. descricaoDetalhada: Introdução detalhada da atividade, necessária 315-400 caracteres (incluindo espaços, números...), descrevendo destaques e características da atividade, excluindo palavras de perspectiva de terceiros.\n6. preco: Informações de preço do ingresso, formato de retorno [\"\",\"\"], retorne lista vazia se não identificado.\n7. tempoLancamento: Se a atividade pertence a concertos, festivais de música, Livehouse, comédia e outros tipos, precisa identificar o tempo de lançamento do ingresso, formato de data é xxxx-xx-xx, retorne string vazia se nenhum.\n8. temVistanoturna: Se é uma atividade noturna (Sim/Não).\n9. adequadoFamilias: Se é adequado para pais e filhos (Sim/Não).\n10. aoArLivre: Se é atividade ao ar livre (Sim/Não).\n11. temEspetaculoCultural: Se inclui apresentações culturais (Sim/Não).\n12. temTermas: Se tem projetos de águas termais (Sim/Não).\nRequisitos de saída:\n1. Use formato JSON para retornar informações extraídas\n2. Cada atividade como um objeto, contendo todos os campos\n3. Todos os objetos de atividade formam um array\n4. Não retorne nenhum caractere além do formato JSON\nExemplo de formato de saída:\n[\n  {\"nomeAtividade\":\"Nome da Atividade\",\"descricaoBreve\":\"Descrição de uma frase\",\"localizacao\":\"Localização geográfica\",\"dataInicio\":\"Tempo de início\",\"dataFim\":\"Tempo de fim\",\"descricaoDetalhada\":\"Introdução detalhada da atividade\",\"preco\":[],\"tempoLancamento\":\"Tempo de lançamento do ingresso\",\"temVistanoturna\":\"Sim/Não\",\"adequadoFamilias\":\"Sim/Não\",\"aoArLivre\":\"Sim/Não\",\"temEspetaculoCultural\":\"Sim/Não\",\"temTermas\":\"Sim/Não\"}\n]\nConteúdo do artigo:O Parque Aquático Chimelong está aberto à noite no verão. A festa aquática e o show de luz e música eletrônica farão todo o lugar ficar animado. A experiência do passeio noturno é única e adequada para pais e filhos e jovens.",
        "json_schema": {
            "type": "array",
            "items": {
                "type": "object",
                "properties": {
                    "nomeAtividade": {
                        "type": "string",
                        "description": "Nome da atividade",
                        "能力项": "JSON"
                    },
                    "descricaoBreve": {
                        "type": "string",
                        "description": "Descrição de uma frase",
                        "能力项": "范围、50~200字",
                        "pattern": "^.*$|^$",
                        "minLength": 68,
                        "maxLength": 100
                    },
                    "localizacao": {
                        "type": "string",
                        "description": "Localização geográfica da atividade",
                        "能力项": "JSON"
                    },
                    "dataInicio": {
                        "type": "string",
                        "pattern": "^\\d{4}-\\d{2}-\\d{2}$|^$",
                        "能力项": "日期格式",
                        "description": "Tempo de início"
                    },
                    "dataFim": {
                        "type": "string",
                        "pattern": "^\\d{4}-\\d{2}-\\d{2}$|^$",
                        "能力项": "日期格式",
                        "description": "Tempo de fim"
                    },
                    "descricaoDetalhada": {
                        "type": "string",
                        "description": "Introdução detalhada da atividade",
                        "能力项": "范围、200字以上",
                        "pattern": "^.*$|^$",
                        "minLength": 315,
                        "maxLength": 400
                    },
                    "preco": {
                        "type": "array",
                        "description": "Informações de preço do ingresso",
                        "items": {
                            "type": "string"
                        },
                        "能力项": "主题约束"
                    },
                    "tempoLancamento": {
                        "type": "string",
                        "pattern": "^\\d{4}-\\d{2}-\\d{2}$|^$",
                        "能力项": "日期格式",
                        "description": "Tempo de lançamento do ingresso"
                    },
                    "temVistanoturna": {
                        "type": "string",
                        "enum": [
                            "Sim",
                            "Não"
                        ],
                        "description": "Se é uma atividade noturna",
                        "能力项": "特定格式"
                    },
                    "adequadoFamilias": {
                        "type": "string",
                        "enum": [
                            "Sim",
                            "Não"
                        ],
                        "description": "Se é adequado para pais e filhos",
                        "能力项": "特定格式"
                    },
                    "aoArLivre": {
                        "type": "string",
                        "enum": [
                            "Sim",
                            "Não"
                        ],
                        "description": "Se é atividade ao ar livre",
                        "能力项": "特定格式"
                    },
                    "temEspetaculoCultural": {
                        "type": "string",
                        "enum": [
                            "Sim",
                            "Não"
                        ],
                        "description": "Se inclui apresentações culturais",
                        "能力项": "特定格式"
                    },
                    "temTermas": {
                        "type": "string",
                        "enum": [
                            "Sim",
                            "Não"
                        ],
                        "description": "Se tem projetos de águas termais",
                        "能力项": "特定格式"
                    }
                },
                "required": [
                    "nomeAtividade",
                    "descricaoBreve",
                    "localizacao",
                    "dataInicio",
                    "dataFim",
                    "descricaoDetalhada",
                    "preco",
                    "tempoLancamento",
                    "temVistanoturna",
                    "adequadoFamilias",
                    "aoArLivre",
                    "temEspetaculoCultural",
                    "temTermas"
                ]
            }
        },
        "sub_questions": [
            {
                "point_id": 0,
                "question": "Se atende ao schema",
                "rule": "SCHEMA:json_schema",
                "dep": [],
                "被依赖": false,
                "能力项": "JSON"
            }
        ]
    },
    {
        "category": "SCHEMA",
        "question": "Você é um analista profissional de artigos sobre pontos turísticos. Fornecerei conteúdo do artigo e tipo de artigo. Você precisa executar diferentes estratégias de identificação baseadas em diferentes tipos de artigos. Retorne apenas as informações de atividades extraídas, não retorne nenhuma outra informação redundante.\nTipo de artigo: Auto-identificar\nPor favor, extraia informações de acordo com as seguintes regras:\n1. nomeAtividade: Nome da atividade, referindo-se a nomes específicos de atividades ou jogos mencionados no artigo.\n2. descricaoBreve: Descrição de uma frase, necessária para resumir destaques e características da atividade, excluindo horário operacional, informações práticas, descrições negativas, 68-100 caracteres (incluindo espaços, números...).\n3. localizacao: Localização geográfica da atividade, referindo-se a pontos de referência específicos ou marcos dentro de áreas cênicas ou locais, não pode ser cidades ou províncias.\n4. dataInicio/dataFim: Período de tempo da atividade, formato de data é xxxx-xx-xx, retorne string vazia se não identificado.\n5. descricaoDetalhada: Introdução detalhada da atividade, necessária 315-400 caracteres (incluindo espaços, números...), descrevendo destaques e características da atividade, excluindo palavras de perspectiva de terceiros.\n6. preco: Informações de preço do ingresso, formato de retorno [\"\",\"\"], retorne lista vazia se não identificado.\n7. tempoLancamento: Se a atividade pertence a concertos, festivais de música, Livehouse, comédia e outros tipos, precisa identificar o tempo de lançamento do ingresso, formato de data é xxxx-xx-xx, retorne string vazia se nenhum.\n8. temVistanoturna: Se é uma atividade noturna (Sim/Não).\n9. adequadoFamilias: Se é adequado para pais e filhos (Sim/Não).\n10. aoArLivre: Se é atividade ao ar livre (Sim/Não).\n11. temEspetaculoCultural: Se inclui apresentações culturais (Sim/Não).\n12. temTermas: Se tem projetos de águas termais (Sim/Não).\nRequisitos de saída:\n1. Use formato JSON para retornar informações extraídas\n2. Cada atividade como um objeto, contendo todos os campos\n3. Todos os objetos de atividade formam um array\n4. Não retorne nenhum caractere além do formato JSON\nExemplo de formato de saída:\n[\n  {\"nomeAtividade\":\"Nome da Atividade\",\"descricaoBreve\":\"Descrição de uma frase\",\"localizacao\":\"Localização geográfica\",\"dataInicio\":\"Tempo de início\",\"dataFim\":\"Tempo de fim\",\"descricaoDetalhada\":\"Introdução detalhada da atividade\",\"preco\":[],\"tempoLancamento\":\"Tempo de lançamento do ingresso\",\"temVistanoturna\":\"Sim/Não\",\"adequadoFamilias\":\"Sim/Não\",\"aoArLivre\":\"Sim/Não\",\"temEspetaculoCultural\":\"Sim/Não\",\"temTermas\":\"Sim/Não\"}\n]\nConteúdo do artigo:Desfile de Natal da Disneyland de Xangai, todos os membros da família Mickey estão presentes, a cerimônia de acendimento da árvore de Natal é calorosa e romântica. O show de fogos de artifício noturno e o show de luzes se complementam.",
        "json_schema": {
            "type": "array",
            "items": {
                "type": "object",
                "properties": {
                    "nomeAtividade": {
                        "type": "string",
                        "description": "Nome da atividade",
                        "能力项": "JSON"
                    },
                    "descricaoBreve": {
                        "type": "string",
                        "description": "Descrição de uma frase",
                        "能力项": "范围、50~200字",
                        "pattern": "^.*$|^$",
                        "minLength": 68,
                        "maxLength": 100
                    },
                    "localizacao": {
                        "type": "string",
                        "description": "Localização geográfica da atividade",
                        "能力项": "JSON"
                    },
                    "dataInicio": {
                        "type": "string",
                        "pattern": "^\\d{4}-\\d{2}-\\d{2}$|^$",
                        "能力项": "日期格式",
                        "description": "Tempo de início"
                    },
                    "dataFim": {
                        "type": "string",
                        "pattern": "^\\d{4}-\\d{2}-\\d{2}$|^$",
                        "能力项": "日期格式",
                        "description": "Tempo de fim"
                    },
                    "descricaoDetalhada": {
                        "type": "string",
                        "description": "Introdução detalhada da atividade",
                        "能力项": "范围、200字以上",
                        "pattern": "^.*$|^$",
                        "minLength": 315,
                        "maxLength": 400
                    },
                    "preco": {
                        "type": "array",
                        "description": "Informações de preço do ingresso",
                        "items": {
                            "type": "string"
                        },
                        "能力项": "主题约束"
                    },
                    "tempoLancamento": {
                        "type": "string",
                        "pattern": "^\\d{4}-\\d{2}-\\d{2}$|^$",
                        "能力项": "日期格式",
                        "description": "Tempo de lançamento do ingresso"
                    },
                    "temVistanoturna": {
                        "type": "string",
                        "enum": [
                            "Sim",
                            "Não"
                        ],
                        "description": "Se é uma atividade noturna",
                        "能力项": "特定格式"
                    },
                    "adequadoFamilias": {
                        "type": "string",
                        "enum": [
                            "Sim",
                            "Não"
                        ],
                        "description": "Se é adequado para pais e filhos",
                        "能力项": "特定格式"
                    },
                    "aoArLivre": {
                        "type": "string",
                        "enum": [
                            "Sim",
                            "Não"
                        ],
                        "description": "Se é atividade ao ar livre",
                        "能力项": "特定格式"
                    },
                    "temEspetaculoCultural": {
                        "type": "string",
                        "enum": [
                            "Sim",
                            "Não"
                        ],
                        "description": "Se inclui apresentações culturais",
                        "能力项": "特定格式"
                    },
                    "temTermas": {
                        "type": "string",
                        "enum": [
                            "Sim",
                            "Não"
                        ],
                        "description": "Se tem projetos de águas termais",
                        "能力项": "特定格式"
                    }
                },
                "required": [
                    "nomeAtividade",
                    "descricaoBreve",
                    "localizacao",
                    "dataInicio",
                    "dataFim",
                    "descricaoDetalhada",
                    "preco",
                    "tempoLancamento",
                    "temVistanoturna",
                    "adequadoFamilias",
                    "aoArLivre",
                    "temEspetaculoCultural",
                    "temTermas"
                ]
            }
        },
        "sub_questions": [
            {
                "point_id": 0,
                "question": "Se atende ao schema",
                "rule": "SCHEMA:json_schema",
                "dep": [],
                "被依赖": false,
                "能力项": "JSON"
            }
        ]
    },
    {
        "category": "SCHEMA",
        "question": "Você é um analista profissional de artigos sobre pontos turísticos. Fornecerei conteúdo do artigo e tipo de artigo. Você precisa executar diferentes estratégias de identificação baseadas em diferentes tipos de artigos. Retorne apenas as informações de atividades extraídas, não retorne nenhuma outra informação redundante.\nTipo de artigo: Auto-identificar\nPor favor, extraia informações de acordo com as seguintes regras:\n1. nomeAtividade: Nome da atividade, referindo-se a nomes específicos de atividades ou jogos mencionados no artigo.\n2. descricaoBreve: Descrição de uma frase, necessária para resumir destaques e características da atividade, excluindo horário operacional, informações práticas, descrições negativas, 68-100 caracteres (incluindo espaços, números...).\n3. localizacao: Localização geográfica da atividade, referindo-se a pontos de referência específicos ou marcos dentro de áreas cênicas ou locais, não pode ser cidades ou províncias.\n4. dataInicio/dataFim: Período de tempo da atividade, formato de data é xxxx-xx-xx, retorne string vazia se não identificado.\n5. descricaoDetalhada: Introdução detalhada da atividade, necessária 315-400 caracteres (incluindo espaços, números...), descrevendo destaques e características da atividade, excluindo palavras de perspectiva de terceiros.\n6. preco: Informações de preço do ingresso, formato de retorno [\"\",\"\"], retorne lista vazia se não identificado.\n7. tempoLancamento: Se a atividade pertence a concertos, festivais de música, Livehouse, comédia e outros tipos, precisa identificar o tempo de lançamento do ingresso, formato de data é xxxx-xx-xx, retorne string vazia se nenhum.\n8. temVistanoturna: Se é uma atividade noturna (Sim/Não).\n9. adequadoFamilias: Se é adequado para pais e filhos (Sim/Não).\n10. aoArLivre: Se é atividade ao ar livre (Sim/Não).\n11. temEspetaculoCultural: Se inclui apresentações culturais (Sim/Não).\n12. temTermas: Se tem projetos de águas termais (Sim/Não).\nRequisitos de saída:\n1. Use formato JSON para retornar informações extraídas\n2. Cada atividade como um objeto, contendo todos os campos\n3. Todos os objetos de atividade formam um array\n4. Não retorne nenhum caractere além do formato JSON\nExemplo de formato de saída:\n[\n  {\"nomeAtividade\":\"Nome da Atividade\",\"descricaoBreve\":\"Descrição de uma frase\",\"localizacao\":\"Localização geográfica\",\"dataInicio\":\"Tempo de início\",\"dataFim\":\"Tempo de fim\",\"descricaoDetalhada\":\"Introdução detalhada da atividade\",\"preco\":[],\"tempoLancamento\":\"Tempo de lançamento do ingresso\",\"temVistanoturna\":\"Sim/Não\",\"adequadoFamilias\":\"Sim/Não\",\"aoArLivre\":\"Sim/Não\",\"temEspetaculoCultural\":\"Sim/Não\",\"temTermas\":\"Sim/Não\"}\n]\nConteúdo do artigo:Festival de Música do Mercado Noturno de Hongyadong em Chongqing, bandas independentes se apresentam alternadamente, a vista noturna da margem do rio e a música se integram perfeitamente, pais e filhos, casais são adequados para check-ins noturnos.",
        "json_schema": {
            "type": "array",
            "items": {
                "type": "object",
                "properties": {
                    "nomeAtividade": {
                        "type": "string",
                        "description": "Nome da atividade",
                        "能力项": "JSON"
                    },
                    "descricaoBreve": {
                        "type": "string",
                        "description": "Descrição de uma frase",
                        "能力项": "范围、50~200字",
                        "pattern": "^.*$|^$",
                        "minLength": 68,
                        "maxLength": 100
                    },
                    "localizacao": {
                        "type": "string",
                        "description": "Localização geográfica da atividade",
                        "能力项": "JSON"
                    },
                    "dataInicio": {
                        "type": "string",
                        "pattern": "^\\d{4}-\\d{2}-\\d{2}$|^$",
                        "能力项": "日期格式",
                        "description": "Tempo de início"
                    },
                    "dataFim": {
                        "type": "string",
                        "pattern": "^\\d{4}-\\d{2}-\\d{2}$|^$",
                        "能力项": "日期格式",
                        "description": "Tempo de fim"
                    },
                    "descricaoDetalhada": {
                        "type": "string",
                        "description": "Introdução detalhada da atividade",
                        "能力项": "范围、200字以上",
                        "pattern": "^.*$|^$",
                        "minLength": 315,
                        "maxLength": 400
                    },
                    "preco": {
                        "type": "array",
                        "description": "Informações de preço do ingresso",
                        "items": {
                            "type": "string"
                        },
                        "能力项": "主题约束"
                    },
                    "tempoLancamento": {
                        "type": "string",
                        "pattern": "^\\d{4}-\\d{2}-\\d{2}$|^$",
                        "能力项": "日期格式",
                        "description": "Tempo de lançamento do ingresso"
                    },
                    "temVistanoturna": {
                        "type": "string",
                        "enum": [
                            "Sim",
                            "Não"
                        ],
                        "description": "Se é uma atividade noturna",
                        "能力项": "特定格式"
                    },
                    "adequadoFamilias": {
                        "type": "string",
                        "enum": [
                            "Sim",
                            "Não"
                        ],
                        "description": "Se é adequado para pais e filhos",
                        "能力项": "特定格式"
                    },
                    "aoArLivre": {
                        "type": "string",
                        "enum": [
                            "Sim",
                            "Não"
                        ],
                        "description": "Se é atividade ao ar livre",
                        "能力项": "特定格式"
                    },
                    "temEspetaculoCultural": {
                        "type": "string",
                        "enum": [
                            "Sim",
                            "Não"
                        ],
                        "description": "Se inclui apresentações culturais",
                        "能力项": "特定格式"
                    },
                    "temTermas": {
                        "type": "string",
                        "enum": [
                            "Sim",
                            "Não"
                        ],
                        "description": "Se tem projetos de águas termais",
                        "能力项": "特定格式"
                    }
                },
                "required": [
                    "nomeAtividade",
                    "descricaoBreve",
                    "localizacao",
                    "dataInicio",
                    "dataFim",
                    "descricaoDetalhada",
                    "preco",
                    "tempoLancamento",
                    "temVistanoturna",
                    "adequadoFamilias",
                    "aoArLivre",
                    "temEspetaculoCultural",
                    "temTermas"
                ]
            }
        },
        "sub_questions": [
            {
                "point_id": 0,
                "question": "Se atende ao schema",
                "rule": "SCHEMA:json_schema",
                "dep": [],
                "被依赖": false,
                "能力项": "JSON"
            }
        ]
    },
    {
        "category": "SCHEMA",
        "question": "Você é um analista profissional de artigos sobre pontos turísticos. Fornecerei conteúdo do artigo e tipo de artigo. Você precisa executar diferentes estratégias de identificação baseadas em diferentes tipos de artigos. Retorne apenas as informações de atividades extraídas, não retorne nenhuma outra informação redundante.\nTipo de artigo: Auto-identificar\nPor favor, extraia informações de acordo com as seguintes regras:\n1. nomeAtividade: Nome da atividade, referindo-se a nomes específicos de atividades ou jogos mencionados no artigo.\n2. descricaoBreve: Descrição de uma frase, necessária para resumir destaques e características da atividade, excluindo horário operacional, informações práticas, descrições negativas, 68-100 caracteres (incluindo espaços, números...).\n3. localizacao: Localização geográfica da atividade, referindo-se a pontos de referência específicos ou marcos dentro de áreas cênicas ou locais, não pode ser cidades ou províncias.\n4. dataInicio/dataFim: Período de tempo da atividade, formato de data é xxxx-xx-xx, retorne string vazia se não identificado.\n5. descricaoDetalhada: Introdução detalhada da atividade, necessária 315-400 caracteres (incluindo espaços, números...), descrevendo destaques e características da atividade, excluindo palavras de perspectiva de terceiros.\n6. preco: Informações de preço do ingresso, formato de retorno [\"\",\"\"], retorne lista vazia se não identificado.\n7. tempoLancamento: Se a atividade pertence a concertos, festivais de música, Livehouse, comédia e outros tipos, precisa identificar o tempo de lançamento do ingresso, formato de data é xxxx-xx-xx, retorne string vazia se nenhum.\n8. temVistanoturna: Se é uma atividade noturna (Sim/Não).\n9. adequadoFamilias: Se é adequado para pais e filhos (Sim/Não).\n10. aoArLivre: Se é atividade ao ar livre (Sim/Não).\n11. temEspetaculoCultural: Se inclui apresentações culturais (Sim/Não).\n12. temTermas: Se tem projetos de águas termais (Sim/Não).\nRequisitos de saída:\n1. Use formato JSON para retornar informações extraídas\n2. Cada atividade como um objeto, contendo todos os campos\n3. Todos os objetos de atividade formam um array\n4. Não retorne nenhum caractere além do formato JSON\nExemplo de formato de saída:\n[\n  {\"nomeAtividade\":\"Nome da Atividade\",\"descricaoBreve\":\"Descrição de uma frase\",\"localizacao\":\"Localização geográfica\",\"dataInicio\":\"Tempo de início\",\"dataFim\":\"Tempo de fim\",\"descricaoDetalhada\":\"Introdução detalhada da atividade\",\"preco\":[],\"tempoLancamento\":\"Tempo de lançamento do ingresso\",\"temVistanoturna\":\"Sim/Não\",\"adequadoFamilias\":\"Sim/Não\",\"aoArLivre\":\"Sim/Não\",\"temEspetaculoCultural\":\"Sim/Não\",\"temTermas\":\"Sim/Não\"}\n]\nConteúdo do artigo:Feira do Templo de Ano Novo da Cidade Antiga de Dali, dança Bai, mercado folclórico, show de fogos de artifício ilumina o céu noturno da cidade antiga, experiência de águas termais e comida do mercado noturno são ricas e coloridas.",
        "json_schema": {
            "type": "array",
            "items": {
                "type": "object",
                "properties": {
                    "nomeAtividade": {
                        "type": "string",
                        "description": "Nome da atividade",
                        "能力项": "JSON"
                    },
                    "descricaoBreve": {
                        "type": "string",
                        "description": "Descrição de uma frase",
                        "能力项": "范围、50~200字",
                        "pattern": "^.*$|^$",
                        "minLength": 68,
                        "maxLength": 100
                    },
                    "localizacao": {
                        "type": "string",
                        "description": "Localização geográfica da atividade",
                        "能力项": "JSON"
                    },
                    "dataInicio": {
                        "type": "string",
                        "pattern": "^\\d{4}-\\d{2}-\\d{2}$|^$",
                        "能力项": "日期格式",
                        "description": "Tempo de início"
                    },
                    "dataFim": {
                        "type": "string",
                        "pattern": "^\\d{4}-\\d{2}-\\d{2}$|^$",
                        "能力项": "日期格式",
                        "description": "Tempo de fim"
                    },
                    "descricaoDetalhada": {
                        "type": "string",
                        "description": "Introdução detalhada da atividade",
                        "能力项": "范围、200字以上",
                        "pattern": "^.*$|^$",
                        "minLength": 315,
                        "maxLength": 400
                    },
                    "preco": {
                        "type": "array",
                        "description": "Informações de preço do ingresso",
                        "items": {
                            "type": "string"
                        },
                        "能力项": "主题约束"
                    },
                    "tempoLancamento": {
                        "type": "string",
                        "pattern": "^\\d{4}-\\d{2}-\\d{2}$|^$",
                        "能力项": "日期格式",
                        "description": "Tempo de lançamento do ingresso"
                    },
                    "temVistanoturna": {
                        "type": "string",
                        "enum": [
                            "Sim",
                            "Não"
                        ],
                        "description": "Se é uma atividade noturna",
                        "能力项": "特定格式"
                    },
                    "adequadoFamilias": {
                        "type": "string",
                        "enum": [
                            "Sim",
                            "Não"
                        ],
                        "description": "Se é adequado para pais e filhos",
                        "能力项": "特定格式"
                    },
                    "aoArLivre": {
                        "type": "string",
                        "enum": [
                            "Sim",
                            "Não"
                        ],
                        "description": "Se é atividade ao ar livre",
                        "能力项": "特定格式"
                    },
                    "temEspetaculoCultural": {
                        "type": "string",
                        "enum": [
                            "Sim",
                            "Não"
                        ],
                        "description": "Se inclui apresentações culturais",
                        "能力项": "特定格式"
                    },
                    "temTermas": {
                        "type": "string",
                        "enum": [
                            "Sim",
                            "Não"
                        ],
                        "description": "Se tem projetos de águas termais",
                        "能力项": "特定格式"
                    }
                },
                "required": [
                    "nomeAtividade",
                    "descricaoBreve",
                    "localizacao",
                    "dataInicio",
                    "dataFim",
                    "descricaoDetalhada",
                    "preco",
                    "tempoLancamento",
                    "temVistanoturna",
                    "adequadoFamilias",
                    "aoArLivre",
                    "temEspetaculoCultural",
                    "temTermas"
                ]
            }
        },
        "sub_questions": [
            {
                "point_id": 0,
                "question": "Se atende ao schema",
                "rule": "SCHEMA:json_schema",
                "dep": [],
                "被依赖": false,
                "能力项": "JSON"
            }
        ]
    },
    {
        "category": "SCHEMA",
        "question": "Você é um analista profissional de artigos sobre pontos turísticos. Fornecerei conteúdo do artigo e tipo de artigo. Você precisa executar diferentes estratégias de identificação baseadas em diferentes tipos de artigos. Retorne apenas as informações de atividades extraídas, não retorne nenhuma outra informação redundante.\nTipo de artigo: Auto-identificar\nPor favor, extraia informações de acordo com as seguintes regras:\n1. nomeAtividade: Nome da atividade, referindo-se a nomes específicos de atividades ou jogos mencionados no artigo.\n2. descricaoBreve: Descrição de uma frase, necessária para resumir destaques e características da atividade, excluindo horário operacional, informações práticas, descrições negativas, 68-100 caracteres (incluindo espaços, números...).\n3. localizacao: Localização geográfica da atividade, referindo-se a pontos de referência específicos ou marcos dentro de áreas cênicas ou locais, não pode ser cidades ou províncias.\n4. dataInicio/dataFim: Período de tempo da atividade, formato de data é xxxx-xx-xx, retorne string vazia se não identificado.\n5. descricaoDetalhada: Introdução detalhada da atividade, necessária 315-400 caracteres (incluindo espaços, números...), descrevendo destaques e características da atividade, excluindo palavras de perspectiva de terceiros.\n6. preco: Informações de preço do ingresso, formato de retorno [\"\",\"\"], retorne lista vazia se não identificado.\n7. tempoLancamento: Se a atividade pertence a concertos, festivais de música, Livehouse, comédia e outros tipos, precisa identificar o tempo de lançamento do ingresso, formato de data é xxxx-xx-xx, retorne string vazia se nenhum.\n8. temVistanoturna: Se é uma atividade noturna (Sim/Não).\n9. adequadoFamilias: Se é adequado para pais e filhos (Sim/Não).\n10. aoArLivre: Se é atividade ao ar livre (Sim/Não).\n11. temEspetaculoCultural: Se inclui apresentações culturais (Sim/Não).\n12. temTermas: Se tem projetos de águas termais (Sim/Não).\nRequisitos de saída:\n1. Use formato JSON para retornar informações extraídas\n2. Cada atividade como um objeto, contendo todos os campos\n3. Todos os objetos de atividade formam um array\n4. Não retorne nenhum caractere além do formato JSON\nExemplo de formato de saída:\n[\n  {\"nomeAtividade\":\"Nome da Atividade\",\"descricaoBreve\":\"Descrição de uma frase\",\"localizacao\":\"Localização geográfica\",\"dataInicio\":\"Tempo de início\",\"dataFim\":\"Tempo de fim\",\"descricaoDetalhada\":\"Introdução detalhada da atividade\",\"preco\":[],\"tempoLancamento\":\"Tempo de lançamento do ingresso\",\"temVistanoturna\":\"Sim/Não\",\"adequadoFamilias\":\"Sim/Não\",\"aoArLivre\":\"Sim/Não\",\"temEspetaculoCultural\":\"Sim/Não\",\"temTermas\":\"Sim/Não\"}\n]\nConteúdo do artigo:Tour Científico entre Pais e Filhos da Base de Pandas de Chengdu, explicação sobre pandas, experiência prática, lembranças temáticas ricas e coloridas, o parque tem um pequeno show de luzes noturnas.",
        "json_schema": {
            "type": "array",
            "items": {
                "type": "object",
                "properties": {
                    "nomeAtividade": {
                        "type": "string",
                        "description": "Nome da atividade",
                        "能力项": "JSON"
                    },
                    "descricaoBreve": {
                        "type": "string",
                        "description": "Descrição de uma frase",
                        "能力项": "范围、50~200字",
                        "pattern": "^.*$|^$",
                        "minLength": 68,
                        "maxLength": 100
                    },
                    "localizacao": {
                        "type": "string",
                        "description": "Localização geográfica da atividade",
                        "能力项": "JSON"
                    },
                    "dataInicio": {
                        "type": "string",
                        "pattern": "^\\d{4}-\\d{2}-\\d{2}$|^$",
                        "能力项": "日期格式",
                        "description": "Tempo de início"
                    },
                    "dataFim": {
                        "type": "string",
                        "pattern": "^\\d{4}-\\d{2}-\\d{2}$|^$",
                        "能力项": "日期格式",
                        "description": "Tempo de fim"
                    },
                    "descricaoDetalhada": {
                        "type": "string",
                        "description": "Introdução detalhada da atividade",
                        "能力项": "范围、200字以上",
                        "pattern": "^.*$|^$",
                        "minLength": 315,
                        "maxLength": 400
                    },
                    "preco": {
                        "type": "array",
                        "description": "Informações de preço do ingresso",
                        "items": {
                            "type": "string"
                        },
                        "能力项": "主题约束"
                    },
                    "tempoLancamento": {
                        "type": "string",
                        "pattern": "^\\d{4}-\\d{2}-\\d{2}$|^$",
                        "能力项": "日期格式",
                        "description": "Tempo de lançamento do ingresso"
                    },
                    "temVistanoturna": {
                        "type": "string",
                        "enum": [
                            "Sim",
                            "Não"
                        ],
                        "description": "Se é uma atividade noturna",
                        "能力项": "特定格式"
                    },
                    "adequadoFamilias": {
                        "type": "string",
                        "enum": [
                            "Sim",
                            "Não"
                        ],
                        "description": "Se é adequado para pais e filhos",
                        "能力项": "特定格式"
                    },
                    "aoArLivre": {
                        "type": "string",
                        "enum": [
                            "Sim",
                            "Não"
                        ],
                        "description": "Se é atividade ao ar livre",
                        "能力项": "特定格式"
                    },
                    "temEspetaculoCultural": {
                        "type": "string",
                        "enum": [
                            "Sim",
                            "Não"
                        ],
                        "description": "Se inclui apresentações culturais",
                        "能力项": "特定格式"
                    },
                    "temTermas": {
                        "type": "string",
                        "enum": [
                            "Sim",
                            "Não"
                        ],
                        "description": "Se tem projetos de águas termais",
                        "能力项": "特定格式"
                    }
                },
                "required": [
                    "nomeAtividade",
                    "descricaoBreve",
                    "localizacao",
                    "dataInicio",
                    "dataFim",
                    "descricaoDetalhada",
                    "preco",
                    "tempoLancamento",
                    "temVistanoturna",
                    "adequadoFamilias",
                    "aoArLivre",
                    "temEspetaculoCultural",
                    "temTermas"
                ]
            }
        },
        "sub_questions": [
            {
                "point_id": 0,
                "question": "Se atende ao schema",
                "rule": "SCHEMA:json_schema",
                "dep": [],
                "被依赖": false,
                "能力项": "JSON"
            }
        ]
    }
]