[
    {
        "category": "SCHEMA",
        "question": "Eres un analista profesional de artículos de puntos calientes de viaje. Te proporcionaré contenido de artículos y tipos de artículos. Necesitas ejecutar diferentes estrategias de identificación basadas en diferentes tipos de artículos. Solo devuelve la información de juegos extraída, no devuelvas ninguna otra información redundante.\nTipo de artículo: Auto-identificación\nPor favor extrae información según las siguientes reglas:\n1. playName: Nombre del juego, refiriéndose a nombres específicos de juegos o actividades mencionados en el artículo.\n2. briefDesc: Descripción de una oración, requerida para resumir los aspectos destacados y características del juego, excluyendo tiempo operativo, información práctica, descripciones negativas, 68-100 caracteres (incluir espacio, número...).\n3. location: Ubicación geográfica del juego, refiriéndose a puntos de referencia específicos o monumentos dentro de áreas escénicas o lugares, no puede ser ciudades o provincias.\n4. startDate/endDate: Rango de tiempo del juego, formato de fecha es xxxx-xx-xx, devolver cadena vacía si no se identifica.\n5. detailDesc: Introducción detallada del juego, requerida 315-400 caracteres (incluir espacio, número...), describiendo aspectos destacados y características del juego, excluyendo palabras de perspectiva de terceros.\n6. price: Información de precio de boleto, formato de retorno [\"\",\"\"], devolver lista vacía si no se identifica.\n7. issueTime: Si el juego pertenece a conciertos, festivales de música, Livehouse, cabaret y otros tipos, necesita identificar tiempo de lanzamiento de boletos, formato de fecha es xxxx-xx-xx, devolver cadena vacía si no hay ninguno.\n8. hasNightView: Si es una actividad nocturna (Sí/No).\n9. isParentChildFriendly: Si es adecuado para padres-hijos (Sí/No).\n10. isOutdoor: Si es un juego al aire libre (Sí/No).\n11. hasCulturalShow: Si incluye espectáculos culturales (Sí/No).\n12. hasHotSpring: Si tiene proyectos de aguas termales (Sí/No).\nRequisitos de salida:\n1. Usar formato JSON para devolver información extraída\n2. Cada juego como objeto, conteniendo todos los campos\n3. Todos los objetos de juego forman un array\n4. No devolver ningún carácter que no sea formato JSON\nEjemplo de formato de salida:\n[\n  {\"playName\":\"Nombre del juego\",\"briefDesc\":\"Descripción de una oración\",\"location\":\"Ubicación geográfica\",\"startDate\":\"Hora de inicio\",\"endDate\":\"Hora de fin\",\"detailDesc\":\"Introducción detallada del juego\",\"price\":[],\"issueTime\":\"Tiempo de lanzamiento de boletos\",\"hasNightView\":\"Sí/No\",\"isParentChildFriendly\":\"Sí/No\",\"isOutdoor\":\"Sí/No\",\"hasCulturalShow\":\"Sí/No\",\"hasHotSpring\":\"Sí/No\"}\n]\nContenido del artículo:¡El mercado nocturno navideño del Instituto de Ingeniería Mecánica y Eléctrica de Sanlitun está abierto! Wood Eats Talk Mercado de invierno, Desfile nocturno de postres, Actuación de sello de música independiente, 90 horas de experiencia musical sin parar, atmósfera navideña y comida reunidas. También hay áreas de interacción padre-hijo y talleres de mercado.",
        "json_schema": {
            "type": "array",
            "items": {
                "type": "object",
                "properties": {
                    "playName": {
                        "type": "string",
                        "description": "Nombre del juego",
                        "能力项": "JSON"
                    },
                    "briefDesc": {
                        "type": "string",
                        "description": "Descripción de una oración",
                        "能力项": "范围、50~200字",
                        "pattern": "^.*$|^$",
                        "minLength": 68,
                        "maxLength": 100
                    },
                    "location": {
                        "type": "string",
                        "description": "Ubicación geográfica del juego",
                        "能力项": "JSON"
                    },
                    "startDate": {
                        "type": "string",
                        "pattern": "^\\d{4}-\\d{2}-\\d{2}$|^$",
                        "能力项": "日期格式",
                        "description": "Hora de inicio"
                    },
                    "endDate": {
                        "type": "string",
                        "pattern": "^\\d{4}-\\d{2}-\\d{2}$|^$",
                        "能力项": "日期格式",
                        "description": "Hora de fin"
                    },
                    "detailDesc": {
                        "type": "string",
                        "description": "Introducción detallada del juego",
                        "能力项": "范围、200字以上",
                        "pattern": "^.*$|^$",
                        "minLength": 315,
                        "maxLength": 400
                    },
                    "price": {
                        "type": "array",
                        "description": "Información de precio de boleto",
                        "items": {
                            "type": "string"
                        },
                        "能力项": "主题约束"
                    },
                    "issueTime": {
                        "type": "string",
                        "pattern": "^\\d{4}-\\d{2}-\\d{2}$|^$",
                        "能力项": "日期格式",
                        "description": "Tiempo de lanzamiento de boletos"
                    },
                    "hasNightView": {
                        "type": "string",
                        "enum": [
                            "Sí",
                            "No"
                        ],
                        "description": "Si es una actividad nocturna",
                        "能力项": "特定格式"
                    },
                    "isParentChildFriendly": {
                        "type": "string",
                        "enum": [
                            "Sí",
                            "No"
                        ],
                        "description": "Si es adecuado para padres-hijos",
                        "能力项": "特定格式"
                    },
                    "isOutdoor": {
                        "type": "string",
                        "enum": [
                            "Sí",
                            "No"
                        ],
                        "description": "Si es un juego al aire libre",
                        "能力项": "特定格式"
                    },
                    "hasCulturalShow": {
                        "type": "string",
                        "enum": [
                            "Sí",
                            "No"
                        ],
                        "description": "Si incluye espectáculos culturales",
                        "能力项": "特定格式"
                    },
                    "hasHotSpring": {
                        "type": "string",
                        "enum": [
                            "Sí",
                            "No"
                        ],
                        "description": "Si tiene proyectos de aguas termales",
                        "能力项": "特定格式"
                    }
                },
                "required": [
                    "playName",
                    "briefDesc",
                    "location",
                    "startDate",
                    "endDate",
                    "detailDesc",
                    "price",
                    "issueTime",
                    "hasNightView",
                    "isParentChildFriendly",
                    "isOutdoor",
                    "hasCulturalShow",
                    "hasHotSpring"
                ]
            }
        },
        "sub_questions": [
            {
                "point_id": 0,
                "question": "Si cumple con el esquema",
                "rule": "SCHEMA:json_schema",
                "dep": [],
                "被依赖": false,
                "能力项": "JSON"
            }
        ]
    },
    {
        "category": "SCHEMA",
        "question": "Eres un analista profesional de artículos de puntos calientes de viaje. Te proporcionaré contenido de artículos y tipos de artículos. Necesitas ejecutar diferentes estrategias de identificación basadas en diferentes tipos de artículos. Solo devuelve la información de juegos extraída, no devuelvas ninguna otra información redundante.\nTipo de artículo: Auto-identificación\nPor favor extrae información según las siguientes reglas:\n1. playName: Nombre del juego, refiriéndose a nombres específicos de juegos o actividades mencionados en el artículo.\n2. briefDesc: Descripción de una oración, requerida para resumir los aspectos destacados y características del juego, excluyendo tiempo operativo, información práctica, descripciones negativas, 68-100 caracteres (incluir espacio, número...).\n3. location: Ubicación geográfica del juego, refiriéndose a puntos de referencia específicos o monumentos dentro de áreas escénicas o lugares, no puede ser ciudades o provincias.\n4. startDate/endDate: Rango de tiempo del juego, formato de fecha es xxxx-xx-xx, devolver cadena vacía si no se identifica.\n5. detailDesc: Introducción detallada del juego, requerida 315-400 caracteres (incluir espacio, número...), describiendo aspectos destacados y características del juego, excluyendo palabras de perspectiva de terceros.\n6. price: Información de precio de boleto, formato de retorno [\"\",\"\"], devolver lista vacía si no se identifica.\n7. issueTime: Si el juego pertenece a conciertos, festivales de música, Livehouse, cabaret y otros tipos, necesita identificar tiempo de lanzamiento de boletos, formato de fecha es xxxx-xx-xx, devolver cadena vacía si no hay ninguno.\n8. hasNightView: Si es una actividad nocturna (Sí/No).\n9. isParentChildFriendly: Si es adecuado para padres-hijos (Sí/No).\n10. isOutdoor: Si es un juego al aire libre (Sí/No).\n11. hasCulturalShow: Si incluye espectáculos culturales (Sí/No).\n12. hasHotSpring: Si tiene proyectos de aguas termales (Sí/No).\nRequisitos de salida:\n1. Usar formato JSON para devolver información extraída\n2. Cada juego como objeto, conteniendo todos los campos\n3. Todos los objetos de juego forman un array\n4. No devolver ningún carácter que no sea formato JSON\nEjemplo de formato de salida:\n[\n  {\"playName\":\"Nombre del juego\",\"briefDesc\":\"Descripción de una oración\",\"location\":\"Ubicación geográfica\",\"startDate\":\"Hora de inicio\",\"endDate\":\"Hora de fin\",\"detailDesc\":\"Introducción detallada del juego\",\"price\":[],\"issueTime\":\"Tiempo de lanzamiento de boletos\",\"hasNightView\":\"Sí/No\",\"isParentChildFriendly\":\"Sí/No\",\"isOutdoor\":\"Sí/No\",\"hasCulturalShow\":\"Sí/No\",\"hasHotSpring\":\"Sí/No\"}\n]\nContenido del artículo:El espectáculo de luces navideñas de Happy Valley está abierto, hay actuaciones de desfile a gran escala y mercados temáticos navideños por la noche, padres e hijos, parejas, amigos pueden divertirse, la vista nocturna al aire libre es inolvidable.",
        "json_schema": {
            "type": "array",
            "items": {
                "type": "object",
                "properties": {
                    "playName": {
                        "type": "string",
                        "description": "Nombre del juego",
                        "能力项": "JSON"
                    },
                    "briefDesc": {
                        "type": "string",
                        "description": "Descripción de una oración",
                        "能力项": "范围、50~200字",
                        "pattern": "^.*$|^$",
                        "minLength": 68,
                        "maxLength": 100
                    },
                    "location": {
                        "type": "string",
                        "description": "Ubicación geográfica del juego",
                        "能力项": "JSON"
                    },
                    "startDate": {
                        "type": "string",
                        "pattern": "^\\d{4}-\\d{2}-\\d{2}$|^$",
                        "能力项": "日期格式",
                        "description": "Hora de inicio"
                    },
                    "endDate": {
                        "type": "string",
                        "pattern": "^\\d{4}-\\d{2}-\\d{2}$|^$",
                        "能力项": "日期格式",
                        "description": "Hora de fin"
                    },
                    "detailDesc": {
                        "type": "string",
                        "description": "Introducción detallada del juego",
                        "能力项": "范围、200字以上",
                        "pattern": "^.*$|^$",
                        "minLength": 315,
                        "maxLength": 400
                    },
                    "price": {
                        "type": "array",
                        "description": "Información de precio de boleto",
                        "items": {
                            "type": "string"
                        },
                        "能力项": "主题约束"
                    },
                    "issueTime": {
                        "type": "string",
                        "pattern": "^\\d{4}-\\d{2}-\\d{2}$|^$",
                        "能力项": "日期格式",
                        "description": "Tiempo de lanzamiento de boletos"
                    },
                    "hasNightView": {
                        "type": "string",
                        "enum": [
                            "Sí",
                            "No"
                        ],
                        "description": "Si es una actividad nocturna",
                        "能力项": "特定格式"
                    },
                    "isParentChildFriendly": {
                        "type": "string",
                        "enum": [
                            "Sí",
                            "No"
                        ],
                        "description": "Si es adecuado para padres-hijos",
                        "能力项": "特定格式"
                    },
                    "isOutdoor": {
                        "type": "string",
                        "enum": [
                            "Sí",
                            "No"
                        ],
                        "description": "Si es un juego al aire libre",
                        "能力项": "特定格式"
                    },
                    "hasCulturalShow": {
                        "type": "string",
                        "enum": [
                            "Sí",
                            "No"
                        ],
                        "description": "Si incluye espectáculos culturales",
                        "能力项": "特定格式"
                    },
                    "hasHotSpring": {
                        "type": "string",
                        "enum": [
                            "Sí",
                            "No"
                        ],
                        "description": "Si tiene proyectos de aguas termales",
                        "能力项": "特定格式"
                    }
                },
                "required": [
                    "playName",
                    "briefDesc",
                    "location",
                    "startDate",
                    "endDate",
                    "detailDesc",
                    "price",
                    "issueTime",
                    "hasNightView",
                    "isParentChildFriendly",
                    "isOutdoor",
                    "hasCulturalShow",
                    "hasHotSpring"
                ]
            }
        },
        "sub_questions": [
            {
                "point_id": 0,
                "question": "Si cumple con el esquema",
                "rule": "SCHEMA:json_schema",
                "dep": [],
                "被依赖": false,
                "能力项": "JSON"
            }
        ]
    },
    {
        "category": "SCHEMA",
        "question": "Eres un analista profesional de artículos de puntos calientes de viaje. Te proporcionaré contenido de artículos y tipos de artículos. Necesitas ejecutar diferentes estrategias de identificación basadas en diferentes tipos de artículos. Solo devuelve la información de juegos extraída, no devuelvas ninguna otra información redundante.\nTipo de artículo: Auto-identificación\nPor favor extrae información según las siguientes reglas:\n1. playName: Nombre del juego, refiriéndose a nombres específicos de juegos o actividades mencionados en el artículo.\n2. briefDesc: Descripción de una oración, requerida para resumir los aspectos destacados y características del juego, excluyendo tiempo operativo, información práctica, descripciones negativas, 68-100 caracteres (incluir espacio, número...).\n3. location: Ubicación geográfica del juego, refiriéndose a puntos de referencia específicos o monumentos dentro de áreas escénicas o lugares, no puede ser ciudades o provincias.\n4. startDate/endDate: Rango de tiempo del juego, formato de fecha es xxxx-xx-xx, devolver cadena vacía si no se identifica.\n5. detailDesc: Introducción detallada del juego, requerida 315-400 caracteres (incluir espacio, número...), describiendo aspectos destacados y características del juego, excluyendo palabras de perspectiva de terceros.\n6. price: Información de precio de boleto, formato de retorno [\"\",\"\"], devolver lista vacía si no se identifica.\n7. issueTime: Si el juego pertenece a conciertos, festivales de música, Livehouse, cabaret y otros tipos, necesita identificar tiempo de lanzamiento de boletos, formato de fecha es xxxx-xx-xx, devolver cadena vacía si no hay ninguno.\n8. hasNightView: Si es una actividad nocturna (Sí/No).\n9. isParentChildFriendly: Si es adecuado para padres-hijos (Sí/No).\n10. isOutdoor: Si es un juego al aire libre (Sí/No).\n11. hasCulturalShow: Si incluye espectáculos culturales (Sí/No).\n12. hasHotSpring: Si tiene proyectos de aguas termales (Sí/No).\nRequisitos de salida:\n1. Usar formato JSON para devolver información extraída\n2. Cada juego como objeto, conteniendo todos los campos\n3. Todos los objetos de juego forman un array\n4. No devolver ningún carácter que no sea formato JSON\nEjemplo de formato de salida:\n[\n  {\"playName\":\"Nombre del juego\",\"briefDesc\":\"Descripción de una oración\",\"location\":\"Ubicación geográfica\",\"startDate\":\"Hora de inicio\",\"endDate\":\"Hora de fin\",\"detailDesc\":\"Introducción detallada del juego\",\"price\":[],\"issueTime\":\"Tiempo de lanzamiento de boletos\",\"hasNightView\":\"Sí/No\",\"isParentChildFriendly\":\"Sí/No\",\"isOutdoor\":\"Sí/No\",\"hasCulturalShow\":\"Sí/No\",\"hasHotSpring\":\"Sí/No\"}\n]\nContenido del artículo:El Festival de Hielo y Nieve de la Ciudad Prohibida se abre, exposiciones de esculturas de hielo, toboganes de nieve, bicicletas de hielo y otras formas ricas de jugar te esperan para experimentar, el espectáculo de luces nocturnas es romántico y soñador. Toda la familia puede encontrar diversión.",
        "json_schema": {
            "type": "array",
            "items": {
                "type": "object",
                "properties": {
                    "playName": {
                        "type": "string",
                        "description": "Nombre del juego",
                        "能力项": "JSON"
                    },
                    "briefDesc": {
                        "type": "string",
                        "description": "Descripción de una oración",
                        "能力项": "范围、50~200字",
                        "pattern": "^.*$|^$",
                        "minLength": 68,
                        "maxLength": 100
                    },
                    "location": {
                        "type": "string",
                        "description": "Ubicación geográfica del juego",
                        "能力项": "JSON"
                    },
                    "startDate": {
                        "type": "string",
                        "pattern": "^\\d{4}-\\d{2}-\\d{2}$|^$",
                        "能力项": "日期格式",
                        "description": "Hora de inicio"
                    },
                    "endDate": {
                        "type": "string",
                        "pattern": "^\\d{4}-\\d{2}-\\d{2}$|^$",
                        "能力项": "日期格式",
                        "description": "Hora de fin"
                    },
                    "detailDesc": {
                        "type": "string",
                        "description": "Introducción detallada del juego",
                        "能力项": "范围、200字以上",
                        "pattern": "^.*$|^$",
                        "minLength": 315,
                        "maxLength": 400
                    },
                    "price": {
                        "type": "array",
                        "description": "Información de precio de boleto",
                        "items": {
                            "type": "string"
                        },
                        "能力项": "主题约束"
                    },
                    "issueTime": {
                        "type": "string",
                        "pattern": "^\\d{4}-\\d{2}-\\d{2}$|^$",
                        "能力项": "日期格式",
                        "description": "Tiempo de lanzamiento de boletos"
                    },
                    "hasNightView": {
                        "type": "string",
                        "enum": [
                            "Sí",
                            "No"
                        ],
                        "description": "Si es una actividad nocturna",
                        "能力项": "特定格式"
                    },
                    "isParentChildFriendly": {
                        "type": "string",
                        "enum": [
                            "Sí",
                            "No"
                        ],
                        "description": "Si es adecuado para padres-hijos",
                        "能力项": "特定格式"
                    },
                    "isOutdoor": {
                        "type": "string",
                        "enum": [
                            "Sí",
                            "No"
                        ],
                        "description": "Si es un juego al aire libre",
                        "能力项": "特定格式"
                    },
                    "hasCulturalShow": {
                        "type": "string",
                        "enum": [
                            "Sí",
                            "No"
                        ],
                        "description": "Si incluye espectáculos culturales",
                        "能力项": "特定格式"
                    },
                    "hasHotSpring": {
                        "type": "string",
                        "enum": [
                            "Sí",
                            "No"
                        ],
                        "description": "Si tiene proyectos de aguas termales",
                        "能力项": "特定格式"
                    }
                },
                "required": [
                    "playName",
                    "briefDesc",
                    "location",
                    "startDate",
                    "endDate",
                    "detailDesc",
                    "price",
                    "issueTime",
                    "hasNightView",
                    "isParentChildFriendly",
                    "isOutdoor",
                    "hasCulturalShow",
                    "hasHotSpring"
                ]
            }
        },
        "sub_questions": [
            {
                "point_id": 0,
                "question": "Si cumple con el esquema",
                "rule": "SCHEMA:json_schema",
                "dep": [],
                "被依赖": false,
                "能力项": "JSON"
            }
        ]
    },
    {
        "category": "SCHEMA",
        "question": "Eres un analista profesional de artículos de puntos calientes de viaje. Te proporcionaré contenido de artículos y tipos de artículos. Necesitas ejecutar diferentes estrategias de identificación basadas en diferentes tipos de artículos. Solo devuelve la información de juegos extraída, no devuelvas ninguna otra información redundante.\nTipo de artículo: Auto-identificación\nPor favor extrae información según las siguientes reglas:\n1. playName: Nombre del juego, refiriéndose a nombres específicos de juegos o actividades mencionados en el artículo.\n2. briefDesc: Descripción de una oración, requerida para resumir los aspectos destacados y características del juego, excluyendo tiempo operativo, información práctica, descripciones negativas, 68-100 caracteres (incluir espacio, número...).\n3. location: Ubicación geográfica del juego, refiriéndose a puntos de referencia específicos o monumentos dentro de áreas escénicas o lugares, no puede ser ciudades o provincias.\n4. startDate/endDate: Rango de tiempo del juego, formato de fecha es xxxx-xx-xx, devolver cadena vacía si no se identifica.\n5. detailDesc: Introducción detallada del juego, requerida 315-400 caracteres (incluir espacio, número...), describiendo aspectos destacados y características del juego, excluyendo palabras de perspectiva de terceros.\n6. price: Información de precio de boleto, formato de retorno [\"\",\"\"], devolver lista vacía si no se identifica.\n7. issueTime: Si el juego pertenece a conciertos, festivales de música, Livehouse, cabaret y otros tipos, necesita identificar tiempo de lanzamiento de boletos, formato de fecha es xxxx-xx-xx, devolver cadena vacía si no hay ninguno.\n8. hasNightView: Si es una actividad nocturna (Sí/No).\n9. isParentChildFriendly: Si es adecuado para padres-hijos (Sí/No).\n10. isOutdoor: Si es un juego al aire libre (Sí/No).\n11. hasCulturalShow: Si incluye espectáculos culturales (Sí/No).\n12. hasHotSpring: Si tiene proyectos de aguas termales (Sí/No).\nRequisitos de salida:\n1. Usar formato JSON para devolver información extraída\n2. Cada juego como objeto, conteniendo todos los campos\n3. Todos los objetos de juego forman un array\n4. No devolver ningún carácter que no sea formato JSON\nEjemplo de formato de salida:\n[\n  {\"playName\":\"Nombre del juego\",\"briefDesc\":\"Descripción de una oración\",\"location\":\"Ubicación geográfica\",\"startDate\":\"Hora de inicio\",\"endDate\":\"Hora de fin\",\"detailDesc\":\"Introducción detallada del juego\",\"price\":[],\"issueTime\":\"Tiempo de lanzamiento de boletos\",\"hasNightView\":\"Sí/No\",\"isParentChildFriendly\":\"Sí/No\",\"isOutdoor\":\"Sí/No\",\"hasCulturalShow\":\"Sí/No\",\"hasHotSpring\":\"Sí/No\"}\n]\nContenido del artículo:Espectáculo de fuegos artificiales de Año Nuevo de Universal Studios, el mejor punto de vista es Hollywood Boulevard, fuegos artificiales y edificios temáticos están en el mismo marco, la atmósfera es explosiva, adecuado para citas de parejas y experiencia padre-hijo.",
        "json_schema": {
            "type": "array",
            "items": {
                "type": "object",
                "properties": {
                    "playName": {
                        "type": "string",
                        "description": "Nombre del juego",
                        "能力项": "JSON"
                    },
                    "briefDesc": {
                        "type": "string",
                        "description": "Descripción de una oración",
                        "能力项": "范围、50~200字",
                        "pattern": "^.*$|^$",
                        "minLength": 68,
                        "maxLength": 100
                    },
                    "location": {
                        "type": "string",
                        "description": "Ubicación geográfica del juego",
                        "能力项": "JSON"
                    },
                    "startDate": {
                        "type": "string",
                        "pattern": "^\\d{4}-\\d{2}-\\d{2}$|^$",
                        "能力项": "日期格式",
                        "description": "Hora de inicio"
                    },
                    "endDate": {
                        "type": "string",
                        "pattern": "^\\d{4}-\\d{2}-\\d{2}$|^$",
                        "能力项": "日期格式",
                        "description": "Hora de fin"
                    },
                    "detailDesc": {
                        "type": "string",
                        "description": "Introducción detallada del juego",
                        "能力项": "范围、200字以上",
                        "pattern": "^.*$|^$",
                        "minLength": 315,
                        "maxLength": 400
                    },
                    "price": {
                        "type": "array",
                        "description": "Información de precio de boleto",
                        "items": {
                            "type": "string"
                        },
                        "能力项": "主题约束"
                    },
                    "issueTime": {
                        "type": "string",
                        "pattern": "^\\d{4}-\\d{2}-\\d{2}$|^$",
                        "能力项": "日期格式",
                        "description": "Tiempo de lanzamiento de boletos"
                    },
                    "hasNightView": {
                        "type": "string",
                        "enum": [
                            "Sí",
                            "No"
                        ],
                        "description": "Si es una actividad nocturna",
                        "能力项": "特定格式"
                    },
                    "isParentChildFriendly": {
                        "type": "string",
                        "enum": [
                            "Sí",
                            "No"
                        ],
                        "description": "Si es adecuado para padres-hijos",
                        "能力项": "特定格式"
                    },
                    "isOutdoor": {
                        "type": "string",
                        "enum": [
                            "Sí",
                            "No"
                        ],
                        "description": "Si es un juego al aire libre",
                        "能力项": "特定格式"
                    },
                    "hasCulturalShow": {
                        "type": "string",
                        "enum": [
                            "Sí",
                            "No"
                        ],
                        "description": "Si incluye espectáculos culturales",
                        "能力项": "特定格式"
                    },
                    "hasHotSpring": {
                        "type": "string",
                        "enum": [
                            "Sí",
                            "No"
                        ],
                        "description": "Si tiene proyectos de aguas termales",
                        "能力项": "特定格式"
                    }
                },
                "required": [
                    "playName",
                    "briefDesc",
                    "location",
                    "startDate",
                    "endDate",
                    "detailDesc",
                    "price",
                    "issueTime",
                    "hasNightView",
                    "isParentChildFriendly",
                    "isOutdoor",
                    "hasCulturalShow",
                    "hasHotSpring"
                ]
            }
        },
        "sub_questions": [
            {
                "point_id": 0,
                "question": "Si cumple con el esquema",
                "rule": "SCHEMA:json_schema",
                "dep": [],
                "被依赖": false,
                "能力项": "JSON"
            }
        ]
    },
    {
        "category": "SCHEMA",
        "question": "Eres un analista profesional de artículos de puntos calientes de viaje. Te proporcionaré contenido de artículos y tipos de artículos. Necesitas ejecutar diferentes estrategias de identificación basadas en diferentes tipos de artículos. Solo devuelve la información de juegos extraída, no devuelvas ninguna otra información redundante.\nTipo de artículo: Auto-identificación\nPor favor extrae información según las siguientes reglas:\n1. playName: Nombre del juego, refiriéndose a nombres específicos de juegos o actividades mencionados en el artículo.\n2. briefDesc: Descripción de una oración, requerida para resumir los aspectos destacados y características del juego, excluyendo tiempo operativo, información práctica, descripciones negativas, 68-100 caracteres (incluir espacio, número...).\n3. location: Ubicación geográfica del juego, refiriéndose a puntos de referencia específicos o monumentos dentro de áreas escénicas o lugares, no puede ser ciudades o provincias.\n4. startDate/endDate: Rango de tiempo del juego, formato de fecha es xxxx-xx-xx, devolver cadena vacía si no se identifica.\n5. detailDesc: Introducción detallada del juego, requerida 315-400 caracteres (incluir espacio, número...), describiendo aspectos destacados y características del juego, excluyendo palabras de perspectiva de terceros.\n6. price: Información de precio de boleto, formato de retorno [\"\",\"\"], devolver lista vacía si no se identifica.\n7. issueTime: Si el juego pertenece a conciertos, festivales de música, Livehouse, cabaret y otros tipos, necesita identificar tiempo de lanzamiento de boletos, formato de fecha es xxxx-xx-xx, devolver cadena vacía si no hay ninguno.\n8. hasNightView: Si es una actividad nocturna (Sí/No).\n9. isParentChildFriendly: Si es adecuado para padres-hijos (Sí/No).\n10. isOutdoor: Si es un juego al aire libre (Sí/No).\n11. hasCulturalShow: Si incluye espectáculos culturales (Sí/No).\n12. hasHotSpring: Si tiene proyectos de aguas termales (Sí/No).\nRequisitos de salida:\n1. Usar formato JSON para devolver información extraída\n2. Cada juego como objeto, conteniendo todos los campos\n3. Todos los objetos de juego forman un array\n4. No devolver ningún carácter que no sea formato JSON\nEjemplo de formato de salida:\n[\n  {\"playName\":\"Nombre del juego\",\"briefDesc\":\"Descripción de una oración\",\"location\":\"Ubicación geográfica\",\"startDate\":\"Hora de inicio\",\"endDate\":\"Hora de fin\",\"detailDesc\":\"Introducción detallada del juego\",\"price\":[],\"issueTime\":\"Tiempo de lanzamiento de boletos\",\"hasNightView\":\"Sí/No\",\"isParentChildFriendly\":\"Sí/No\",\"isOutdoor\":\"Sí/No\",\"hasCulturalShow\":\"Sí/No\",\"hasHotSpring\":\"Sí/No\"}\n]\nContenido del artículo:El Festival del Barco Dragón del Lago Oeste comienza en el Día del Barco Dragón, carreras de barcos dragón, actuaciones folclóricas, comida del festival del barco dragón están todos disponibles, la experiencia de visualización de la orilla es excelente, hay espectáculos de luz y agua por la noche.",
        "json_schema": {
            "type": "array",
            "items": {
                "type": "object",
                "properties": {
                    "playName": {
                        "type": "string",
                        "description": "Nombre del juego",
                        "能力项": "JSON"
                    },
                    "briefDesc": {
                        "type": "string",
                        "description": "Descripción de una oración",
                        "能力项": "范围、50~200字",
                        "pattern": "^.*$|^$",
                        "minLength": 68,
                        "maxLength": 100
                    },
                    "location": {
                        "type": "string",
                        "description": "Ubicación geográfica del juego",
                        "能力项": "JSON"
                    },
                    "startDate": {
                        "type": "string",
                        "pattern": "^\\d{4}-\\d{2}-\\d{2}$|^$",
                        "能力项": "日期格式",
                        "description": "Hora de inicio"
                    },
                    "endDate": {
                        "type": "string",
                        "pattern": "^\\d{4}-\\d{2}-\\d{2}$|^$",
                        "能力项": "日期格式",
                        "description": "Hora de fin"
                    },
                    "detailDesc": {
                        "type": "string",
                        "description": "Introducción detallada del juego",
                        "能力项": "范围、200字以上",
                        "pattern": "^.*$|^$",
                        "minLength": 315,
                        "maxLength": 400
                    },
                    "price": {
                        "type": "array",
                        "description": "Información de precio de boleto",
                        "items": {
                            "type": "string"
                        },
                        "能力项": "主题约束"
                    },
                    "issueTime": {
                        "type": "string",
                        "pattern": "^\\d{4}-\\d{2}-\\d{2}$|^$",
                        "能力项": "日期格式",
                        "description": "Tiempo de lanzamiento de boletos"
                    },
                    "hasNightView": {
                        "type": "string",
                        "enum": [
                            "Sí",
                            "No"
                        ],
                        "description": "Si es una actividad nocturna",
                        "能力项": "特定格式"
                    },
                    "isParentChildFriendly": {
                        "type": "string",
                        "enum": [
                            "Sí",
                            "No"
                        ],
                        "description": "Si es adecuado para padres-hijos",
                        "能力项": "特定格式"
                    },
                    "isOutdoor": {
                        "type": "string",
                        "enum": [
                            "Sí",
                            "No"
                        ],
                        "description": "Si es un juego al aire libre",
                        "能力项": "特定格式"
                    },
                    "hasCulturalShow": {
                        "type": "string",
                        "enum": [
                            "Sí",
                            "No"
                        ],
                        "description": "Si incluye espectáculos culturales",
                        "能力项": "特定格式"
                    },
                    "hasHotSpring": {
                        "type": "string",
                        "enum": [
                            "Sí",
                            "No"
                        ],
                        "description": "Si tiene proyectos de aguas termales",
                        "能力项": "特定格式"
                    }
                },
                "required": [
                    "playName",
                    "briefDesc",
                    "location",
                    "startDate",
                    "endDate",
                    "detailDesc",
                    "price",
                    "issueTime",
                    "hasNightView",
                    "isParentChildFriendly",
                    "isOutdoor",
                    "hasCulturalShow",
                    "hasHotSpring"
                ]
            }
        },
        "sub_questions": [
            {
                "point_id": 0,
                "question": "Si cumple con el esquema",
                "rule": "SCHEMA:json_schema",
                "dep": [],
                "被依赖": false,
                "能力项": "JSON"
            }
        ]
    },
    {
        "category": "SCHEMA",
        "question": "Eres un analista profesional de artículos de puntos calientes de viaje. Te proporcionaré contenido de artículos y tipos de artículos. Necesitas ejecutar diferentes estrategias de identificación basadas en diferentes tipos de artículos. Solo devuelve la información de juegos extraída, no devuelvas ninguna otra información redundante.\nTipo de artículo: Auto-identificación\nPor favor extrae información según las siguientes reglas:\n1. playName: Nombre del juego, refiriéndose a nombres específicos de juegos o actividades mencionados en el artículo.\n2. briefDesc: Descripción de una oración, requerida para resumir los aspectos destacados y características del juego, excluyendo tiempo operativo, información práctica, descripciones negativas, 68-100 caracteres (incluir espacio, número...).\n3. location: Ubicación geográfica del juego, refiriéndose a puntos de referencia específicos o monumentos dentro de áreas escénicas o lugares, no puede ser ciudades o provincias.\n4. startDate/endDate: Rango de tiempo del juego, formato de fecha es xxxx-xx-xx, devolver cadena vacía si no se identifica.\n5. detailDesc: Introducción detallada del juego, requerida 315-400 caracteres (incluir espacio, número...), describiendo aspectos destacados y características del juego, excluyendo palabras de perspectiva de terceros.\n6. price: Información de precio de boleto, formato de retorno [\"\",\"\"], devolver lista vacía si no se identifica.\n7. issueTime: Si el juego pertenece a conciertos, festivales de música, Livehouse, cabaret y otros tipos, necesita identificar tiempo de lanzamiento de boletos, formato de fecha es xxxx-xx-xx, devolver cadena vacía si no hay ninguno.\n8. hasNightView: Si es una actividad nocturna (Sí/No).\n9. isParentChildFriendly: Si es adecuado para padres-hijos (Sí/No).\n10. isOutdoor: Si es un juego al aire libre (Sí/No).\n11. hasCulturalShow: Si incluye espectáculos culturales (Sí/No).\n12. hasHotSpring: Si tiene proyectos de aguas termales (Sí/No).\nRequisitos de salida:\n1. Usar formato JSON para devolver información extraída\n2. Cada juego como objeto, conteniendo todos los campos\n3. Todos los objetos de juego forman un array\n4. No devolver ningún carácter que no sea formato JSON\nEjemplo de formato de salida:\n[\n  {\"playName\":\"Nombre del juego\",\"briefDesc\":\"Descripción de una oración\",\"location\":\"Ubicación geográfica\",\"startDate\":\"Hora de inicio\",\"endDate\":\"Hora de fin\",\"detailDesc\":\"Introducción detallada del juego\",\"price\":[],\"issueTime\":\"Tiempo de lanzamiento de boletos\",\"hasNightView\":\"Sí/No\",\"isParentChildFriendly\":\"Sí/No\",\"isOutdoor\":\"Sí/No\",\"hasCulturalShow\":\"Sí/No\",\"hasHotSpring\":\"Sí/No\"}\n]\nContenido del artículo:El parque acuático Chimelong está abierto por la noche en verano. La fiesta del agua y el espectáculo de luz y música electrónica harán que todo el lugar se emocione. La experiencia de tour nocturno es única y adecuada para padres e hijos y jóvenes.",
        "json_schema": {
            "type": "array",
            "items": {
                "type": "object",
                "properties": {
                    "playName": {
                        "type": "string",
                        "description": "Nombre del juego",
                        "能力项": "JSON"
                    },
                    "briefDesc": {
                        "type": "string",
                        "description": "Descripción de una oración",
                        "能力项": "范围、50~200字",
                        "pattern": "^.*$|^$",
                        "minLength": 68,
                        "maxLength": 100
                    },
                    "location": {
                        "type": "string",
                        "description": "Ubicación geográfica del juego",
                        "能力项": "JSON"
                    },
                    "startDate": {
                        "type": "string",
                        "pattern": "^\\d{4}-\\d{2}-\\d{2}$|^$",
                        "能力项": "日期格式",
                        "description": "Hora de inicio"
                    },
                    "endDate": {
                        "type": "string",
                        "pattern": "^\\d{4}-\\d{2}-\\d{2}$|^$",
                        "能力项": "日期格式",
                        "description": "Hora de fin"
                    },
                    "detailDesc": {
                        "type": "string",
                        "description": "Introducción detallada del juego",
                        "能力项": "范围、200字以上",
                        "pattern": "^.*$|^$",
                        "minLength": 315,
                        "maxLength": 400
                    },
                    "price": {
                        "type": "array",
                        "description": "Información de precio de boleto",
                        "items": {
                            "type": "string"
                        },
                        "能力项": "主题约束"
                    },
                    "issueTime": {
                        "type": "string",
                        "pattern": "^\\d{4}-\\d{2}-\\d{2}$|^$",
                        "能力项": "日期格式",
                        "description": "Tiempo de lanzamiento de boletos"
                    },
                    "hasNightView": {
                        "type": "string",
                        "enum": [
                            "Sí",
                            "No"
                        ],
                        "description": "Si es una actividad nocturna",
                        "能力项": "特定格式"
                    },
                    "isParentChildFriendly": {
                        "type": "string",
                        "enum": [
                            "Sí",
                            "No"
                        ],
                        "description": "Si es adecuado para padres-hijos",
                        "能力项": "特定格式"
                    },
                    "isOutdoor": {
                        "type": "string",
                        "enum": [
                            "Sí",
                            "No"
                        ],
                        "description": "Si es un juego al aire libre",
                        "能力项": "特定格式"
                    },
                    "hasCulturalShow": {
                        "type": "string",
                        "enum": [
                            "Sí",
                            "No"
                        ],
                        "description": "Si incluye espectáculos culturales",
                        "能力项": "特定格式"
                    },
                    "hasHotSpring": {
                        "type": "string",
                        "enum": [
                            "Sí",
                            "No"
                        ],
                        "description": "Si tiene proyectos de aguas termales",
                        "能力项": "特定格式"
                    }
                },
                "required": [
                    "playName",
                    "briefDesc",
                    "location",
                    "startDate",
                    "endDate",
                    "detailDesc",
                    "price",
                    "issueTime",
                    "hasNightView",
                    "isParentChildFriendly",
                    "isOutdoor",
                    "hasCulturalShow",
                    "hasHotSpring"
                ]
            }
        },
        "sub_questions": [
            {
                "point_id": 0,
                "question": "Si cumple con el esquema",
                "rule": "SCHEMA:json_schema",
                "dep": [],
                "被依赖": false,
                "能力项": "JSON"
            }
        ]
    },
    {
        "category": "SCHEMA",
        "question": "Eres un analista profesional de artículos de puntos calientes de viaje. Te proporcionaré contenido de artículos y tipos de artículos. Necesitas ejecutar diferentes estrategias de identificación basadas en diferentes tipos de artículos. Solo devuelve la información de juegos extraída, no devuelvas ninguna otra información redundante.\nTipo de artículo: Auto-identificación\nPor favor extrae información según las siguientes reglas:\n1. playName: Nombre del juego, refiriéndose a nombres específicos de juegos o actividades mencionados en el artículo.\n2. briefDesc: Descripción de una oración, requerida para resumir los aspectos destacados y características del juego, excluyendo tiempo operativo, información práctica, descripciones negativas, 68-100 caracteres (incluir espacio, número...).\n3. location: Ubicación geográfica del juego, refiriéndose a puntos de referencia específicos o monumentos dentro de áreas escénicas o lugares, no puede ser ciudades o provincias.\n4. startDate/endDate: Rango de tiempo del juego, formato de fecha es xxxx-xx-xx, devolver cadena vacía si no se identifica.\n5. detailDesc: Introducción detallada del juego, requerida 315-400 caracteres (incluir espacio, número...), describiendo aspectos destacados y características del juego, excluyendo palabras de perspectiva de terceros.\n6. price: Información de precio de boleto, formato de retorno [\"\",\"\"], devolver lista vacía si no se identifica.\n7. issueTime: Si el juego pertenece a conciertos, festivales de música, Livehouse, cabaret y otros tipos, necesita identificar tiempo de lanzamiento de boletos, formato de fecha es xxxx-xx-xx, devolver cadena vacía si no hay ninguno.\n8. hasNightView: Si es una actividad nocturna (Sí/No).\n9. isParentChildFriendly: Si es adecuado para padres-hijos (Sí/No).\n10. isOutdoor: Si es un juego al aire libre (Sí/No).\n11. hasCulturalShow: Si incluye espectáculos culturales (Sí/No).\n12. hasHotSpring: Si tiene proyectos de aguas termales (Sí/No).\nRequisitos de salida:\n1. Usar formato JSON para devolver información extraída\n2. Cada juego como objeto, conteniendo todos los campos\n3. Todos los objetos de juego forman un array\n4. No devolver ningún carácter que no sea formato JSON\nEjemplo de formato de salida:\n[\n  {\"playName\":\"Nombre del juego\",\"briefDesc\":\"Descripción de una oración\",\"location\":\"Ubicación geográfica\",\"startDate\":\"Hora de inicio\",\"endDate\":\"Hora de fin\",\"detailDesc\":\"Introducción detallada del juego\",\"price\":[],\"issueTime\":\"Tiempo de lanzamiento de boletos\",\"hasNightView\":\"Sí/No\",\"isParentChildFriendly\":\"Sí/No\",\"isOutdoor\":\"Sí/No\",\"hasCulturalShow\":\"Sí/No\",\"hasHotSpring\":\"Sí/No\"}\n]\nContenido del artículo:Desfile navideño de Shanghai Disneyland, todos los miembros de la familia Mickey están fuera, la ceremonia de encendido del árbol de Navidad es cálida y romántica. El espectáculo nocturno de fuegos artificiales y el espectáculo de luces se complementan.",
        "json_schema": {
            "type": "array",
            "items": {
                "type": "object",
                "properties": {
                    "playName": {
                        "type": "string",
                        "description": "Nombre del juego",
                        "能力项": "JSON"
                    },
                    "briefDesc": {
                        "type": "string",
                        "description": "Descripción de una oración",
                        "能力项": "范围、50~200字",
                        "pattern": "^.*$|^$",
                        "minLength": 68,
                        "maxLength": 100
                    },
                    "location": {
                        "type": "string",
                        "description": "Ubicación geográfica del juego",
                        "能力项": "JSON"
                    },
                    "startDate": {
                        "type": "string",
                        "pattern": "^\\d{4}-\\d{2}-\\d{2}$|^$",
                        "能力项": "日期格式",
                        "description": "Hora de inicio"
                    },
                    "endDate": {
                        "type": "string",
                        "pattern": "^\\d{4}-\\d{2}-\\d{2}$|^$",
                        "能力项": "日期格式",
                        "description": "Hora de fin"
                    },
                    "detailDesc": {
                        "type": "string",
                        "description": "Introducción detallada del juego",
                        "能力项": "范围、200字以上",
                        "pattern": "^.*$|^$",
                        "minLength": 315,
                        "maxLength": 400
                    },
                    "price": {
                        "type": "array",
                        "description": "Información de precio de boleto",
                        "items": {
                            "type": "string"
                        },
                        "能力项": "主题约束"
                    },
                    "issueTime": {
                        "type": "string",
                        "pattern": "^\\d{4}-\\d{2}-\\d{2}$|^$",
                        "能力项": "日期格式",
                        "description": "Tiempo de lanzamiento de boletos"
                    },
                    "hasNightView": {
                        "type": "string",
                        "enum": [
                            "Sí",
                            "No"
                        ],
                        "description": "Si es una actividad nocturna",
                        "能力项": "特定格式"
                    },
                    "isParentChildFriendly": {
                        "type": "string",
                        "enum": [
                            "Sí",
                            "No"
                        ],
                        "description": "Si es adecuado para padres-hijos",
                        "能力项": "特定格式"
                    },
                    "isOutdoor": {
                        "type": "string",
                        "enum": [
                            "Sí",
                            "No"
                        ],
                        "description": "Si es un juego al aire libre",
                        "能力项": "特定格式"
                    },
                    "hasCulturalShow": {
                        "type": "string",
                        "enum": [
                            "Sí",
                            "No"
                        ],
                        "description": "Si incluye espectáculos culturales",
                        "能力项": "特定格式"
                    },
                    "hasHotSpring": {
                        "type": "string",
                        "enum": [
                            "Sí",
                            "No"
                        ],
                        "description": "Si tiene proyectos de aguas termales",
                        "能力项": "特定格式"
                    }
                },
                "required": [
                    "playName",
                    "briefDesc",
                    "location",
                    "startDate",
                    "endDate",
                    "detailDesc",
                    "price",
                    "issueTime",
                    "hasNightView",
                    "isParentChildFriendly",
                    "isOutdoor",
                    "hasCulturalShow",
                    "hasHotSpring"
                ]
            }
        },
        "sub_questions": [
            {
                "point_id": 0,
                "question": "Si cumple con el esquema",
                "rule": "SCHEMA:json_schema",
                "dep": [],
                "被依赖": false,
                "能力项": "JSON"
            }
        ]
    },
    {
        "category": "SCHEMA",
        "question": "Eres un analista profesional de artículos de puntos calientes de viaje. Te proporcionaré contenido de artículos y tipos de artículos. Necesitas ejecutar diferentes estrategias de identificación basadas en diferentes tipos de artículos. Solo devuelve la información de juegos extraída, no devuelvas ninguna otra información redundante.\nTipo de artículo: Auto-identificación\nPor favor extrae información según las siguientes reglas:\n1. playName: Nombre del juego, refiriéndose a nombres específicos de juegos o actividades mencionados en el artículo.\n2. briefDesc: Descripción de una oración, requerida para resumir los aspectos destacados y características del juego, excluyendo tiempo operativo, información práctica, descripciones negativas, 68-100 caracteres (incluir espacio, número...).\n3. location: Ubicación geográfica del juego, refiriéndose a puntos de referencia específicos o monumentos dentro de áreas escénicas o lugares, no puede ser ciudades o provincias.\n4. startDate/endDate: Rango de tiempo del juego, formato de fecha es xxxx-xx-xx, devolver cadena vacía si no se identifica.\n5. detailDesc: Introducción detallada del juego, requerida 315-400 caracteres (incluir espacio, número...), describiendo aspectos destacados y características del juego, excluyendo palabras de perspectiva de terceros.\n6. price: Información de precio de boleto, formato de retorno [\"\",\"\"], devolver lista vacía si no se identifica.\n7. issueTime: Si el juego pertenece a conciertos, festivales de música, Livehouse, cabaret y otros tipos, necesita identificar tiempo de lanzamiento de boletos, formato de fecha es xxxx-xx-xx, devolver cadena vacía si no hay ninguno.\n8. hasNightView: Si es una actividad nocturna (Sí/No).\n9. isParentChildFriendly: Si es adecuado para padres-hijos (Sí/No).\n10. isOutdoor: Si es un juego al aire libre (Sí/No).\n11. hasCulturalShow: Si incluye espectáculos culturales (Sí/No).\n12. hasHotSpring: Si tiene proyectos de aguas termales (Sí/No).\nRequisitos de salida:\n1. Usar formato JSON para devolver información extraída\n2. Cada juego como objeto, conteniendo todos los campos\n3. Todos los objetos de juego forman un array\n4. No devolver ningún carácter que no sea formato JSON\nEjemplo de formato de salida:\n[\n  {\"playName\":\"Nombre del juego\",\"briefDesc\":\"Descripción de una oración\",\"location\":\"Ubicación geográfica\",\"startDate\":\"Hora de inicio\",\"endDate\":\"Hora de fin\",\"detailDesc\":\"Introducción detallada del juego\",\"price\":[],\"issueTime\":\"Tiempo de lanzamiento de boletos\",\"hasNightView\":\"Sí/No\",\"isParentChildFriendly\":\"Sí/No\",\"isOutdoor\":\"Sí/No\",\"hasCulturalShow\":\"Sí/No\",\"hasHotSpring\":\"Sí/No\"}\n]\nContenido del artículo:Festival de música del mercado nocturno de Chongqing Hongyadong, bandas independientes actúan por turnos, la vista nocturna de la ribera y la música están perfectamente integradas, padres e hijos, parejas son adecuados para check-ins nocturnos.",
        "json_schema": {
            "type": "array",
            "items": {
                "type": "object",
                "properties": {
                    "playName": {
                        "type": "string",
                        "description": "Nombre del juego",
                        "能力项": "JSON"
                    },
                    "briefDesc": {
                        "type": "string",
                        "description": "Descripción de una oración",
                        "能力项": "范围、50~200字",
                        "pattern": "^.*$|^$",
                        "minLength": 68,
                        "maxLength": 100
                    },
                    "location": {
                        "type": "string",
                        "description": "Ubicación geográfica del juego",
                        "能力项": "JSON"
                    },
                    "startDate": {
                        "type": "string",
                        "pattern": "^\\d{4}-\\d{2}-\\d{2}$|^$",
                        "能力项": "日期格式",
                        "description": "Hora de inicio"
                    },
                    "endDate": {
                        "type": "string",
                        "pattern": "^\\d{4}-\\d{2}-\\d{2}$|^$",
                        "能力项": "日期格式",
                        "description": "Hora de fin"
                    },
                    "detailDesc": {
                        "type": "string",
                        "description": "Introducción detallada del juego",
                        "能力项": "范围、200字以上",
                        "pattern": "^.*$|^$",
                        "minLength": 315,
                        "maxLength": 400
                    },
                    "price": {
                        "type": "array",
                        "description": "Información de precio de boleto",
                        "items": {
                            "type": "string"
                        },
                        "能力项": "主题约束"
                    },
                    "issueTime": {
                        "type": "string",
                        "pattern": "^\\d{4}-\\d{2}-\\d{2}$|^$",
                        "能力项": "日期格式",
                        "description": "Tiempo de lanzamiento de boletos"
                    },
                    "hasNightView": {
                        "type": "string",
                        "enum": [
                            "Sí",
                            "No"
                        ],
                        "description": "Si es una actividad nocturna",
                        "能力项": "特定格式"
                    },
                    "isParentChildFriendly": {
                        "type": "string",
                        "enum": [
                            "Sí",
                            "No"
                        ],
                        "description": "Si es adecuado para padres-hijos",
                        "能力项": "特定格式"
                    },
                    "isOutdoor": {
                        "type": "string",
                        "enum": [
                            "Sí",
                            "No"
                        ],
                        "description": "Si es un juego al aire libre",
                        "能力项": "特定格式"
                    },
                    "hasCulturalShow": {
                        "type": "string",
                        "enum": [
                            "Sí",
                            "No"
                        ],
                        "description": "Si incluye espectáculos culturales",
                        "能力项": "特定格式"
                    },
                    "hasHotSpring": {
                        "type": "string",
                        "enum": [
                            "Sí",
                            "No"
                        ],
                        "description": "Si tiene proyectos de aguas termales",
                        "能力项": "特定格式"
                    }
                },
                "required": [
                    "playName",
                    "briefDesc",
                    "location",
                    "startDate",
                    "endDate",
                    "detailDesc",
                    "price",
                    "issueTime",
                    "hasNightView",
                    "isParentChildFriendly",
                    "isOutdoor",
                    "hasCulturalShow",
                    "hasHotSpring"
                ]
            }
        },
        "sub_questions": [
            {
                "point_id": 0,
                "question": "Si cumple con el esquema",
                "rule": "SCHEMA:json_schema",
                "dep": [],
                "被依赖": false,
                "能力项": "JSON"
            }
        ]
    },
    {
        "category": "SCHEMA",
        "question": "Eres un analista profesional de artículos de puntos calientes de viaje. Te proporcionaré contenido de artículos y tipos de artículos. Necesitas ejecutar diferentes estrategias de identificación basadas en diferentes tipos de artículos. Solo devuelve la información de juegos extraída, no devuelvas ninguna otra información redundante.\nTipo de artículo: Auto-identificación\nPor favor extrae información según las siguientes reglas:\n1. playName: Nombre del juego, refiriéndose a nombres específicos de juegos o actividades mencionados en el artículo.\n2. briefDesc: Descripción de una oración, requerida para resumir los aspectos destacados y características del juego, excluyendo tiempo operativo, información práctica, descripciones negativas, 68-100 caracteres (incluir espacio, número...).\n3. location: Ubicación geográfica del juego, refiriéndose a puntos de referencia específicos o monumentos dentro de áreas escénicas o lugares, no puede ser ciudades o provincias.\n4. startDate/endDate: Rango de tiempo del juego, formato de fecha es xxxx-xx-xx, devolver cadena vacía si no se identifica.\n5. detailDesc: Introducción detallada del juego, requerida 315-400 caracteres (incluir espacio, número...), describiendo aspectos destacados y características del juego, excluyendo palabras de perspectiva de terceros.\n6. price: Información de precio de boleto, formato de retorno [\"\",\"\"], devolver lista vacía si no se identifica.\n7. issueTime: Si el juego pertenece a conciertos, festivales de música, Livehouse, cabaret y otros tipos, necesita identificar tiempo de lanzamiento de boletos, formato de fecha es xxxx-xx-xx, devolver cadena vacía si no hay ninguno.\n8. hasNightView: Si es una actividad nocturna (Sí/No).\n9. isParentChildFriendly: Si es adecuado para padres-hijos (Sí/No).\n10. isOutdoor: Si es un juego al aire libre (Sí/No).\n11. hasCulturalShow: Si incluye espectáculos culturales (Sí/No).\n12. hasHotSpring: Si tiene proyectos de aguas termales (Sí/No).\nRequisitos de salida:\n1. Usar formato JSON para devolver información extraída\n2. Cada juego como objeto, conteniendo todos los campos\n3. Todos los objetos de juego forman un array\n4. No devolver ningún carácter que no sea formato JSON\nEjemplo de formato de salida:\n[\n  {\"playName\":\"Nombre del juego\",\"briefDesc\":\"Descripción de una oración\",\"location\":\"Ubicación geográfica\",\"startDate\":\"Hora de inicio\",\"endDate\":\"Hora de fin\",\"detailDesc\":\"Introducción detallada del juego\",\"price\":[],\"issueTime\":\"Tiempo de lanzamiento de boletos\",\"hasNightView\":\"Sí/No\",\"isParentChildFriendly\":\"Sí/No\",\"isOutdoor\":\"Sí/No\",\"hasCulturalShow\":\"Sí/No\",\"hasHotSpring\":\"Sí/No\"}\n]\nContenido del artículo:Feria del templo de Año Nuevo de la ciudad antigua de Dali, danza Bai, mercado folclórico, espectáculo de fuegos artificiales ilumina el cielo nocturno de la ciudad antigua, experiencia de aguas termales y comida del mercado nocturno son ricas y coloridas.",
        "json_schema": {
            "type": "array",
            "items": {
                "type": "object",
                "properties": {
                    "playName": {
                        "type": "string",
                        "description": "Nombre del juego",
                        "能力项": "JSON"
                    },
                    "briefDesc": {
                        "type": "string",
                        "description": "Descripción de una oración",
                        "能力项": "范围、50~200字",
                        "pattern": "^.*$|^$",
                        "minLength": 68,
                        "maxLength": 100
                    },
                    "location": {
                        "type": "string",
                        "description": "Ubicación geográfica del juego",
                        "能力项": "JSON"
                    },
                    "startDate": {
                        "type": "string",
                        "pattern": "^\\d{4}-\\d{2}-\\d{2}$|^$",
                        "能力项": "日期格式",
                        "description": "Hora de inicio"
                    },
                    "endDate": {
                        "type": "string",
                        "pattern": "^\\d{4}-\\d{2}-\\d{2}$|^$",
                        "能力项": "日期格式",
                        "description": "Hora de fin"
                    },
                    "detailDesc": {
                        "type": "string",
                        "description": "Introducción detallada del juego",
                        "能力项": "范围、200字以上",
                        "pattern": "^.*$|^$",
                        "minLength": 315,
                        "maxLength": 400
                    },
                    "price": {
                        "type": "array",
                        "description": "Información de precio de boleto",
                        "items": {
                            "type": "string"
                        },
                        "能力项": "主题约束"
                    },
                    "issueTime": {
                        "type": "string",
                        "pattern": "^\\d{4}-\\d{2}-\\d{2}$|^$",
                        "能力项": "日期格式",
                        "description": "Tiempo de lanzamiento de boletos"
                    },
                    "hasNightView": {
                        "type": "string",
                        "enum": [
                            "Sí",
                            "No"
                        ],
                        "description": "Si es una actividad nocturna",
                        "能力项": "特定格式"
                    },
                    "isParentChildFriendly": {
                        "type": "string",
                        "enum": [
                            "Sí",
                            "No"
                        ],
                        "description": "Si es adecuado para padres-hijos",
                        "能力项": "特定格式"
                    },
                    "isOutdoor": {
                        "type": "string",
                        "enum": [
                            "Sí",
                            "No"
                        ],
                        "description": "Si es un juego al aire libre",
                        "能力项": "特定格式"
                    },
                    "hasCulturalShow": {
                        "type": "string",
                        "enum": [
                            "Sí",
                            "No"
                        ],
                        "description": "Si incluye espectáculos culturales",
                        "能力项": "特定格式"
                    },
                    "hasHotSpring": {
                        "type": "string",
                        "enum": [
                            "Sí",
                            "No"
                        ],
                        "description": "Si tiene proyectos de aguas termales",
                        "能力项": "特定格式"
                    }
                },
                "required": [
                    "playName",
                    "briefDesc",
                    "location",
                    "startDate",
                    "endDate",
                    "detailDesc",
                    "price",
                    "issueTime",
                    "hasNightView",
                    "isParentChildFriendly",
                    "isOutdoor",
                    "hasCulturalShow",
                    "hasHotSpring"
                ]
            }
        },
        "sub_questions": [
            {
                "point_id": 0,
                "question": "Si cumple con el esquema",
                "rule": "SCHEMA:json_schema",
                "dep": [],
                "被依赖": false,
                "能力项": "JSON"
            }
        ]
    },
    {
        "category": "SCHEMA",
        "question": "Eres un analista profesional de artículos de puntos calientes de viaje. Te proporcionaré contenido de artículos y tipos de artículos. Necesitas ejecutar diferentes estrategias de identificación basadas en diferentes tipos de artículos. Solo devuelve la información de juegos extraída, no devuelvas ninguna otra información redundante.\nTipo de artículo: Auto-identificación\nPor favor extrae información según las siguientes reglas:\n1. playName: Nombre del juego, refiriéndose a nombres específicos de juegos o actividades mencionados en el artículo.\n2. briefDesc: Descripción de una oración, requerida para resumir los aspectos destacados y características del juego, excluyendo tiempo operativo, información práctica, descripciones negativas, 68-100 caracteres (incluir espacio, número...).\n3. location: Ubicación geográfica del juego, refiriéndose a puntos de referencia específicos o monumentos dentro de áreas escénicas o lugares, no puede ser ciudades o provincias.\n4. startDate/endDate: Rango de tiempo del juego, formato de fecha es xxxx-xx-xx, devolver cadena vacía si no se identifica.\n5. detailDesc: Introducción detallada del juego, requerida 315-400 caracteres (incluir espacio, número...), describiendo aspectos destacados y características del juego, excluyendo palabras de perspectiva de terceros.\n6. price: Información de precio de boleto, formato de retorno [\"\",\"\"], devolver lista vacía si no se identifica.\n7. issueTime: Si el juego pertenece a conciertos, festivales de música, Livehouse, cabaret y otros tipos, necesita identificar tiempo de lanzamiento de boletos, formato de fecha es xxxx-xx-xx, devolver cadena vacía si no hay ninguno.\n8. hasNightView: Si es una actividad nocturna (Sí/No).\n9. isParentChildFriendly: Si es adecuado para padres-hijos (Sí/No).\n10. isOutdoor: Si es un juego al aire libre (Sí/No).\n11. hasCulturalShow: Si incluye espectáculos culturales (Sí/No).\n12. hasHotSpring: Si tiene proyectos de aguas termales (Sí/No).\nRequisitos de salida:\n1. Usar formato JSON para devolver información extraída\n2. Cada juego como objeto, conteniendo todos los campos\n3. Todos los objetos de juego forman un array\n4. No devolver ningún carácter que no sea formato JSON\nEjemplo de formato de salida:\n[\n  {\"playName\":\"Nombre del juego\",\"briefDesc\":\"Descripción de una oración\",\"location\":\"Ubicación geográfica\",\"startDate\":\"Hora de inicio\",\"endDate\":\"Hora de fin\",\"detailDesc\":\"Introducción detallada del juego\",\"price\":[],\"issueTime\":\"Tiempo de lanzamiento de boletos\",\"hasNightView\":\"Sí/No\",\"isParentChildFriendly\":\"Sí/No\",\"isOutdoor\":\"Sí/No\",\"hasCulturalShow\":\"Sí/No\",\"hasHotSpring\":\"Sí/No\"}\n]\nContenido del artículo:Tour científico padre-hijo de la base de pandas de Chengdu, explicación de pandas, experiencia hecha a mano, souvenirs temáticos ricos y coloridos, el parque tiene un pequeño espectáculo de luces nocturnas.",
        "json_schema": {
            "type": "array",
            "items": {
                "type": "object",
                "properties": {
                    "playName": {
                        "type": "string",
                        "description": "Nombre del juego",
                        "能力项": "JSON"
                    },
                    "briefDesc": {
                        "type": "string",
                        "description": "Descripción de una oración",
                        "能力项": "范围、50~200字",
                        "pattern": "^.*$|^$",
                        "minLength": 68,
                        "maxLength": 100
                    },
                    "location": {
                        "type": "string",
                        "description": "Ubicación geográfica del juego",
                        "能力项": "JSON"
                    },
                    "startDate": {
                        "type": "string",
                        "pattern": "^\\d{4}-\\d{2}-\\d{2}$|^$",
                        "能力项": "日期格式",
                        "description": "Hora de inicio"
                    },
                    "endDate": {
                        "type": "string",
                        "pattern": "^\\d{4}-\\d{2}-\\d{2}$|^$",
                        "能力项": "日期格式",
                        "description": "Hora de fin"
                    },
                    "detailDesc": {
                        "type": "string",
                        "description": "Introducción detallada del juego",
                        "能力项": "范围、200字以上",
                        "pattern": "^.*$|^$",
                        "minLength": 315,
                        "maxLength": 400
                    },
                    "price": {
                        "type": "array",
                        "description": "Información de precio de boleto",
                        "items": {
                            "type": "string"
                        },
                        "能力项": "主题约束"
                    },
                    "issueTime": {
                        "type": "string",
                        "pattern": "^\\d{4}-\\d{2}-\\d{2}$|^$",
                        "能力项": "日期格式",
                        "description": "Tiempo de lanzamiento de boletos"
                    },
                    "hasNightView": {
                        "type": "string",
                        "enum": [
                            "Sí",
                            "No"
                        ],
                        "description": "Si es una actividad nocturna",
                        "能力项": "特定格式"
                    },
                    "isParentChildFriendly": {
                        "type": "string",
                        "enum": [
                            "Sí",
                            "No"
                        ],
                        "description": "Si es adecuado para padres-hijos",
                        "能力项": "特定格式"
                    },
                    "isOutdoor": {
                        "type": "string",
                        "enum": [
                            "Sí",
                            "No"
                        ],
                        "description": "Si es un juego al aire libre",
                        "能力项": "特定格式"
                    },
                    "hasCulturalShow": {
                        "type": "string",
                        "enum": [
                            "Sí",
                            "No"
                        ],
                        "description": "Si incluye espectáculos culturales",
                        "能力项": "特定格式"
                    },
                    "hasHotSpring": {
                        "type": "string",
                        "enum": [
                            "Sí",
                            "No"
                        ],
                        "description": "Si tiene proyectos de aguas termales",
                        "能力项": "特定格式"
                    }
                },
                "required": [
                    "playName",
                    "briefDesc",
                    "location",
                    "startDate",
                    "endDate",
                    "detailDesc",
                    "price",
                    "issueTime",
                    "hasNightView",
                    "isParentChildFriendly",
                    "isOutdoor",
                    "hasCulturalShow",
                    "hasHotSpring"
                ]
            }
        },
        "sub_questions": [
            {
                "point_id": 0,
                "question": "Si cumple con el esquema",
                "rule": "SCHEMA:json_schema",
                "dep": [],
                "被依赖": false,
                "能力项": "JSON"
            }
        ]
    }
]